Workbook

Sheet 商品销售明细表
B1: 2026年商品销售明细表
G2: =SUBTOTAL(9,G4:G4065) -> 3651 | I2: =SUBTOTAL(9,I4:I4065) -> 2494481.5 | K2: =SUBTOTAL(9,K4:K4065) -> 2504870.2
A3: 月份 | B3: 发生日期 | C3: 销售单号 | D3: 编码 | E3: 商品型号 | F3: 客户单位 | G3: 数量 | H3: 单价 | I3: 金额 | J3: 税率 | K3: 含税金额 | L3: 收款分类 | M3: 公司
A4: 1月 | B4: 46027 | C4: 2328/2111 | D4: 2100002016998 | E4: 1500W-4 | F4: EQUIPODONTO ASSISTENCIA TECNICA ODONTOLOGICA LTDA | G4: 2 | H4: 1100 | I4: =G4*H4 -> 2200 | J4: 0.0325 | K4: =ROUND(I4+I4*J4,2) -> 2271.5 | M4: AR
A5: 1月 | B5: 46027 | C5: 2330/2112 | D5: 2100002017018 | E5: COMP 750W 220V | F5: WG ODONTO MANUTENCAO E ASSISTENCIA TECNICA LTDA | G5: 1 | H5: 534.84 | I5: =G5*H5 -> 534.84 | J5: 0.0325 | K5: =ROUND(I5+I5*J5,2) -> 552.22 | M5: AR
A6: 1月 | B6: 46027 | C6: 2332/2113 | D6: 2100002017001 | E6: COMP 550W 110V | F6: FELIPE MARTINIANO ASSUNCAO | G6: 1 | H6: 469.25 | I6: =G6*H6 -> 469.25 | J6: 0.0325 | K6: =ROUND(I6+I6*J6,2) -> 484.5 | M6: AR
A7: 1月 | B7: 46027 | C7: 2335/2114 | D7: 2100002017032 | E7: 1100 8L | F7: VRV FERRAMENTAS | G7: 1 | H7: 661 | I7: =G7*H7 -> 661 | K7: =ROUND(I7+I7*J7,2) -> 661 | M7: AR
A8: 1月 | B8: 46028 | C8: 2337/2116 | D8: 2100002017414 | E8: 配件 | F8: ODONTEK EQUIPAMENTOS ODONTOLOGICOS LTDA | G8: 1 | H8: 450 | I8: =G8*H8 -> 450 | K8: =ROUND(I8+I8*J8,2) -> 450 | M8: AR
A9: 1月 | B9: 46028 | C9: 2337/2116 | D9: 2100002016639 | E9: 配件 | F9: ODONTEK EQUIPAMENTOS ODONTOLOGICOS LTDA | G9: 8 | H9: 15 | I9: =G9*H9 -> 120 | K9: =ROUND(I9+I9*J9,2) -> 120 | M9: AR
A10: 1月 | B10: 46028 | C10: 2329/2117 | D10: 2100002017049 | E10: 1100*2 50L | F10: FERRAGENS HOME HOUSE COM. DE EQUIP. E MAQUINAS LTDA | G10: 1 | H10: 1524 | I10: =G10*H10 -> 1524 | K10: =ROUND(I10+I10*J10,2) -> 1524 | M10: AR
A11: 1月 | B11: 46028 | C11: 2329/2117 | D11: 2100002017469 | E11: BM-1902 25L 127V | F11: FERRAGENS HOME HOUSE COM. DE EQUIP. E MAQUINAS LTDA | G11: 1 | H11: 640 | I11: =G11*H11 -> 640 | K11: =ROUND(I11+I11*J11,2) -> 640 | M11: AR
A12: 1月 | B12: 46028 | C12: 2329/2117 | D12: 2100002016776 | E12: 1200- 8L | F12: FERRAGENS HOME HOUSE COM. DE EQUIP. E MAQUINAS LTDA | G12: 2 | H12: 714.57 | I12: =G12*H12 -> 1429.14 | K12: =ROUND(I12+I12*J12,2) -> 1429.14 | M12: AR
A13: 1月 | B13: 46028 | C13: 2329/2117 | D13: 2100002016752 | E13: 1200 25L | F13: FERRAGENS HOME HOUSE COM. DE EQUIP. E MAQUINAS LTDA | G13: 1 | H13: 902.39 | I13: =G13*H13 -> 902.39 | K13: =ROUND(I13+I13*J13,2) -> 902.39 | M13: AR
A14: 1月 | B14: 46028 | C14: 2343/2119 | D14: 2100002017018 | E14: COMP 750W 220V | F14: THIAGO LOURENCO DO AMARAL | G14: 2 | H14: 603.2 | I14: =G14*H14 -> 1206.4 | K14: =ROUND(I14+I14*J14,2) -> 1206.4 | M14: AR
A15: 1月 | B15: 46028 | C15: 2344/2120 | D15: 2100002017414 | E15: 配件 | F15: JEFERSON ANTONIO PEREIRA ----1100 -220 V | G15: 1 | H15: 400 | I15: =G15*H15 -> 400 | K15: =ROUND(I15+I15*J15,2) -> 400 | M15: AR
A16: 1月 | B16: 46028 | C16: 2334/2121 | D16: 2100002016615 | E16: 1500W-2 | F16: PROTEC COMERCIO E MANUTENCAO DE EQUIPAMENTOS DE SAUDE LTDA | G16: 6 | H16: 639 | I16: =G16*H16 -> 3834 | K16: =ROUND(I16+I16*J16,2) -> 3834 | M16: AR
A17: 1月 | B17: 46028 | C17: 2334/2121 | D17: 2100002016752 | E17: 1200 25L | F17: PROTEC COMERCIO E MANUTENCAO DE EQUIPAMENTOS DE SAUDE LTDA | G17: 1 | H17: 902.39 | I17: =G17*H17 -> 902.39 | K17: =ROUND(I17+I17*J17,2) -> 902.39 | M17: AR
A18: 1月 | B18: 46028 | C18: 2342/2122 | D18: 2100002017018 | E18: COMP 750W 220V | F18: WG ODONTO MANUTENCAO E ASSISTENCIA TECNICA LTDA | G18: 1 | H18: 534.84 | I18: 534.84 | J18: 0.0325 | K18: =ROUND(I18+I18*J18,2) -> 552.22 | M18: AR
A19: 1月 | B19: 46029 | C19: 2345/2123 | D19: 2100002017032 | E19: 1100 8L | F19: PALACIO DAS FERRAMENTAS E PARAFUSOS LTDA | G19: 20 | H19: 659 | I19: =G19*H19 -> 13180 | K19: =ROUND(I19+I19*J19,2) -> 13180 | M19: AR
A20: 1月 | B20: 46029 | C20: 2347/2124 | D20: 2100002016776 | E20: 1200- 8L | F20: FERRAGENS HOME HOUSE COM. DE EQUIP. E MAQUINAS LTDA | G20: 6 | H20: 714.57 | I20: =G20*H20 -> 4287.42 | K20: =ROUND(I20+I20*J20,2) -> 4287.42 | M20: AR
A21: 1月 | B21: 46029 | C21: 2350/2125 | D21: 2100002017490 | E21: 1500W-4 | F21: FRANCISCO NORBERTO DA SILVA | G21: 1 | H21: 1058 | I21: =G21*H21 -> 1058 | K21: =ROUND(I21+I21*J21,2) -> 1058 | M21: AR
A22: 1月 | B22: 46029 | C22: 2341/2126 | D22: 2100002017148 | E22: 1500W-4 | F22: ASSISTECDONTO LTDA | G22: 2 | H22: 1058 | I22: =G22*H22 -> 2116 | J22: 0.0325 | K22: =ROUND(I22+I22*J22,2) -> 2184.77 | M22: AR
A23: 1月 | B23: 46029 | C23: 2341/2126 | D23: 2100002016875 | E23: USK-750W | F23: ASSISTECDONTO LTDA | G23: 4 | H23: 632 | I23: =G23*H23 -> 2528 | J23: 0.0325 | K23: =ROUND(I23+I23*J23,2) -> 2610.16 | M23: AR
A24: 1月 | B24: 46029 | C24: 2341/2126 | D24: 2100002017216 | E24: 配件 | F24: ASSISTECDONTO LTDA | G24: 10 | H24: 20 | I24: =G24*H24 -> 200 | K24: =ROUND(I24+I24*J24,2) -> 200 | M24: AR
A25: 1月 | B25: 46029 | C25: 2341/2126 | D25: 2100002016639 | E25: 配件 | F25: ASSISTECDONTO LTDA | G25: 6 | H25: 60 | I25: =G25*H25 -> 360 | K25: =ROUND(I25+I25*J25,2) -> 360 | M25: AR
A26: 1月 | B26: 46030 | C26: 2352/2127 | D26: 2100002017032 | E26: 1100 8L | F26: VT FERRAMENTAS LTDA | G26: 1 | H26: 665 | I26: =G26*H26 -> 665 | K26: =ROUND(I26+I26*J26,2) -> 665 | M26: AR
A27: 1月 | B27: 46030 | C27: 2349/2128 | D27: 2100002016936 | E27: 1500 50L | F27: MP2 MAQUINAS E FERRAMENTAS LTDA | G27: 1 | H27: 1694 | I27: =G27*H27 -> 1694 | J27: 0.0325 | K27: =ROUND(I27+I27*J27,2) -> 1749.06 | M27: AR
A28: 1月 | B28: 46030 | C28: 2346/2129 | D28: 2100002017483 | E28: 750-25L | F28: GALLARDO COMERCIO DE EQUIPAMENTOS ODONTO MEDICOS LTDA | G28: 5 | H28: 846 | I28: =G28*H28 -> 4230 | K28: =ROUND(I28+I28*J28,2) -> 4230 | M28: AR
A29: 1月 | B29: 46030 | C29: 2346/2129 | D29: 2100002017476 | E29: 550*2-50L | F29: GALLARDO COMERCIO DE EQUIPAMENTOS ODONTO MEDICOS LTDA | G29: 1 | H29: 1685 | I29: =G29*H29 -> 1685 | K29: =ROUND(I29+I29*J29,2) -> 1685 | M29: AR
A30: 1月 | B30: 46030 | C30: 2346/2129 | D30: 2100002017049 | E30: 1100*2 50L | F30: GALLARDO COMERCIO DE EQUIPAMENTOS ODONTO MEDICOS LTDA | G30: 1 | H30: 1524 | I30: =G30*H30 -> 1524 | K30: =ROUND(I30+I30*J30,2) -> 1524 | M30: AR
A31: 1月 | B31: 46030 | C31: 2357/2130 | D31: 2100002017414 | E31: 配件 | F31: CARVALHO MARMORES E GRANITOS LTDA | G31: 2 | H31: 15 | I31: =G31*H31 -> 30 | K31: =ROUND(I31+I31*J31,2) -> 30 | M31: AR
A32: 1月 | B32: 46030 | C32: 2357/2130 | D32: 2100002017414 | E32: 配件 | F32: CARVALHO MARMORES E GRANITOS LTDA | G32: 2 | H32: 40 | I32: =G32*H32 -> 80 | K32: =ROUND(I32+I32*J32,2) -> 80 | M32: AR
A33: 1月 | B33: 46030 | C33: 2357/2130 | D33: 2100002017414 | E33: 配件 | F33: CARVALHO MARMORES E GRANITOS LTDA | G33: 2 | H33: 10 | I33: =G33*H33 -> 20 | K33: =ROUND(I33+I33*J33,2) -> 20 | M33: AR
A34: 1月 | B34: 46030 | C34: 2357/2130 | D34: 2100002017414 | E34: 配件 | F34: CARVALHO MARMORES E GRANITOS LTDA | G34: 1 | H34: 80 | I34: =G34*H34 -> 80 | K34: =ROUND(I34+I34*J34,2) -> 80 | M34: AR
A35: 1月 | B35: 46030 | C35: 2354/2131 | D35: 2100002017483 | E35: 750-25L | F35: FERRAGENS HOME HOUSE COM. DE EQUIP. E MAQUINAS LTDA | G35: 1 | H35: 846 | I35: =G35*H35 -> 846 | K35: =ROUND(I35+I35*J35,2) -> 846 | M35: AR
A36: 1月 | B36: 46030 | C36: 2354/2131 | D36: 2100002017469 | E36: BM-1902 25L 127V | F36: FERRAGENS HOME HOUSE COM. DE EQUIP. E MAQUINAS LTDA | G36: 2 | H36: 640 | I36: =G36*H36 -> 1280 | K36: =ROUND(I36+I36*J36,2) -> 1280 | M36: AR
A37: 1月 | B37: 46030 | C37: 2356/2132 | D37: 2100002016998 | E37: 1500W-4 | F37: KLM LTDA | G37: 1 | H37: 1063.92 | I37: =G37*H37 -> 1063.92 | J37: 0.0325 | K37: =ROUND(I37+I37*J37,2) -> 1098.5 | M37: AR
A38: 1月 | B38: 46030 | C38: 2358/2133 | D38: 2100002017483 | E38: 750-25L | F38: DENTAL TEC COMERCIO E SERVICOS LTDA | G38: 2 | H38: 846 | I38: =G38*H38 -> 1692 | K38: =ROUND(I38+I38*J38,2) -> 1692 | M38: AR
A39: 1月 | B39: 46030 | C39: 2358/2133 | D39: 2100002017476 | E39: 550*2-50L | F39: DENTAL TEC COMERCIO E SERVICOS LTDA | G39: 1 | H39: 1685 | I39: =G39*H39 -> 1685 | K39: =ROUND(I39+I39*J39,2) -> 1685 | M39: AR
A40: 1月 | B40: 46030 | C40: 2338/2134 | D40: 2100002017193 | E40: BM-1902-25L 220V | F40: LOJAO DAS FERRAMENTAS LTDA | G40: 2 | H40: 642 | I40: =G40*H40 -> 1284 | K40: =ROUND(I40+I40*J40,2) -> 1284 | M40: AR
A41: 1月 | B41: 46030 | C41: 2311/2135 | D41: 2100002017179 | E41: E71T-GS 1KG 0.8MM | F41: J C NEPOMUCENO FERRAMENTAS | G41: 20 | H41: 27.29 | I41: =G41*H41 -> 545.8 | J41: 0.0325 | K41: =ROUND(I41+I41*J41,2) -> 563.54 | M41: AR
A42: 1月 | B42: 46030 | C42: 2353/2136 | D42: 2100002017049 | E42: 1100*2 50L | F42: EQUIPAR PRODUTOS MEDICOS HOSPITALARES LTDA | G42: 3 | H42: 1524 | I42: =G42*H42 -> 4572 | K42: =ROUND(I42+I42*J42,2) -> 4572 | M42: AR
A43: 1月 | B43: 46030 | C43: 2365/2137 | D43: 2100002017452 | E43: 1200*2-50L | F43: RUBENS DE ALMEIDA GIL | G43: 1 | H43: 1498 | I43: =G43*H43 -> 1498 | K43: =ROUND(I43+I43*J43,2) -> 1498 | M43: AR
A44: 1月 | B44: 46030 | C44: 2370/2141 | D44: 2100002017476 | E44: 550*2-50L | F44: TECNODONTO LTDA | G44: 1 | H44: 1685 | I44: =G44*H44 -> 1685 | K44: =ROUND(I44+I44*J44,2) -> 1685 | M44: AR
A45: 1月 | B45: 46030 | C45: 2364/2142 | D45: 2100002017230 | E45: 1200*2-50L | F45: FERRAGENS HOME HOUSE COM. DE EQUIP. E MAQUINAS LTDA | G45: 1 | H45: 1498 | I45: =G45*H45 -> 1498 | K45: =ROUND(I45+I45*J45,2) -> 1498 | M45: AR
A46: 1月 | B46: 46030 | C46: 2361/2144 | D46: 2100002017483 | E46: 750-25L | F46: R C NEPOMUCENO FERRAMENTAS | G46: 3 | H46: 852.9 | I46: =G46*H46 -> 2558.7 | K46: =ROUND(I46+I46*J46,2) -> 2558.7 | M46: AR
A47: 1月 | B47: 46031 | C47: 2375/2145 | D47: 2100002017032 | E47: 1100 8L | F47: GENIOBOX COMERCIAL LTDA | G47: 1 | H47: 660 | I47: =G47*H47 -> 660 | K47: =ROUND(I47+I47*J47,2) -> 660 | M47: AR
A48: 1月 | B48: 46031 | C48: 2376/2146 | D48: 2100002017032 | E48: 1100 8L | F48: GENIOBOX COMERCIAL LTDA | G48: 1 | H48: 660 | I48: =G48*H48 -> 660 | K48: =ROUND(I48+I48*J48,2) -> 660 | M48: AR
A49: 1月 | B49: 46034 | C49: 2378/2148 | D49: 2100002017292 | E49: BM-1902 25L | F49: FERRAGENS HOME HOUSE COM. DE EQUIP. E MAQUINAS LTDA | G49: 1 | H49: 640 | I49: =G49*H49 -> 640 | K49: =ROUND(I49+I49*J49,2) -> 640 | M49: AR
A50: 1月 | B50: 46034 | C50: 2378/2148 | D50: 2100002017469 | E50: BM-1902 25L 127V | F50: FERRAGENS HOME HOUSE COM. DE EQUIP. E MAQUINAS LTDA | G50: 2 | H50: 640 | I50: =G50*H50 -> 1280 | K50: =ROUND(I50+I50*J50,2) -> 1280 | M50: AR
A51: 1月 | B51: 46034 | C51: 2378/2148 | D51: 2100002016752 | E51: 1200 25L | F51: FERRAGENS HOME HOUSE COM. DE EQUIP. E MAQUINAS LTDA | G51: 1 | H51: 902.39 | I51: =G51*H51 -> 902.39 | K51: =ROUND(I51+I51*J51,2) -> 902.39 | M51: AR
A52: 1月 | B52: 46034 | C52: 2378/2148 | D52: 2100002016776 | E52: 1200- 8L | F52: FERRAGENS HOME HOUSE COM. DE EQUIP. E MAQUINAS LTDA | G52: 2 | H52: 640 | I52: =G52*H52 -> 1280 | K52: =ROUND(I52+I52*J52,2) -> 1280 | M52: AR
A53: 1月 | B53: 46034 | C53: 2373/2149 | D53: 2100002017278 | E53: 配件 | F53: CLEYTON FRANCELLINO BARROS | G53: 4 | H53: 27 | I53: =G53*H53 -> 108 | K53: =ROUND(I53+I53*J53,2) -> 108 | M53: AR
... A64: 1月 | B64: 46035 | C64: 2383/2156 | D64: 2100002017292 | E64: BM-1902 25L | F64: FERRAGENS HOME HOUSE COM. DE EQUIP. E MAQUINAS LTDA | G64: 2 | H64: 640 | I64: =G64*H64 -> 1280 | K64: =ROUND(I64+I64*J64,2) -> 1280 | M64: AR
A65: 1月 | B65: 46035 | C65: 21434/2157 | D65: 2100002017018 | E65: COMP 750W 220V | F65: SYCOW MED ODONTO IND.COM.SERV LTDA | G65: 1 | H65: 534.84 | I65: =G65*H65 -> 534.84 | J65: 0.0325 | K65: =ROUND(I65+I65*J65,2) -> 552.22 | M65: AR
A66: 1月 | B66: 46035 | C66: 2395/2158 | D66: 2100002017452 | E66: 1200*2-50L | F66: SABINO ASSISTENCIA TECNICA ODONTOLOGICA LTDA | G66: 2 | H66: 1648 | I66: =G66*H66 -> 3296 | K66: =ROUND(I66+I66*J66,2) -> 3296 | M66: AR
A67: 1月 | B67: 46035 | C67: 2396/2159 | D67: 2100002016998 | E67: 1500W-4 | F67: RC ODONTO LTDA | G67: 1 | H67: 1058 | I67: =G67*H67 -> 1058 | J67: 0.0325 | K67: =ROUND(I67+I67*J67,2) -> 1092.39 | M67: AR
A68: 1月 | B68: 46035 | C68: 2384/2160 | D68: 2100002017254 | E68: 1500 - 50L | F68: ANA CATARINA GOMES | G68: 1 | H68: 1694.45 | I68: =G68*H68 -> 1694.45 | K68: =ROUND(I68+I68*J68,2) -> 1694.45 | M68: AR
A69: 1月 | B69: 46035 | C69: 2384/2160 | D69: 2100002016998 | E69: 1500W-4 | F69: ANA CATARINA GOMES | G69: 1 | H69: 1058 | I69: =G69*H69 -> 1058 | J69: 0.0325 | K69: =ROUND(I69+I69*J69,2) -> 1092.39 | M69: AR
A70: 1月 | B70: 46035 | C70: 2381/2162 | D70: 2100002017254 | E70: 1500 - 50L | F70: GILBERTO ALVES REPRESENTACOES COMERCIAIS LTDA | G70: 1 | H70: 1694.45 | I70: =G70*H70 -> 1694.45 | K70: =ROUND(I70+I70*J70,2) -> 1694.45 | M70: AR
A71: 1月 | B71: 46035 | C71: 2394/2163 | D71: 2100002017513 | E71: 750-25L | F71: R C NEPOMUCENO FERRAMENTAS | G71: 5 | H71: 852.9 | I71: =G71*H71 -> 4264.5 | K71: =ROUND(I71+I71*J71,2) -> 4264.5 | M71: AR
A72: 1月 | B72: 46035 | C72: 2394/2163 | D72: 2100002017032 | E72: 1100 8L | F72: R C NEPOMUCENO FERRAMENTAS | G72: 2 | H72: 664.58 | I72: =G72*H72 -> 1329.16 | K72: =ROUND(I72+I72*J72,2) -> 1329.16 | M72: AR
A73: 1月 | B73: 46036 | C73: 2406/2164 | D73: 2100002017049 | E73: 1100*2 50L | F73: DENTAL SAO CRISTOVAO LTDA | G73: 2 | H73: 1530 | I73: =G73*H73 -> 3060 | K73: =ROUND(I73+I73*J73,2) -> 3060 | M73: AR
A74: 1月 | B74: 46036 | C74: 2405/2165 | D74: 2100002017452 | E74: 1200*2-50L | F74: APIAGRO LTDA | G74: 5 | H74: 1498 | I74: =G74*H74 -> 7490 | K74: =ROUND(I74+I74*J74,2) -> 7490 | M74: AR
A75: 1月 | B75: 46036 | C75: 2408/2166 | D75: 2100002017131 | E75: BM-1902 25L 127V | F75: GENIOBOX COMERCIAL LTDA | G75: 3 | H75: 640 | I75: =G75*H75 -> 1920 | K75: =ROUND(I75+I75*J75,2) -> 1920 | M75: AR
A76: 1月 | B76: 46036 | C76: 2404/2168 | D76: 2100002017049 | E76: 1100*2 50L | F76: FERRAGENS HOME HOUSE COM. DE EQUIP. E MAQUINAS LTDA | G76: 2 | H76: 1524 | I76: =G76*H76 -> 3048 | K76: =ROUND(I76+I76*J76,2) -> 3048 | M76: AR
A77: 1月 | B77: 46036 | C77: 2404/2168 | D77: 2100002017032 | E77: 1100 8L | F77: FERRAGENS HOME HOUSE COM. DE EQUIP. E MAQUINAS LTDA | G77: 5 | H77: 660 | I77: =G77*H77 -> 3300 | K77: =ROUND(I77+I77*J77,2) -> 3300 | M77: AR
A78: 1月 | B78: 46036 | C78: 2404/2168 | D78: 2100002016776 | E78: 1200- 8L | F78: FERRAGENS HOME HOUSE COM. DE EQUIP. E MAQUINAS LTDA | G78: 1 | H78: 714 | I78: =G78*H78 -> 714 | K78: =ROUND(I78+I78*J78,2) -> 714 | M78: AR
A79: 1月 | B79: 46036 | C79: 2404/2168 | D79: 2100002016752 | E79: 1200 25L | F79: FERRAGENS HOME HOUSE COM. DE EQUIP. E MAQUINAS LTDA | G79: 1 | H79: 902 | I79: =G79*H79 -> 902 | K79: =ROUND(I79+I79*J79,2) -> 902 | M79: AR
A80: 1月 | B80: 46036 | C80: 2386/2171 | D80: 2100002017254 | E80: 1500 - 50L | F80: MED SYSTEM EQUIPAMENTOS LTDA | G80: 1 | H80: 1948.7 | I80: =G80*H80 -> 1948.7 | K80: =ROUND(I80+I80*J80,2) -> 1948.7 | M80: AR
A81: 1月 | B81: 46036 | C81: 2386/2171 | D81: 2100002017452 | E81: 1200*2-50L | F81: MED SYSTEM EQUIPAMENTOS LTDA | G81: 1 | H81: 1648 | I81: =G81*H81 -> 1648 | K81: =ROUND(I81+I81*J81,2) -> 1648 | M81: AR
A82: 1月 | B82: 46036 | C82: 2411/2172 | D82: 2100002016998 | E82: 1500W-4 | F82: OAK DENTAL LTDA | G82: 2 | H82: 1058 | I82: =G82*H82 -> 2116 | J82: 0.0325 | K82: =ROUND(I82+I82*J82,2) -> 2184.77 | M82: AR
A83: 1月 | B83: 46037 | C83: 2418/2173 | D83: 2100002017513 | E83: 750-25L | F83: GALLARDO COMERCIO DE EQUIPAMENTOS ODONTO MEDICOS LTDA | G83: 12 | H83: 840 | I83: =G83*H83 -> 10080 | K83: =ROUND(I83+I83*J83,2) -> 10080 | M83: AR
A84: 1月 | B84: 46037 | C84: 2413/2174 | D84: 2100002017254 | E84: 1500 - 50L | F84: E F DA S SANTOS | G84: 1 | H84: 1694.45 | I84: =G84*H84 -> 1694.45 | K84: =ROUND(I84+I84*J84,2) -> 1694.45 | M84: AR
A85: 1月 | B85: 46037 | C85: 2413/2174 | D85: 2100002017476 | E85: 550*2-50L | F85: E F DA S SANTOS | G85: 1 | H85: 1685 | I85: =G85*H85 -> 1685 | K85: =ROUND(I85+I85*J85,2) -> 1685 | M85: AR
A86: 1月 | B86: 46037 | C86: 2414/2175 | D86: 2100002017513 | E86: 750-25L | F86: LUIS BARBOSA DOS SANTOS | G86: 1 | H86: 900 | I86: =G86*H86 -> 900 | K86: =ROUND(I86+I86*J86,2) -> 900 | M86: AR
A87: 1月 | B87: 46037 | C87: 2412/2176 | D87: 2100002016998 | E87: 1500W-4 | F87: J.C DE S.MAGALHAES | G87: 1 | H87: 1058 | I87: =G87*H87 -> 1058 | J87: 0.0325 | K87: =ROUND(I87+I87*J87,2) -> 1092.39 | M87: AR
A88: 1月 | B88: 46037 | C88: 2415/2177 | D88: 2100002017032 | E88: 1100 8L | F88: FERRAGENS HOME HOUSE COM. DE EQUIP. E MAQUINAS LTDA | G88: 2 | H88: 660 | I88: =G88*H88 -> 1320 | K88: =ROUND(I88+I88*J88,2) -> 1320 | M88: AR
A89: 1月 | B89: 46037 | C89: 2415/2177 | D89: 0002 | E89: E71T-GS 1KG 1MM | F89: FERRAGENS HOME HOUSE COM. DE EQUIP. E MAQUINAS LTDA | G89: 20 | H89: 27.29 | I89: =G89*H89 -> 545.8 | J89: 0.0325 | K89: =ROUND(I89+I89*J89,2) -> 563.54 | M89: AR
A90: 1月 | B90: 46037 | C90: 2419/2178 | D90: 2100002017513 | E90: 750-25L | F90: ULTRA HD EQUIPAMENTOS E CONSULTORIA ODONTOMEDICA LTDA | G90: 5 | H90: 846 | I90: =G90*H90 -> 4230 | K90: =ROUND(I90+I90*J90,2) -> 4230 | M90: AR
A91: 1月 | B91: 46037 | C91: 2419/2178 | D91: 2100002017209 | E91: 550*2-50L | F91: ULTRA HD EQUIPAMENTOS E CONSULTORIA ODONTOMEDICA LTDA | G91: 3 | H91: 1685 | I91: =G91*H91 -> 5055 | K91: =ROUND(I91+I91*J91,2) -> 5055 | M91: AR
A92: 1月 | B92: 46037 | C92: 2422/2179 | D92: 2100002017513 | E92: 750-25L | F92: GENIOBOX COMERCIAL LTDA | G92: 2 | H92: 846 | I92: =G92*H92 -> 1692 | K92: =ROUND(I92+I92*J92,2) -> 1692 | M92: AR
A93: 1月 | B93: 46037 | C93: 2422/2179 | D93: 2100002017469 | E93: BM-1902 25L 127V | F93: GENIOBOX COMERCIAL LTDA | G93: 2 | H93: 640 | I93: =G93*H93 -> 1280 | K93: =ROUND(I93+I93*J93,2) -> 1280 | M93: AR
A94: 1月 | B94: 46037 | C94: 2417/2180 | D94: 2100002016998 | E94: 1500W-4 | F94: PROJETCOMP MANUTENCAO INDUSTRIAL LTDA | G94: 2 | H94: 1058 | I94: =G94*H94 -> 2116 | J94: 0.0325 | K94: =ROUND(I94+I94*J94,2) -> 2184.77 | M94: AR
A95: 1月 | B95: 46037 | C95: 2430/2183 | D95: 2100002017513 | E95: 750-25L | F95: COLUMBIA COMERCIAL DE EQUIPAMENTOS LTDA | G95: 22 | H95: 818.19 | I95: =G95*H95 -> 18000.18 | K95: =ROUND(I95+I95*J95,2) -> 18000.18 | M95: AR
A96: 1月 | B96: 46037 | C96: 2429/2184 | D96: 2100002016608 | E96: 1200W-2 | F96: FELIPE DOS ANJOS SEIXAS | G96: 1 | H96: 600 | I96: =G96*H96 -> 600 | K96: =ROUND(I96+I96*J96,2) -> 600 | M96: AR
A97: 1月 | B97: 46037 | C97: 2434/2185 | D97: 2100002017018 | E97: COMP 750W 220V | F97: TEK ODONTO LTDA | G97: 1 | H97: 534.84 | I97: =G97*H97 -> 534.84 | J97: 0.0325 | K97: =ROUND(I97+I97*J97,2) -> 552.22 | M97: AR
A98: 1月 | B98: 46038 | C98: 2410/2186 | D98: 2100002017469 | E98: BM-1902 25L 127V | F98: FERRAGENS HOME HOUSE COM. DE EQUIP. E MAQUINAS LTDA | G98: 20 | H98: 640 | I98: =G98*H98 -> 12800 | K98: =ROUND(I98+I98*J98,2) -> 12800 | M98: AR
A99: 1月 | B99: 46038 | C99: 2410/2186 | D99: 2100002017292 | E99: BM-1902 25L | F99: FERRAGENS HOME HOUSE COM. DE EQUIP. E MAQUINAS LTDA | G99: 20 | H99: 640 | I99: =G99*H99 -> 12800 | K99: =ROUND(I99+I99*J99,2) -> 12800 | M99: AR
A100: 1月 | B100: 46038 | C100: 2437/2187 | D100: 2100002017476 | E100: 550*2-50L | F100: DANIEL GRILLO RIBEIRO | G100: 1 | H100: 1685 | I100: =G100*H100 -> 1685 | K100: =ROUND(I100+I100*J100,2) -> 1685 | M100: AR
A101: 1月 | B101: 46038 | C101: 2439/2188 | D101: 2100002017254 | E101: 1500 - 50L | F101: SIDNEI MONTEIRO | G101: 1 | H101: 1694.45 | I101: =G101*H101 -> 1694.45 | K101: =ROUND(I101+I101*J101,2) -> 1694.45 | M101: AR
A102: 1月 | B102: 46038 | C102: 2416/2189 | D102: 2100002017292 | E102: BM-1902 25L | F102: EMPORIO DAS FERRAMENTAS AUTOMOTIVOS LTDA | G102: 3 | H102: 640 | I102: =G102*H102 -> 1920 | K102: =ROUND(I102+I102*J102,2) -> 1920 | M102: AR
A103: 1月 | B103: 46038 | C103: 2436/2190 | D103: 2100002017513 | E103: 750-25L | F103: L. DE OLIVEIRA CONSERTOS DE MAQUINAS E COMERCIO DE FERRAMENT | G103: 6 | H103: 820 | I103: =G103*H103 -> 4920 | K103: =ROUND(I103+I103*J103,2) -> 4920 | M103: AR
A104: 1月 | B104: 46038 | C104: 2436/2190 | D104: 2100002017476 | E104: 550*2-50L | F104: L. DE OLIVEIRA CONSERTOS DE MAQUINAS E COMERCIO DE FERRAMENT | G104: 2 | H104: 1685 | I104: =G104*H104 -> 3370 | K104: =ROUND(I104+I104*J104,2) -> 3370 | M104: AR
A105: 1月 | B105: 46038 | C105: 2435/2191 | D105: 2100002017018 | E105: COMP 750W 220V | F105: LUIS ANTONIO MODENA | G105: 3 | H105: 615.07 | I105: =G105*H105 -> 1845.21 | J105: 0.0325 | K105: =ROUND(I105+I105*J105,2) -> 1905.18 | M105: AR
A106: 1月 | B106: 46038 | C106: 2435/2191 | D106: 2100002016998 | E106: 1500W-4 | F106: LUIS ANTONIO MODENA | G106: 2 | H106: 1217 | I106: =G106*H106 -> 2434 | J106: 0.0325 | K106: =ROUND(I106+I106*J106,2) -> 2513.11 | M106: AR
A107: 1月 | B107: 46038 | C107: 2440/2192 | D107: 2100002017018 | E107: COMP 750W 220V | F107: LUIZ CARLOS DE ARAUJO | G107: 4 | H107: 535 | I107: =G107*H107 -> 2140 | K107: =ROUND(I107+I107*J107,2) -> 2140 | M107: AR
A108: 1月 | B108: 46038 | C108: 2445/2193 | D108: 2100002017032 | E108: 1100 8L | F108: GENIOBOX COMERCIAL LTDA | G108: 1 | H108: 660.39 | I108: =G108*H108 -> 660.39 | K108: =ROUND(I108+I108*J108,2) -> 660.39 | M108: AR
A109: 1月 | B109: 46038 | C109: 2448/2194 | D109: 2100002017452 | E109: 1200*2-50L | F109: OAK DENTAL LTDA | G109: 1 | H109: 1498 | I109: =G109*H109 -> 1498 | K109: =ROUND(I109+I109*J109,2) -> 1498 | M109: AR
A110: 1月 | B110: 46038 | C110: 2444/2195 | D110: 2100002017537 | E110: BM-1902-50L 127V E | F110: PALACIO DAS FERRAMENTAS E PARAFUSOS LTDA | G110: 28 | H110: 916.56 | I110: =G110*H110 -> 25663.68 | K110: =ROUND(I110+I110*J110,2) -> 25663.68 | M110: AR
...

Sheet 主营业务收入汇总
A1: 2026年度主营业务收入汇总表 | Q1: 2026年度主营业务收入汇总表
D2: =D6+D7-D8-D9-D10 -> 0.01 | E2: =E6+E7-E8-E9-E10 -> 0 | F2: =F6+F7-F8-F9-F10 -> 0 | G2: =G6+G7-G8-G9-G10 -> 0.02 | H2: =H6+H7-H8-H9-H10 -> -0.01 | I2: =I6+I7-I8-I9-I10 -> -0.01 | J2: =J6+J7-J8-J9-J10 -> 0.01 | K2: =K6+K7-K8-K9-K10 -> 0 | ... P2: =P6+P7-P8-P9-P10 -> -0.01 | Q2: =SUM(J6:J7) -> 0 | AD2: =903577.57-5980 -> 897597.57
A3: 金额单位：元 | Q3: 金额单位：雷亚尔 | R3: 1.289 | S3: 1.3247 | T3: 1.341
A4: 月份 | C4: 科目 | D4: 合计 | E4: 1月 | F4: 2月 | G4: 3月 | H4: 4月 | I4: 5月 | J4: 6月 | K4: 7月 | L4: 8月 | M4: 9月 | N4: 10月 | O4: 11月 | P4: 12月 | Q4: 合计 | R4: 1月 | S4: 2月 | T4: 3月 | U4: 4月 | V4: 5月 | W4: 6月 | X4: 7月 | Y4: 8月 | Z4: 9月 | AA4: 10月 | AB4: 11月 | AC4: 12月
A5: 企业
A6: 总计 | C6: 主营业务收入 | D6: =SUM(E6:P6) -> 3265169.6 | E6: =E11+E16+E21+E26+E31+E36+E41 -> 1776835.5 | F6: =F11+F16+F21+F26+F31+F36+F41 -> 1488334.1 | G6: =G11+G16+G21+G26+G31+G36+G41 -> 0 | H6: =H11+H16+H21+H26+H31+H36+H41 -> 0 | I6: =I11+I16+I21+I26+I31+I36+I41 -> 0 | J6: =J11+J16+J21+J26+J31+J36+J41 -> 0 | K6: =K11+K16+K21+K26+K31+K36+K41 -> 0 | L6: =L11+L16+L21+L26+L31+L36+L41 -> 0 | ... P6: =P11+P16+P21+P26+P31+P36+P41 -> 0 | Q6: =SUM(R6:AC6) -> 2501985.8 | R6: =R11+R16+R21+R26+R31+R36+R41 -> 1378460.4 | S6: =S11+S16+S21+S26+S31+S36+S41 -> 1123525.4 | T6: =T11+T16+T21+T26+T31+T36+T41 -> 0 | U6: =U11+U16+U21+U26+U31+U36+U41 -> 0 | V6: =V11+V16+V21+V26+V31+V36+V41 -> 0 | W6: =W11+W16+W21+W26+W31+W36+W41 -> 0 | X6: =X11+X16+X21+X26+X31+X36+X41 -> 0 | Y6: =Y11+Y16+Y21+Y26+Y31+Y36+Y41 -> 0 | Z6: =Z11+Z16+Z21+Z26+Z31+Z36+Z41 -> 0 | AA6: =AC11+AC16+AC21+AC26+AC31+AC36+AC41 -> 0 | AB6: =AB11+AB16+AB21+AB26+AB31+AB36+AB41 -> 0 | AC6: =AC11+AC16+AC21+AC26+AC31+AC36+AC41 -> 0 | AD6: =S6+S7 -> 1124862.7 | AE6: =F6+F7 -> 1490105.6 | AF6: =Y6+Y7 -> 0
A7: 总计 | C7: 财务费用--刷卡费 | D7: =SUM(E7:P7) -> 3836.84 | E7: =E12+E17+E22+E27+E32+E37+E42 -> 2065.3 | F7: =F12+F17+F22+F27+F32+F37+F42 -> 1771.54 | G7: =G12+G17+G22+G27+G32+G37+G42 -> 0 | H7: =H12+H17+H22+H27+H32+H37+H42 -> 0 | I7: =I12+I17+I22+I27+I32+I37+I42 -> 0 | J7: =J12+J17+J22+J27+J32+J37+J42 -> 0 | K7: =K12+K17+K22+K27+K32+K37+K42 -> 0 | L7: =L12+L17+L22+L27+L32+L37+L42 -> 0 | ... P7: =P12+P17+P22+P27+P32+P37+P42 -> 0 | Q7: =SUM(R7:AC7) -> 2939.5642 | R7: =R12+R17+R22+R27+R32+R37+R42 -> 1602.25 | S7: =S12+S17+S22+S27+S32+S37+S42 -> 1337.3142 | T7: =T12+T17+T22+T27+T32+T37+T42 -> 0 | U7: =U12+U17+U22+U27+U32+U37+U42 -> 0 | V7: =V12+V17+V22+V27+V32+V37+V42 -> 0 | W7: =W12+W17+W22+W27+W32+W37+W42 -> 0 | X7: =X12+X17+X22+X27+X32+X37+X42 -> 0 | Y7: =Y12+Y17+Y22+Y27+Y32+Y37+Y42 -> 0 | Z7: =Z12+Z17+Z22+Z27+Z32+Z37+Z42 -> 0 | AA7: =AC12+AC17+AC22+AC27+AC32+AC37+AC42 -> 0 | AB7: =AB12+AB17+AB22+AB27+AB32+AB37+AB42 -> 0 | AC7: =AC12+AC17+AC22+AC27+AC32+AC37+AC42 -> 0
A8: 总计 | C8: 博莱多收款 | D8: =SUM(E8:P8) -> 1893079.6 | E8: =E13+E18+E23+E28+E33+E38+E43 -> 1016233.3 | F8: =F13+F18+F23+F28+F33+F38+F43 -> 876846.29 | G8: =G13+G18+G23+G28+G33+G38+G43 -> -0.01 | H8: =H13+H18+H23+H28+H33+H38+H43 -> 0 | I8: =I13+I18+I23+I28+I33+I38+I43 -> 0 | J8: =J13+J18+J23+J28+J33+J38+J43 -> 0 | K8: =K13+K18+K23+K28+K33+K38+K43 -> 0 | L8: =L13+L18+L23+L28+L33+L38+L43 -> 0 | ... P8: =P13+P18+P23+P28+P33+P38+P43 -> 0 | Q8: =SUM(R8:AC8) -> 1450309.6 | R8: =R13+R18+R23+R28+R33+R38+R43 -> 788388.94 | S8: =S13+S18+S23+S28+S33+S38+S43 -> 661920.65 | T8: =T13+T18+T23+T28+T33+T38+T43 -> 0 | U8: =U13+U18+U23+U28+U33+U38+U43 -> 0 | V8: =V13+V18+V23+V28+V33+V38+V43 -> 0 | W8: =W13+W18+W23+W28+W33+W38+W43 -> 0 | X8: =X13+X18+X23+X28+X33+X38+X43 -> 0 | Y8: =Y13+Y18+Y23+Y28+Y33+Y38+Y43 -> 0 | Z8: =Z13+Z18+Z23+Z28+Z33+Z38+Z43 -> 0 | AA8: =AC13+AC18+AC23+AC28+AC33+AC38+AC43 -> 0 | AB8: =AB13+AB18+AB23+AB28+AB33+AB38+AB43 -> 0 | AC8: =AC13+AC18+AC23+AC28+AC33+AC38+AC43 -> 0
A9: 总计 | C9: 刷卡收款 | D9: =SUM(E9:P9) -> 313698.19 | E9: =E14+E19+E24+E29+E34+E39+E44 -> 175650.41 | F9: =F14+F19+F24+F29+F34+F39+F44 -> 138047.78 | G9: =G14+G19+G24+G29+G34+G39+G44 -> -0.01 | H9: =H14+H19+H24+H29+H34+H39+H44 -> 0.01 | I9: =I14+I19+I24+I29+I34+I39+I44 -> 0.01 | J9: =J14+J19+J24+J29+J34+J39+J44 -> -0.01 | K9: =K14+K19+K24+K29+K34+K39+K44 -> 0 | L9: =L14+L19+L24+L29+L34+L39+L44 -> -0.01 | ... P9: =P14+P19+P24+P29+P34+P39+P44 -> 0.01 | Q9: =SUM(R9:AC9) -> 240479.33 | R9: =R14+R19+R24+R29+R34+R39+R44 -> 136268.73 | S9: =S14+S19+S24+S29+S34+S39+S44 -> 104210.6 | T9: =T14+T19+T24+T29+T34+T39+T44 -> 0 | U9: =U14+U19+U24+U29+U34+U39+U44 -> 0 | V9: =V14+V19+V24+V29+V34+V39+V44 -> 0 | W9: =W14+W19+W24+W29+W34+W39+W44 -> 0 | X9: =X14+X19+X24+X29+X34+X39+X44 -> 0 | Y9: =Y14+Y19+Y24+Y29+Y34+Y39+Y44 -> 0 | Z9: =Z14+Z19+Z24+Z29+Z34+Z39+Z44 -> 0 | AA9: =AC14+AC19+AC24+AC29+AC34+AC39+AC44 -> 0 | AB9: =AB14+AB19+AB24+AB29+AB34+AB39+AB44 -> 0 | AC9: =AC14+AC19+AC24+AC29+AC34+AC39+AC44 -> 0 | AD9: =S9-S7 -> 102873.29
A10: 总计 | C10: 现款-现金、银行存款 | D10: =SUM(E10:P10) -> 1062228.6 | E10: =E15+E20+E25+E30+E35+E40+E45 -> 587017.07 | F10: =F15+F20+F25+F30+F35+F40+F45 -> 475211.53 | G10: =G15+G20+G25+G30+G35+G40+G45 -> 0 | H10: =H15+H20+H25+H30+H35+H40+H45 -> 0 | I10: =I15+I20+I25+I30+I35+I40+I45 -> 0 | J10: =J15+J20+J25+J30+J35+J40+J45 -> 0 | K10: =K15+K20+K25+K30+K35+K40+K45 -> 0 | L10: =L15+L20+L25+L30+L35+L40+L45 -> 0 | ... P10: =P15+P20+P25+P30+P35+P40+P45 -> 0 | Q10: =SUM(R10:AC10) -> 814136.45 | R10: =R15+R20+R25+R30+R35+R40+R45 -> 455405.02 | S10: =S15+S20+S25+S30+S35+S40+S45 -> 358731.43 | T10: =T15+T20+T25+T30+T35+T40+T45 -> 0 | U10: =U15+U20+U25+U30+U35+U40+U45 -> 0 | V10: =V15+V20+V25+V30+V35+V40+V45 -> 0 | W10: =W15+W20+W25+W30+W35+W40+W45 -> 0 | X10: =X15+X20+X25+X30+X35+X40+X45 -> 0 | Y10: =Y15+Y20+Y25+Y30+Y35+Y40+Y45 -> 0 | Z10: =Z15+Z20+Z25+Z30+Z35+Z40+Z45 -> 0 | AA10: =AC15+AC20+AC25+AC30+AC35+AC40+AC45 -> 0 | AB10: =AB15+AB20+AB25+AB30+AB35+AB40+AB45 -> 0 | AC10: =AC15+AC20+AC25+AC30+AC35+AC40+AC45 -> 0
A11: ARGOTECH | B11: 阿家达 | C11: 主营业务收入 | D11: =SUM(E11:P11) -> 2861588.7 | E11: =ROUND(R11*$R$3,2) -> 1529653.4 | F11: =ROUND(S11*$S$3,2) -> 1331935.3 | G11: =ROUND(T11*$T$3,2) -> 0 | H11: =ROUND(U11*$U$3,2) -> 0 | I11: =ROUND(V11*V$3,2) -> 0 | J11: =ROUND(W11*W$3,2) -> 0 | K11: =ROUND(X11*X$3,2) -> 0 | L11: =ROUND(Y11*Y$3,2) -> 0 | M11: =ROUND(Z11*Z$3,2) -> 0 | N11: =ROUND(AC11*AC$3,2) -> 0 | O11: =ROUND(AB11*AB$3,2) -> 0 | P11: =ROUND(AC11*AC$3,2) -> 0 | Q11: =SUM(R11:AC11) -> 2192159.6 | R11: ='销售帐 -ARGOTECH'!$L390 -> 1186697.8 | S11: ='销售帐 -ARGOTECH'!$L691 -> 1005461.8 | T11: ='销售帐 -ARGOTECH'!$L798 -> 0 | U11: ='销售帐 -ARGOTECH'!$L993 -> 0 | V11: ='销售帐 -ARGOTECH'!$L1286 -> 0 | W11: ='销售帐 -ARGOTECH'!$L1615 -> 0 | X11: ='销售帐 -ARGOTECH'!$L1946 -> 0 | Y11: ='销售帐 -ARGOTECH'!$L2272 -> 0 | Z11: ='销售帐 -ARGOTECH'!$L2641 -> 0 | AA11: ='销售帐 -ARGOTECH'!$L3105 -> 0 | AB11: ='销售帐 -ARGOTECH'!$L3400 -> 0 | AC11: ='销售帐 -ARGOTECH'!$L3508 -> 0 | AD11: =S11+S12 -> 1006603.7 | AE11: =F11+F12 -> 1333447.9 | AF11: =Y11+Y12 -> 0
A12: ARGOTECH | B12: 阿家达 | C12: 财务费用--刷卡费 | D12: =SUM(E12:P12) -> 2991.32 | E12: =ROUND(R12*$R$3,2) -> 1478.74 | F12: =ROUND(S12*$S$3,2) -> 1512.58 | G12: =ROUND(T12*$T$3,2) -> 0 | H12: =ROUND(U12*$U$3,2) -> 0 | I12: =ROUND(V12*V$3,2) -> 0 | J12: =ROUND(W12*W$3,2) -> 0 | K12: =ROUND(X12*X$3,2) -> 0 | L12: =ROUND(Y12*Y$3,2) -> 0 | M12: =ROUND(Z12*Z$3,2) -> 0 | N12: =ROUND(AC12*AC$3,2) -> 0 | O12: =ROUND(AB12*AB$3,2) -> 0 | P12: =ROUND(AC12*AC$3,2) -> 0 | Q12: =SUM(R12:AC12) -> 2289.03 | R12: ='销售帐 -ARGOTECH'!$R390 -> 1147.2 | S12: ='销售帐 -ARGOTECH'!$R691 -> 1141.83 | T12: ='销售帐 -ARGOTECH'!$R798 -> 0 | U12: ='销售帐 -ARGOTECH'!$R993 -> 0 | V12: ='销售帐 -ARGOTECH'!$R1286 -> 0 | W12: ='销售帐 -ARGOTECH'!$R1615 -> 0 | X12: ='销售帐 -ARGOTECH'!$R1946 -> 0 | Y12: ='销售帐 -ARGOTECH'!$R2272 -> 0 | Z12: ='销售帐 -ARGOTECH'!$R2641 -> 0 | AA12: ='销售帐 -ARGOTECH'!$R3105 -> 0 | AB12: ='销售帐 -ARGOTECH'!$R3400 -> 0 | AC12: ='销售帐 -ARGOTECH'!$R3508 -> 0
A13: ARGOTECH | B13: 阿家达 | C13: 博莱多收款 | D13: =SUM(E13:P13) -> 1674833.6 | E13: =ROUND(R13*$R$3,2) -> 892598.28 | F13: =ROUND(S13*$S$3,2) -> 782235.31 | G13: =ROUND(T13*$T$3,2) -> 0 | H13: =ROUND(U13*$U$3,2) -> 0 | I13: =ROUND(V13*V$3,2) -> 0 | J13: =ROUND(W13*W$3,2) -> 0 | K13: =ROUND(X13*X$3,2) -> 0 | L13: =ROUND(Y13*Y$3,2) -> 0 | M13: =ROUND(Z13*Z$3,2) -> 0 | N13: =ROUND(AC13*AC$3,2) -> 0 | O13: =ROUND(AB13*AB$3,2) -> 0 | P13: =ROUND(AC13*AC$3,2) -> 0 | Q13: =SUM(R13:AC13) -> 1282973.4 | R13: ='销售帐 -ARGOTECH'!$O390 -> 692473.45 | S13: ='销售帐 -ARGOTECH'!$O691 -> 590499.97 | T13: ='销售帐 -ARGOTECH'!$O798 -> 0 | U13: ='销售帐 -ARGOTECH'!$O993 -> 0 | V13: ='销售帐 -ARGOTECH'!$O1286 -> 0 | W13: ='销售帐 -ARGOTECH'!$O1615 -> 0 | X13: ='销售帐 -ARGOTECH'!$O1946 -> 0 | Y13: ='销售帐 -ARGOTECH'!$O2272 -> 0 | Z13: ='销售帐 -ARGOTECH'!$O2641 -> 0 | AA13: ='销售帐 -ARGOTECH'!$O3105 -> 0 | AB13: ='销售帐 -ARGOTECH'!$O3400 -> 0 | AC13: ='销售帐 -ARGOTECH'!$O3508 -> 0
A14: ARGOTECH | B14: 阿家达 | C14: 刷卡收款 | D14: =SUM(E14:P14) -> 267979.78 | E14: =ROUND(R14*$R$3,2)+0.01 -> 141204.89 | F14: =ROUND(S14*$S$3,2) -> 126774.85 | G14: =ROUND(T14*$T$3,2)-0.01 -> -0.01 | H14: =ROUND(U14*$U$3,2)+0.01 -> 0.01 | I14: =ROUND(V14*V$3,2)+0.01 -> 0.01 | J14: =ROUND(W14*W$3,2) -> 0 | K14: =ROUND(X14*X$3,2) -> 0 | L14: =ROUND(Y14*Y$3,2)+0.01 -> 0.01 | M14: =ROUND(Z14*Z$3,2) -> 0 | N14: =ROUND(AC14*AC$3,2) -> 0 | O14: =ROUND(AB14*AB$3,2)+0.01 -> 0.01 | P14: =ROUND(AC14*AC$3,2)+0.01 -> 0.01 | Q14: =SUM(R14:AC14) -> 205246.87 | R14: ='销售帐 -ARGOTECH'!$P390 -> 109546.07 | S14: ='销售帐 -ARGOTECH'!$P691 -> 95700.8 | T14: ='销售帐 -ARGOTECH'!$P798 -> 0 | U14: ='销售帐 -ARGOTECH'!$P993 -> 0 | V14: ='销售帐 -ARGOTECH'!$P1286 -> 0 | W14: ='销售帐 -ARGOTECH'!$P1615 -> 0 | X14: ='销售帐 -ARGOTECH'!$P1946 -> 0 | Y14: ='销售帐 -ARGOTECH'!$P2272 -> 0 | Z14: ='销售帐 -ARGOTECH'!$P2641 -> 0 | AA14: ='销售帐 -ARGOTECH'!$P3105 -> 0 | AB14: ='销售帐 -ARGOTECH'!$P3400 -> 0 | AC14: ='销售帐 -ARGOTECH'!$P3508 -> 0 | AD14: =S14-S12 -> 94558.97 | AF14: =R14-R12 -> 108398.87
A15: ARGOTECH | B15: 阿家达 | C15: 现款-现金、银行存款 | D15: =SUM(E15:P15) -> 921766.7 | E15: =ROUND(R15*$R$3,2) -> 497328.99 | F15: =ROUND(S15*$S$3,2) -> 424437.71 | G15: =ROUND(T15*$T$3,2) -> 0 | H15: =ROUND(U15*$U$3,2) -> 0 | I15: =ROUND(V15*V$3,2) -> 0 | J15: =ROUND(W15*W$3,2) -> 0 | K15: =ROUND(X15*X$3,2) -> 0 | L15: =ROUND(Y15*Y$3,2) -> 0 | M15: =ROUND(Z15*Z$3,2) -> 0 | N15: =ROUND(AC15*AC$3,2) -> 0 | O15: =ROUND(AB15*AB$3,2) -> 0 | P15: =ROUND(AC15*AC$3,2) -> 0 | Q15: =SUM(R15:AC15) -> 706228.33 | R15: ='销售帐 -ARGOTECH'!M390+'销售帐 -ARGOTECH'!N390 -> 385825.44 | S15: ='销售帐 -ARGOTECH'!$N691+'销售帐 -ARGOTECH'!M691 -> 320402.89 | T15: ='销售帐 -ARGOTECH'!$N798 -> 0 | U15: ='销售帐 -ARGOTECH'!$N993 -> 0 | V15: ='销售帐 -ARGOTECH'!$N1286 -> 0 | W15: ='销售帐 -ARGOTECH'!$N1615 -> 0 | X15: ='销售帐 -ARGOTECH'!$N1946 -> 0 | Y15: ='销售帐 -ARGOTECH'!$N2272 -> 0 | Z15: ='销售帐 -ARGOTECH'!$N2641 -> 0 | AA15: ='销售帐 -ARGOTECH'!$N3105 -> 0 | AB15: ='销售帐 -ARGOTECH'!$N3400 -> 0 | AC15: ='销售帐 -ARGOTECH'!$N3508 -> 0
A16: CAIYA | B16: 界野 | C16: 主营业务收入 | D16: =SUM(E16:P16) -> 58803.38 | E16: =ROUND(R16*$R$3,2) -> 20735.09 | F16: =ROUND(S16*$S$3,2) -> 38068.29 | G16: =ROUND(T16*$T$3,2) -> 0 | H16: =ROUND(U16*$U$3,2) -> 0 | I16: =ROUND(V16*V$3,2) -> 0 | J16: =ROUND(W16*W$3,2) -> 0 | K16: =ROUND(X16*X$3,2) -> 0 | L16: =ROUND(Y16*Y$3,2) -> 0 | M16: =ROUND(Z16*Z$3,2) -> 0 | N16: =ROUND(AC16*AC$3,2) -> 0 | O16: =ROUND(AB16*AB$3,2) -> 0 | P16: =ROUND(AC16*AC$3,2) -> 0 | Q16: =SUM(R16:AC16) -> 44823.47 | R16: =销售帐CAIYA!L23 -> 16086.18 | S16: =销售帐CAIYA!$L47 -> 28737.29 | T16: =销售帐CAIYA!$L55 -> 0 | U16: =销售帐CAIYA!$L60 -> 0 | V16: =销售帐CAIYA!$L65 -> 0 | W16: =销售帐CAIYA!$L80 -> 0 | X16: =销售帐CAIYA!$L92 -> 0 | Y16: =销售帐CAIYA!$L106 -> 0 | Z16: =销售帐CAIYA!$L116 -> 0 | AA16: =销售帐CAIYA!$L125 -> 0 | AB16: =销售帐CAIYA!$L153 -> 0 | AC16: =销售帐CAIYA!$L161 -> 0 | AD16: =S16+S17 -> 28800.3 | AE16: =F16+F17 -> 38151.76 | AF16: =Y16+Y17 -> 0
A17: CAIYA | B17: 界野 | C17: 财务费用--刷卡费 | D17: =SUM(E17:P17) -> 83.47 | E17: =ROUND(R17*$R$3,2) -> 0 | F17: =ROUND(S17*$S$3,2) -> 83.47 | G17: =ROUND(T17*$T$3,2) -> 0 | H17: =ROUND(U17*$U$3,2) -> 0 | I17: =ROUND(V17*V$3,2) -> 0 | J17: =ROUND(W17*W$3,2) -> 0 | K17: =ROUND(X17*X$3,2) -> 0 | L17: =ROUND(Y17*Y$3,2) -> 0 | M17: =ROUND(Z17*Z$3,2) -> 0 | N17: =ROUND(AC17*AC$3,2) -> 0 | O17: =ROUND(AB17*AB$3,2) -> 0 | P17: =ROUND(AC17*AC$3,2) -> 0 | Q17: =SUM(R17:AC17) -> 63.01 | R17: =销售帐CAIYA!Q23 -> 0 | S17: =销售帐CAIYA!$R47 -> 63.01 | T17: =销售帐CAIYA!$Q55 -> 0 | U17: =销售帐CAIYA!$Q60 -> 0 | V17: =销售帐CAIYA!$Q65 -> 0 | W17: =销售帐CAIYA!$Q80 -> 0 | X17: =销售帐CAIYA!$Q92 -> 0 | Y17: =销售帐CAIYA!$Q106 -> 0 | Z17: =销售帐CAIYA!$Q116 -> 0 | AA17: =销售帐CAIYA!$Q125 -> 0 | AB17: =销售帐CAIYA!$Q153 -> 0 | AC17: =销售帐CAIYA!$Q161 -> 0
A18: CAIYA | B18: 界野 | C18: 博莱多收款 | D18: =SUM(E18:P18) -> 32423.32 | E18: =ROUND(R18*$R$3,2) -> 10455.41 | F18: =ROUND(S18*$S$3,2) -> 21967.92 | G18: =ROUND(T18*$T$3,2)-0.01 -> -0.01 | H18: =ROUND(U18*$U$3,2) -> 0 | I18: =ROUND(V18*V$3,2) -> 0 | J18: =ROUND(W18*W$3,2) -> 0 | K18: =ROUND(X18*X$3,2) -> 0 | L18: =ROUND(Y18*Y$3,2) -> 0 | M18: =ROUND(Z18*Z$3,2) -> 0 | N18: =ROUND(AC18*AC$3,2) -> 0 | O18: =ROUND(AB18*AB$3,2) -> 0 | P18: =ROUND(AC18*AC$3,2) -> 0 | Q18: =SUM(R18:AC18) -> 24694.58 | R18: =销售帐CAIYA!O23 -> 8111.26 | S18: =销售帐CAIYA!$O47 -> 16583.32 | T18: =销售帐CAIYA!$O55 -> 0 | U18: =销售帐CAIYA!$O60 -> 0 | V18: =销售帐CAIYA!$O65 -> 0 | W18: =销售帐CAIYA!$O80 -> 0 | X18: =销售帐CAIYA!$O92 -> 0 | Y18: =销售帐CAIYA!$O106 -> 0 | Z18: =销售帐CAIYA!$O116 -> 0 | AA18: =销售帐CAIYA!$O125 -> 0 | AB18: =销售帐CAIYA!$O153 -> 0 | AC18: =销售帐CAIYA!$O161 -> 0
A19: CAIYA | B19: 界野 | C19: 刷卡收款 | D19: =SUM(E19:P19) -> 3521.85 | E19: =ROUND(R19*$R$3,2) -> 0 | F19: =ROUND(S19*$S$3,2) -> 3521.85 | G19: =ROUND(T19*$T$3,2) -> 0 | H19: =ROUND(U19*$U$3,2) -> 0 | I19: =ROUND(V19*V$3,2) -> 0 | J19: =ROUND(W19*W$3,2) -> 0 | K19: =ROUND(X19*X$3,2) -> 0 | L19: =ROUND(Y19*Y$3,2) -> 0 | M19: =ROUND(Z19*Z$3,2) -> 0 | N19: =ROUND(AC19*AC$3,2) -> 0 | O19: =ROUND(AB19*AB$3,2) -> 0 | P19: =ROUND(AC19*AC$3,2) -> 0 | Q19: =SUM(R19:AC19) -> 2658.6 | R19: =销售帐CAIYA!P23 -> 0 | S19: =销售帐CAIYA!$P47 -> 2658.6 | T19: =销售帐CAIYA!$P55 -> 0 | U19: =销售帐CAIYA!$P60 -> 0 | V19: =销售帐CAIYA!$P65 -> 0 | W19: =销售帐CAIYA!$P80 -> 0 | X19: =销售帐CAIYA!$P92 -> 0 | Y19: =销售帐CAIYA!$P106 -> 0 | Z19: =销售帐CAIYA!$P116 -> 0 | AA19: =销售帐CAIYA!$P125 -> 0 | AB19: =销售帐CAIYA!$P153 -> 0 | AC19: =销售帐CAIYA!$P161 -> 0 | AD19: =S19-S17 -> 2595.59 | AF19: =R19-R17 -> 0
A20: CAIYA | B20: 界野 | C20: 现款-现金、银行存款 | D20: =SUM(E20:P20) -> 22941.67 | E20: =ROUND(R20*$R$3,2)+0.01 -> 10279.68 | F20: =ROUND(S20*$S$3,2) -> 12661.99 | G20: =ROUND(T20*$T$3,2) -> 0 | H20: =ROUND(U20*$U$3,2) -> 0 | I20: =ROUND(V20*V$3,2) -> 0 | J20: =ROUND(W20*W$3,2) -> 0 | K20: =ROUND(X20*X$3,2) -> 0 | L20: =ROUND(Y20*Y$3,2) -> 0 | M20: =ROUND(Z20*Z$3,2) -> 0 | N20: =ROUND(AC20*AC$3,2) -> 0 | O20: =ROUND(AB20*AB$3,2) -> 0 | P20: =ROUND(AC20*AC$3,2) -> 0 | Q20: =SUM(R20:AC20) -> 17533.3 | R20: =销售帐CAIYA!M23+销售帐CAIYA!N23 -> 7974.92 | S20: =销售帐CAIYA!$M55+销售帐CAIYA!$N47 -> 9558.38 | T20: =销售帐CAIYA!$M60+销售帐CAIYA!$N55 -> 0 | U20: =销售帐CAIYA!$M60+销售帐CAIYA!$N60 -> 0 | V20: =销售帐CAIYA!$M65+销售帐CAIYA!$N65 -> 0 | W20: =销售帐CAIYA!$M80+销售帐CAIYA!$N80 -> 0 | X20: =销售帐CAIYA!$M92+销售帐CAIYA!$N92 -> 0 | Y20: =销售帐CAIYA!$M106+销售帐CAIYA!$N106 -> 0 | Z20: =销售帐CAIYA!$M116+销售帐CAIYA!$N116 -> 0 | AA20: =销售帐CAIYA!$M125+销售帐CAIYA!$N125 -> 0 | AB20: =销售帐CAIYA!$M153+销售帐CAIYA!$N153 -> 0 | AC20: =销售帐CAIYA!$M161+销售帐CAIYA!$N161 -> 0
A21: COMPBRASIL | B21: 江帝伯拉ZO | C21: 主营业务收入 | D21: =SUM(E21:P21) -> 0 | E21: =ROUND(R21*$R$3,2) -> 0 | F21: =ROUND(S21*$S$3,2) -> 0 | G21: =ROUND(T21*$T$3,2) -> 0 | H21: =ROUND(U21*$U$3,2) -> 0 | I21: =ROUND(V21*V$3,2) -> 0 | J21: =ROUND(W21*W$3,2) -> 0 | K21: =ROUND(X21*X$3,2) -> 0 | L21: =ROUND(Y21*Y$3,2) -> 0 | M21: =ROUND(Z21*Z$3,2) -> 0 | N21: =ROUND(AC21*AC$3,2) -> 0 | O21: =ROUND(AB21*AB$3,2) -> 0 | P21: =ROUND(AC21*AC$3,2) -> 0 | Q21: =SUM(R21:AC21) -> 0 | R21: ='销售帐 - COMPBRASIL'!$L27 -> 0 | S21: ='销售帐 - COMPBRASIL'!$L35 -> 0 | T21: ='销售帐 - COMPBRASIL'!$L40 -> 0 | U21: ='销售帐 - COMPBRASIL'!$L82 -> 0 | V21: ='销售帐 - COMPBRASIL'!$L270 -> 0 | W21: ='销售帐 - COMPBRASIL'!$L387 -> 0 | X21: ='销售帐 - COMPBRASIL'!$L479 -> 0 | Y21: ='销售帐 - COMPBRASIL'!$L578 -> 0 | Z21: ='销售帐 - COMPBRASIL'!$L645 -> 0 | AA21: ='销售帐 - COMPBRASIL'!$L733 -> 0 | AB21: ='销售帐 - COMPBRASIL'!$L798 -> 0 | AC21: ='销售帐 - COMPBRASIL'!$L809 -> 0 | AE21: =E21+E22 -> 0 | AF21: =Y21+Y22 -> 0
A22: COMPBRASIL | B22: 江帝伯拉ZO | C22: 财务费用--刷卡费 | D22: =SUM(E22:P22) -> 0 | E22: =ROUND(R22*$R$3,2) -> 0 | F22: =ROUND(S22*$S$3,2) -> 0 | G22: =ROUND(T22*$T$3,2) -> 0 | H22: =ROUND(U22*$U$3,2) -> 0 | I22: =ROUND(V22*V$3,2) -> 0 | J22: =ROUND(W22*W$3,2) -> 0 | K22: =ROUND(X22*X$3,2) -> 0 | L22: =ROUND(Y22*Y$3,2) -> 0 | M22: =ROUND(Z22*Z$3,2) -> 0 | N22: =ROUND(AC22*AC$3,2) -> 0 | O22: =ROUND(AB22*AB$3,2) -> 0 | P22: =ROUND(AC22*AC$3,2) -> 0 | Q22: =SUM(R22:AC22) -> 0 | R22: ='销售帐 - COMPBRASIL'!$Q27 -> 0 | S22: ='销售帐 - COMPBRASIL'!$Q35 -> 0 | T22: ='销售帐 - COMPBRASIL'!$Q40 -> 0 | U22: ='销售帐 - COMPBRASIL'!$Q82 -> 0 | V22: ='销售帐 - COMPBRASIL'!$Q270 -> 0 | W22: ='销售帐 - COMPBRASIL'!$Q387 -> 0 | X22: ='销售帐 - COMPBRASIL'!$Q479 -> 0 | Y22: ='销售帐 - COMPBRASIL'!$Q578 -> 0 | Z22: ='销售帐 - COMPBRASIL'!$Q645 -> 0 | AA22: ='销售帐 - COMPBRASIL'!$Q733 -> 0 | AB22: ='销售帐 - COMPBRASIL'!$Q798 -> 0 | AC22: ='销售帐 - COMPBRASIL'!$Q809 -> 0
A23: COMPBRASIL | B23: 江帝伯拉ZO | C23: 博莱多收款 | D23: =SUM(E23:P23) -> 0.01 | E23: =ROUND(R23*$R$3,2) -> 0 | F23: =ROUND(S23*$S$3,2)+0.01 -> 0.01 | G23: =ROUND(T23*$T$3,2) -> 0 | H23: =ROUND(U23*$U$3,2) -> 0 | I23: =ROUND(V23*V$3,2) -> 0 | J23: =ROUND(W23*W$3,2) -> 0 | K23: =ROUND(X23*X$3,2) -> 0 | L23: =ROUND(Y23*Y$3,2) -> 0 | M23: =ROUND(Z23*Z$3,2) -> 0 | N23: =ROUND(AC23*AC$3,2) -> 0 | O23: =ROUND(AB23*AB$3,2) -> 0 | P23: =ROUND(AC23*AC$3,2) -> 0 | Q23: =SUM(R23:AC23) -> 0 | R23: ='销售帐 - COMPBRASIL'!$O27 -> 0 | S23: ='销售帐 - COMPBRASIL'!$O35 -> 0 | T23: ='销售帐 - COMPBRASIL'!$O40 -> 0 | U23: ='销售帐 - COMPBRASIL'!$O82 -> 0 | V23: ='销售帐 - COMPBRASIL'!$O270 -> 0 | W23: ='销售帐 - COMPBRASIL'!$O387 -> 0 | X23: ='销售帐 - COMPBRASIL'!$O479 -> 0 | Y23: ='销售帐 - COMPBRASIL'!$O578 -> 0 | Z23: ='销售帐 - COMPBRASIL'!$O645 -> 0 | AA23: ='销售帐 - COMPBRASIL'!$O733 -> 0 | AB23: ='销售帐 - COMPBRASIL'!$O798 -> 0 | AC23: ='销售帐 - COMPBRASIL'!$O809 -> 0
A24: COMPBRASIL | B24: 江帝伯拉ZO | C24: 刷卡收款 | D24: =SUM(E24:P24) -> 0 | E24: =ROUND(R24*$R$3,2) -> 0 | F24: =ROUND(S24*$S$3,2) -> 0 | G24: =ROUND(T24*$T$3,2) -> 0 | H24: =ROUND(U24*$U$3,2) -> 0 | I24: =ROUND(V24*V$3,2) -> 0 | J24: =ROUND(W24*W$3,2) -> 0 | K24: =ROUND(X24*X$3,2) -> 0 | L24: =ROUND(Y24*Y$3,2) -> 0 | M24: =ROUND(Z24*Z$3,2) -> 0 | N24: =ROUND(AC24*AC$3,2) -> 0 | O24: =ROUND(AB24*AB$3,2) -> 0 | P24: =ROUND(AC24*AC$3,2) -> 0 | Q24: =SUM(R24:AC24) -> 0 | R24: ='销售帐 - COMPBRASIL'!$P27 -> 0 | S24: ='销售帐 - COMPBRASIL'!$P35 -> 0 | T24: ='销售帐 - COMPBRASIL'!$P40 -> 0 | U24: ='销售帐 - COMPBRASIL'!$P82 -> 0 | V24: ='销售帐 - COMPBRASIL'!$P270 -> 0 | W24: ='销售帐 - COMPBRASIL'!$P387 -> 0 | X24: ='销售帐 - COMPBRASIL'!$P479 -> 0 | Y24: ='销售帐 - COMPBRASIL'!$P578 -> 0 | Z24: ='销售帐 - COMPBRASIL'!$P645 -> 0 | AA24: ='销售帐 - COMPBRASIL'!$P733 -> 0 | AB24: ='销售帐 - COMPBRASIL'!$P798 -> 0 | AC24: ='销售帐 - COMPBRASIL'!$P809 -> 0 | AD24: =R24-R22 -> 0
A25: COMPBRASIL | B25: 江帝伯拉ZO | C25: 现款-现金、银行存款 | D25: =SUM(E25:P25) -> 0 | E25: =ROUND(R25*$R$3,2) -> 0 | F25: =ROUND(S25*$S$3,2) -> 0 | G25: =ROUND(T25*$T$3,2) -> 0 | H25: =ROUND(U25*$U$3,2) -> 0 | I25: =ROUND(V25*V$3,2) -> 0 | J25: =ROUND(W25*W$3,2) -> 0 | K25: =ROUND(X25*X$3,2) -> 0 | L25: =ROUND(Y25*Y$3,2) -> 0 | M25: =ROUND(Z25*Z$3,2) -> 0 | N25: =ROUND(AC25*AC$3,2) -> 0 | O25: =ROUND(AB25*AB$3,2) -> 0 | P25: =ROUND(AC25*AC$3,2) -> 0 | Q25: =SUM(R25:AC25) -> 0 | R25: ='销售帐 - COMPBRASIL'!$M27+'销售帐 - COMPBRASIL'!$N27 -> 0 | S25: ='销售帐 - COMPBRASIL'!$M35+'销售帐 - COMPBRASIL'!$N35 -> 0 | T25: ='销售帐 - COMPBRASIL'!$M40+'销售帐 - COMPBRASIL'!$N40 -> 0 | U25: ='销售帐 - COMPBRASIL'!$M82+'销售帐 - COMPBRASIL'!$N82 -> 0 | V25: ='销售帐 - COMPBRASIL'!$M270+'销售帐 - COMPBRASIL'!$N270 -> 0 | W25: ='销售帐 - COMPBRASIL'!$M387+'销售帐 - COMPBRASIL'!$N387 -> 0 | X25: ='销售帐 - COMPBRASIL'!$M479+'销售帐 - COMPBRASIL'!$N479 -> 0 | Y25: ='销售帐 - COMPBRASIL'!$M578+'销售帐 - COMPBRASIL'!$N578 -> 0 | Z25: ='销售帐 - COMPBRASIL'!$M645+'销售帐 - COMPBRASIL'!$N645 -> 0 | AA25: ='销售帐 - COMPBRASIL'!$M733+'销售帐 - COMPBRASIL'!$N733 -> 0 | AB25: ='销售帐 - COMPBRASIL'!$M798+'销售帐 - COMPBRASIL'!$N798 -> 0 | AC25: ='销售帐 - COMPBRASIL'!$M809+'销售帐 - COMPBRASIL'!$N809 -> 0
A26: DEYUN | B26: 德永 | C26: 主营业务收入 | D26: =SUM(E26:P26) -> 13025.99 | E26: =ROUND(R26*$R$3,2) -> 13025.99 | F26: =ROUND(S26*$S$3,2) -> 0 | G26: =ROUND(T26*$T$3,2) -> 0 | H26: =ROUND(U26*$U$3,2) -> 0 | I26: =ROUND(V26*V$3,2) -> 0 | J26: =ROUND(W26*W$3,2) -> 0 | K26: =ROUND(X26*X$3,2) -> 0 | L26: =ROUND(Y26*Y$3,2) -> 0 | M26: =ROUND(Z26*Z$3,2) -> 0 | N26: =ROUND(AC26*AC$3,2) -> 0 | O26: =ROUND(AB26*AB$3,2) -> 0 | P26: =ROUND(AC26*AC$3,2) -> 0 | Q26: =SUM(R26:AC26) -> 10105.5 | R26: =销售帐DEYUN!$L13 -> 10105.5 | S26: =销售帐DEYUN!$L17 -> 0 | T26: =销售帐DEYUN!L23 -> 0 | V26: =销售帐DEYUN!$L32 -> 0 | W26: =销售帐DEYUN!$L37 -> 0 | X26: =销售帐DEYUN!$L48 -> 0 | Y26: =销售帐DEYUN!$L61 -> 0 | Z26: =销售帐DEYUN!$L74 -> 0 | AA26: =销售帐DEYUN!$L86 -> 0 | AB26: =销售帐DEYUN!$L96 -> 0 | AC26: =销售帐DEYUN!$L107 -> 0 | AD26: =S26+S27 -> 0 | AE26: =F26+F27 -> 0 | AF26: =Y26+Y27 -> 0
A27: DEYUN | B27: 德永 | C27: 财务费用--刷卡费 | D27: =SUM(E27:P27) -> 0 | E27: =ROUND(R27*$R$3,2) -> 0 | F27: =ROUND(S27*$S$3,2) -> 0 | G27: =ROUND(T27*$T$3,2) -> 0 | H27: =ROUND(U27*$U$3,2) -> 0 | I27: =ROUND(V27*V$3,2) -> 0 | J27: =ROUND(W27*W$3,2) -> 0 | K27: =ROUND(X27*X$3,2) -> 0 | L27: =ROUND(Y27*Y$3,2) -> 0 | M27: =ROUND(Z27*Z$3,2) -> 0 | N27: =ROUND(AC27*AC$3,2) -> 0 | O27: =ROUND(AB27*AB$3,2) -> 0 | P27: =ROUND(AC27*AC$3,2) -> 0 | Q27: =SUM(R27:AC27) -> 0 | R27: =销售帐DEYUN!$Q13 -> 0 | S27: =销售帐DEYUN!$Q17 -> 0 | T27: =销售帐DEYUN!Q23 -> 0 | V27: =销售帐DEYUN!$Q32 -> 0 | W27: =销售帐DEYUN!$Q37 -> 0 | X27: =销售帐DEYUN!$Q48 -> 0 | Y27: =销售帐DEYUN!$Q61 -> 0 | Z27: =销售帐DEYUN!$Q74 -> 0 | AA27: =销售帐DEYUN!$Q86 -> 0 | AB27: =销售帐DEYUN!$Q96 -> 0 | AC27: =销售帐DEYUN!$Q107 -> 0
A28: DEYUN | B28: 德永 | C28: 博莱多收款 | D28: =SUM(E28:P28) -> 13025.99 | E28: =ROUND(R28*$R$3,2) -> 13025.99 | F28: =ROUND(S28*$S$3,2) -> 0 | G28: =ROUND(T28*$T$3,2) -> 0 | H28: =ROUND(U28*$U$3,2) -> 0 | I28: =ROUND(V28*V$3,2) -> 0 | J28: =ROUND(W28*W$3,2) -> 0 | K28: =ROUND(X28*X$3,2) -> 0 | L28: =ROUND(Y28*Y$3,2) -> 0 | M28: =ROUND(Z28*Z$3,2) -> 0 | N28: =ROUND(AC28*AC$3,2) -> 0 | O28: =ROUND(AB28*AB$3,2) -> 0 | P28: =ROUND(AC28*AC$3,2) -> 0 | Q28: =SUM(R28:AC28) -> 10105.5 | R28: =销售帐DEYUN!$O13 -> 10105.5 | S28: =销售帐DEYUN!$O17 -> 0 | T28: =销售帐DEYUN!O23 -> 0 | V28: =销售帐DEYUN!$O32 -> 0 | W28: =销售帐DEYUN!$O37 -> 0 | X28: =销售帐DEYUN!$O48 -> 0 | Y28: =销售帐DEYUN!$O61 -> 0 | Z28: =销售帐DEYUN!$O74 -> 0 | AA28: =销售帐DEYUN!$O86 -> 0 | AB28: =销售帐DEYUN!$O96 -> 0 | AC28: =销售帐DEYUN!$O107 -> 0
A29: DEYUN | B29: 德永 | C29: 刷卡收款 | D29: =SUM(E29:P29) -> -0.01 | E29: =ROUND(R29*$R$3,2) -> 0 | F29: =ROUND(S29*$S$3,2) -> 0 | G29: =ROUND(T29*$T$3,2) -> 0 | H29: =ROUND(U29*$U$3,2) -> 0 | I29: =ROUND(V29*V$3,2) -> 0 | J29: =ROUND(W29*W$3,2) -> 0 | K29: =ROUND(X29*X$3,2) -> 0 | L29: =ROUND(Y29*Y$3,2)-0.01 -> -0.01 | M29: =ROUND(Z29*Z$3,2) -> 0 | N29: =ROUND(AC29*AC$3,2) -> 0 | O29: =ROUND(AB29*AB$3,2) -> 0 | P29: =ROUND(AC29*AC$3,2) -> 0 | Q29: =SUM(R29:AC29) -> 0 | R29: =销售帐DEYUN!$P13 -> 0 | S29: =销售帐DEYUN!$P17 -> 0 | T29: =销售帐DEYUN!P23 -> 0 | V29: =销售帐DEYUN!$P32 -> 0 | W29: =销售帐DEYUN!$P37 -> 0 | X29: =销售帐DEYUN!$P48 -> 0 | Y29: =销售帐DEYUN!$P61 -> 0 | Z29: =销售帐DEYUN!$P74 -> 0 | AA29: =销售帐DEYUN!$P86 -> 0 | AB29: =销售帐DEYUN!$P96 -> 0 | AC29: =销售帐DEYUN!$P107 -> 0 | AD29: =S29-S27 -> 0 | AF29: =R29-R27 -> 0
A30: DEYUN | B30: 德永 | C30: 现款-现金、银行存款 | D30: =SUM(E30:P30) -> 0 | E30: =ROUND(R30*$R$3,2) -> 0 | F30: =ROUND(S30*$S$3,2) -> 0 | G30: =ROUND(T30*$T$3,2) -> 0 | H30: =ROUND(U30*$U$3,2) -> 0 | I30: =ROUND(V30*V$3,2) -> 0 | J30: =ROUND(W30*W$3,2) -> 0 | K30: =ROUND(X30*X$3,2) -> 0 | L30: =ROUND(Y30*Y$3,2) -> 0 | M30: =ROUND(Z30*Z$3,2) -> 0 | N30: =ROUND(AC30*AC$3,2) -> 0 | O30: =ROUND(AB30*AB$3,2) -> 0 | P30: =ROUND(AC30*AC$3,2) -> 0 | Q30: =SUM(R30:AC30) -> 0 | R30: =销售帐DEYUN!$M13+销售帐DEYUN!$N13 -> 0 | S30: =销售帐DEYUN!$M17+销售帐DEYUN!$N17 -> 0 | T30: =销售帐DEYUN!M23+销售帐DEYUN!N23 -> 0 | V30: =销售帐DEYUN!$M32+销售帐DEYUN!$N32 -> 0 | W30: =销售帐DEYUN!$M37+销售帐DEYUN!$N37 -> 0 | X30: =销售帐DEYUN!$M48+销售帐DEYUN!$N48 -> 0 | Y30: =销售帐DEYUN!$M61+销售帐DEYUN!$N61 -> 0 | Z30: =销售帐DEYUN!$M74+销售帐DEYUN!$N74 -> 0 | AA30: =销售帐DEYUN!$M86+销售帐DEYUN!$N86 -> 0 | AB30: =销售帐DEYUN!$M96+销售帐DEYUN!$N96 -> 0 | AC30: =销售帐DEYUN!$M107+销售帐DEYUN!$N107 -> 0
A31: MARTELUX | B31: 麻德罗思 | C31: 主营业务收入 | D31: =SUM(E31:P31) -> 281344.77 | E31: =ROUND(R31*$R$3,2) -> 163676.64 | F31: =ROUND(S31*$S$3,2) -> 117668.13 | G31: =ROUND(T31*$T$3,2) -> 0 | H31: =ROUND(U31*$U$3,2) -> 0 | I31: =ROUND(V31*V$3,2) -> 0 | J31: =ROUND(W31*W$3,2) -> 0 | K31: =ROUND(X31*X$3,2) -> 0 | L31: =ROUND(Y31*Y$3,2) -> 0 | M31: =ROUND(Z31*Z$3,2) -> 0 | N31: =ROUND(AC31*AC$3,2) -> 0 | O31: =ROUND(AB31*AB$3,2) -> 0 | P31: =ROUND(AC31*AC$3,2) -> 0 | Q31: =SUM(R31:AC31) -> 215805.8 | R31: ='销售帐 MARTELUX'!$L100 -> 126979.55 | S31: ='销售帐 MARTELUX'!$L172 -> 88826.246 | T31: ='销售帐 MARTELUX'!L335 -> 0 | U31: ='销售帐 MARTELUX'!$L446 -> 0 | V31: ='销售帐 MARTELUX'!$L610 -> 0 | W31: ='销售帐 MARTELUX'!$L839 -> 0 | X31: ='销售帐 MARTELUX'!$L1080 -> 0 | Y31: ='销售帐 MARTELUX'!$L1351 -> 0 | Z31: ='销售帐 MARTELUX'!$L1557 -> 0 | AA31: ='销售帐 MARTELUX'!$L1742 -> 0 | AB31: ='销售帐 MARTELUX'!$L1895 -> 0 | AC31: ='销售帐 MARTELUX'!$L1929 -> 0 | AD31: =S31+S32 -> 88958.72 | AE31: =F31+F32 -> 117843.62 | AF31: =Y31+Y32 -> 0
A32: MARTELUX | B32: 麻德罗思 | C32: 财务费用--刷卡费 | D32: =SUM(E32:P32) -> 596.34 | E32: =ROUND(R32*$R$3,2) -> 420.85 | F32: =ROUND(S32*$S$3,2) -> 175.49 | G32: =ROUND(T32*$T$3,2) -> 0 | H32: =ROUND(U32*$U$3,2) -> 0 | I32: =ROUND(V32*V$3,2) -> 0 | J32: =ROUND(W32*W$3,2) -> 0 | K32: =ROUND(X32*X$3,2) -> 0 | L32: =ROUND(Y32*Y$3,2) -> 0 | M32: =ROUND(Z32*Z$3,2) -> 0 | N32: =ROUND(AC32*AC$3,2) -> 0 | O32: =ROUND(AB32*AB$3,2) -> 0 | P32: =ROUND(AC32*AC$3,2) -> 0 | Q32: =SUM(R32:AC32) -> 458.96424 | R32: ='销售帐 MARTELUX'!$R100 -> 326.49 | S32: ='销售帐 MARTELUX'!$R172 -> 132.47424 | T32: ='销售帐 MARTELUX'!R335 -> 0 | U32: ='销售帐 MARTELUX'!$R446 -> 0 | V32: ='销售帐 MARTELUX'!$R610 -> 0 | W32: ='销售帐 MARTELUX'!$R839 -> 0 | X32: ='销售帐 MARTELUX'!$R1080 -> 0 | Y32: ='销售帐 MARTELUX'!$R1351 -> 0 | Z32: ='销售帐 MARTELUX'!$R1557 -> 0 | AA32: ='销售帐 MARTELUX'!$R1742 -> 0 | AB32: ='销售帐 MARTELUX'!$R1895 -> 0 | AC32: ='销售帐 MARTELUX'!$R1929 -> 0
A33: MARTELUX | B33: 麻德罗思 | C33: 博莱多收款 | D33: =SUM(E33:P33) -> 151631.33 | E33: =ROUND(R33*$R$3,2) -> 78988.28 | F33: =ROUND(S33*$S$3,2) -> 72643.05 | G33: =ROUND(T33*$T$3,2) -> 0 | H33: =ROUND(U33*$U$3,2) -> 0 | I33: =ROUND(V33*V$3,2) -> 0 | J33: =ROUND(W33*W$3,2) -> 0 | K33: =ROUND(X33*X$3,2) -> 0 | L33: =ROUND(Y33*Y$3,2) -> 0 | M33: =ROUND(Z33*Z$3,2) -> 0 | N33: =ROUND(AC33*AC$3,2) -> 0 | O33: =ROUND(AB33*AB$3,2) -> 0 | P33: =ROUND(AC33*AC$3,2) -> 0 | Q33: =SUM(R33:AC33) -> 116116.09 | R33: ='销售帐 MARTELUX'!$O100 -> 61278.73 | S33: ='销售帐 MARTELUX'!$O172 -> 54837.36 | T33: ='销售帐 MARTELUX'!O335 -> 0 | U33: ='销售帐 MARTELUX'!$O446 -> 0 | V33: ='销售帐 MARTELUX'!$O610 -> 0 | W33: ='销售帐 MARTELUX'!$O839 -> 0 | X33: ='销售帐 MARTELUX'!$O1080 -> 0 | Y33: ='销售帐 MARTELUX'!$O1351 -> 0 | Z33: ='销售帐 MARTELUX'!$O1557 -> 0 | AA33: ='销售帐 MARTELUX'!$O1742 -> 0 | AB33: ='销售帐 MARTELUX'!$O1895 -> 0 | AC33: ='销售帐 MARTELUX'!$O1929 -> 0
A34: MARTELUX | B34: 麻德罗思 | C34: 刷卡收款 | D34: =SUM(E34:P34) -> 34113.07 | E34: =ROUND(R34*$R$3,2) -> 26362.02 | F34: =ROUND(S34*$S$3,2) -> 7751.08 | G34: =ROUND(T34*$T$3,2) -> 0 | H34: =ROUND(U34*$U$3,2) -> 0 | I34: =ROUND(V34*V$3,2) -> 0 | J34: =ROUND(W34*W$3,2)-0.01 -> -0.01 | K34: =ROUND(X34*X$3,2) -> 0 | L34: =ROUND(Y34*Y$3,2)-0.01 -> -0.01 | M34: =ROUND(Z34*Z$3,2) -> 0 | N34: =ROUND(AC34*AC$3,2)-0.01 -> -0.01 | O34: =ROUND(AB34*AB$3,2) -> 0 | P34: =ROUND(AC34*AC$3,2) -> 0 | Q34: =SUM(R34:AC34) -> 26302.73 | R34: ='销售帐 MARTELUX'!$P100 -> 20451.53 | S34: ='销售帐 MARTELUX'!$P172 -> 5851.2 | T34: ='销售帐 MARTELUX'!P335 -> 0 | U34: ='销售帐 MARTELUX'!$P446 -> 0 | V34: ='销售帐 MARTELUX'!$P610 -> 0 | W34: ='销售帐 MARTELUX'!$P839 -> 0 | X34: ='销售帐 MARTELUX'!$P1080 -> 0 | Y34: ='销售帐 MARTELUX'!$P1351 -> 0 | Z34: ='销售帐 MARTELUX'!$P1557 -> 0 | AA34: ='销售帐 MARTELUX'!$P1742 -> 0 | AB34: ='销售帐 MARTELUX'!$P1895 -> 0 | AC34: ='销售帐 MARTELUX'!$P1929 -> 0 | AD34: =S34-S32 -> 5718.7258 | AF34: =R34-R32 -> 20125.04
A35: MARTELUX | B35: 麻德罗思 | C35: 现款-现金、银行存款 | D35: =SUM(E35:P35) -> 96196.66 | E35: =ROUND(R35*$R$3,2) -> 58747.18 | F35: =ROUND(S35*$S$3,2) -> 37449.48 | G35: =ROUND(T35*$T$3,2) -> 0 | H35: =ROUND(U35*$U$3,2) -> 0 | I35: =ROUND(V35*V$3,2) -> 0 | J35: =ROUND(W35*W$3,2) -> 0 | K35: =ROUND(X35*X$3,2) -> 0 | L35: =ROUND(Y35*Y$3,2) -> 0 | M35: =ROUND(Z35*Z$3,2) -> 0 | N35: =ROUND(AC35*AC$3,2) -> 0 | O35: =ROUND(AB35*AB$3,2) -> 0 | P35: =ROUND(AC35*AC$3,2) -> 0 | Q35: =SUM(R35:AC35) -> 73845.94 | R35: ='销售帐 MARTELUX'!$M100+'销售帐 MARTELUX'!$N100 -> 45575.78 | S35: ='销售帐 MARTELUX'!$M172+'销售帐 MARTELUX'!$N172 -> 28270.16 | T35: ='销售帐 MARTELUX'!M335+'销售帐 MARTELUX'!N335 -> 0 | U35: ='销售帐 MARTELUX'!$M446+'销售帐 MARTELUX'!$N446 -> 0 | V35: ='销售帐 MARTELUX'!$M610+'销售帐 MARTELUX'!$N610 -> 0 | W35: ='销售帐 MARTELUX'!$M839+'销售帐 MARTELUX'!$N839 -> 0 | X35: ='销售帐 MARTELUX'!$M1080+'销售帐 MARTELUX'!$N1080 -> 0 | Y35: ='销售帐 MARTELUX'!$M1351+'销售帐 MARTELUX'!$N1351 -> 0 | Z35: ='销售帐 MARTELUX'!$M1557+'销售帐 MARTELUX'!$N1557 -> 0 | AA35: ='销售帐 MARTELUX'!$M1742+'销售帐 MARTELUX'!$N1742 -> 0 | AB35: ='销售帐 MARTELUX'!$M1895+'销售帐 MARTELUX'!$N1895 -> 0 | AC35: ='销售帐 MARTELUX'!$M1929+'销售帐 MARTELUX'!$N1929 -> 0
A36: NORTE | B36: 诺基土 | C36: 主营业务收入 | D36: =SUM(E36:P36) -> 50406.74 | E36: =ROUND(R36*$R$3,2)+0.01 -> 49744.39 | F36: =ROUND(S36*$S$3,2) -> 662.35 | G36: =ROUND(T36*$T$3,2) -> 0 | H36: =ROUND(U36*$U$3,2) -> 0 | I36: =ROUND(V36*V$3,2) -> 0 | J36: =ROUND(W36*W$3,2) -> 0 | K36: =ROUND(X36*X$3,2) -> 0 | L36: =ROUND(Y36*Y$3,2) -> 0 | M36: =ROUND(Z36*Z$3,2) -> 0 | N36: =ROUND(AC36*AC$3,2) -> 0 | O36: =ROUND(AB36*AB$3,2) -> 0 | P36: =ROUND(AC36*AC$3,2) -> 0 | Q36: =SUM(R36:AC36) -> 44995.53 | R36: ='销售帐NORTE TOOLS'!L32 -> 38591.45 | S36: ='销售帐NORTE TOOLS'!L37 -> 500 | T36: ='销售帐NORTE TOOLS'!L70 -> 0 | U36: ='销售帐NORTE TOOLS'!L89 -> 0 | V36: ='销售帐NORTE TOOLS'!L102 -> 0 | W36: ='销售帐NORTE TOOLS'!L135 -> 0 | X36: ='销售帐NORTE TOOLS'!L178 -> 0 | Y36: ='销售帐NORTE TOOLS'!L235 -> 0 | Z36: ='销售帐NORTE TOOLS'!L257 -> 0 | AA36: ='[1]销售帐NORTE TOOLS'!$L10 -> 5904.08 | AB36: ='销售帐NORTE TOOLS'!L289 -> 0 | AC36: 0 | AD36: =S36+S37 -> 500 | AE36: =F36+F37 -> 662.35 | AF36: =Y36+Y37 -> 0
A37: NORTE | B37: 诺基土 | C37: 财务费用--刷卡费 | D37: =SUM(E37:P37) -> 165.71 | E37: =ROUND(R37*$R$3,2) -> 165.71 | F37: =ROUND(S37*$S$3,2) -> 0 | G37: =ROUND(T37*$T$3,2) -> 0 | H37: =ROUND(U37*$U$3,2) -> 0 | I37: =ROUND(V37*V$3,2) -> 0 | J37: =ROUND(W37*W$3,2) -> 0 | K37: =ROUND(X37*X$3,2) -> 0 | L37: =ROUND(Y37*Y$3,2) -> 0 | M37: =ROUND(Z37*Z$3,2) -> 0 | N37: =ROUND(AC37*AC$3,2) -> 0 | O37: =ROUND(AB37*AB$3,2) -> 0 | P37: =ROUND(AC37*AC$3,2) -> 0 | Q37: =SUM(R37:AC37) -> 204.48 | R37: ='销售帐NORTE TOOLS'!R32 -> 128.56 | S37: ='销售帐NORTE TOOLS'!R37 -> 0 | T37: ='销售帐NORTE TOOLS'!R70 -> 0 | U37: ='销售帐NORTE TOOLS'!R89 -> 0 | V37: ='销售帐NORTE TOOLS'!R102 -> 0 | W37: ='销售帐NORTE TOOLS'!R135 -> 0 | X37: ='销售帐NORTE TOOLS'!R178 -> 0 | Y37: ='销售帐NORTE TOOLS'!R235 -> 0 | Z37: ='销售帐NORTE TOOLS'!R257 -> 0 | AA37: ='[1]销售帐NORTE TOOLS'!$R10 -> 75.92 | AB37: ='销售帐NORTE TOOLS'!Q289 -> 0 | AC37: 0
A38: NORTE | B38: 诺基土 | C38: 博莱多收款 | D38: =SUM(E38:P38) -> 21165.38 | E38: =ROUND(R38*$R$3,2) -> 21165.38 | F38: =ROUND(S38*$S$3,2) -> 0 | G38: =ROUND(T38*$T$3,2) -> 0 | H38: =ROUND(U38*$U$3,2) -> 0 | I38: =ROUND(V38*V$3,2) -> 0 | J38: =ROUND(W38*W$3,2) -> 0 | K38: =ROUND(X38*X$3,2) -> 0 | L38: =ROUND(Y38*Y$3,2) -> 0 | M38: =ROUND(Z38*Z$3,2) -> 0 | N38: =ROUND(AC38*AC$3,2) -> 0 | O38: =ROUND(AB38*AB$3,2) -> 0 | P38: =ROUND(AC38*AC$3,2) -> 0 | Q38: =SUM(R38:AC38) -> 16420 | R38: ='销售帐NORTE TOOLS'!O32 -> 16420 | S38: ='销售帐NORTE TOOLS'!O37 -> 0 | T38: ='销售帐NORTE TOOLS'!O70 -> 0 | U38: ='销售帐NORTE TOOLS'!O89 -> 0 | V38: ='销售帐NORTE TOOLS'!O102 -> 0 | W38: ='销售帐NORTE TOOLS'!O135 -> 0 | X38: ='销售帐NORTE TOOLS'!O178 -> 0 | Y38: ='销售帐NORTE TOOLS'!O235 -> 0 | Z38: ='销售帐NORTE TOOLS'!O257 -> 0 | AA38: ='[1]销售帐NORTE TOOLS'!$O10 -> 0 | AB38: ='销售帐NORTE TOOLS'!O289 -> 0 | AC38: 0
A39: NORTE | B39: 诺基土 | C39: 刷卡收款 | D39: =SUM(E39:P39) -> 8083.5 | E39: =ROUND(R39*$R$3,2)+0.01 -> 8083.5 | F39: =ROUND(S39*$S$3,2) -> 0 | G39: =ROUND(T39*$T$3,2) -> 0 | H39: =ROUND(U39*$U$3,2) -> 0 | I39: =ROUND(V39*V$3,2) -> 0 | J39: =ROUND(W39*W$3,2) -> 0 | K39: =ROUND(X39*X$3,2) -> 0 | L39: =ROUND(Y39*Y$3,2) -> 0 | M39: =ROUND(Z39*Z$3,2) -> 0 | N39: =ROUND(AC39*AC$3,2) -> 0 | O39: =ROUND(AB39*AB$3,2) -> 0 | P39: =ROUND(AC39*AC$3,2) -> 0 | Q39: =SUM(R39:AC39) -> 9751.13 | R39: ='销售帐NORTE TOOLS'!P32 -> 6271.13 | S39: ='销售帐NORTE TOOLS'!P37 -> 0 | T39: ='销售帐NORTE TOOLS'!P70 -> 0 | U39: ='销售帐NORTE TOOLS'!P89 -> 0 | V39: ='销售帐NORTE TOOLS'!P102 -> 0 | W39: ='销售帐NORTE TOOLS'!P135 -> 0 | X39: ='销售帐NORTE TOOLS'!P178 -> 0 | Y39: ='销售帐NORTE TOOLS'!P235 -> 0 | Z39: ='销售帐NORTE TOOLS'!P257 -> 0 | AA39: ='[1]销售帐NORTE TOOLS'!$P10 -> 3480 | AB39: ='销售帐NORTE TOOLS'!P289 -> 0 | AC39: 0 | AD39: =S39-S37 -> 0 | AE39: =Y39-Y37 -> 0 | AF39: =R39-R37 -> 6142.57
A40: NORTE | B40: 诺基土 | C40: 现款-现金、银行存款 | D40: =SUM(E40:P40) -> 21323.57 | E40: =ROUND(R40*$R$3,2)-0.01 -> 20661.22 | F40: =ROUND(S40*$S$3,2) -> 662.35 | G40: =ROUND(T40*$T$3,2) -> 0 | H40: =ROUND(U40*$U$3,2) -> 0 | I40: =ROUND(V40*V$3,2) -> 0 | J40: =ROUND(W40*W$3,2) -> 0 | K40: =ROUND(X40*X$3,2) -> 0 | L40: =ROUND(Y40*Y$3,2) -> 0 | M40: =ROUND(Z40*Z$3,2) -> 0 | N40: =ROUND(AC40*AC$3,2) -> 0 | O40: =ROUND(AB40*AB$3,2) -> 0 | P40: =ROUND(AC40*AC$3,2) -> 0 | Q40: =SUM(R40:AC40) -> 19028.88 | R40: ='销售帐NORTE TOOLS'!M32+'销售帐NORTE TOOLS'!N32 -> 16028.88 | S40: ='销售帐NORTE TOOLS'!M37+'销售帐NORTE TOOLS'!N37 -> 500 | T40: ='销售帐NORTE TOOLS'!M70+'销售帐NORTE TOOLS'!N70 -> 0 | U40: ='销售帐NORTE TOOLS'!M89+'销售帐NORTE TOOLS'!N89 -> 0 | V40: ='销售帐NORTE TOOLS'!N102 -> 0 | W40: ='销售帐NORTE TOOLS'!N135 -> 0 | X40: ='销售帐NORTE TOOLS'!N178 -> 0 | Y40: ='销售帐NORTE TOOLS'!M235+'销售帐NORTE TOOLS'!N235 -> 0 | Z40: ='销售帐NORTE TOOLS'!M257+'销售帐NORTE TOOLS'!N257 -> 0 | AA40: ='[1]销售帐NORTE TOOLS'!$M10+'[1]销售帐NORTE TOOLS'!$N10 -> 2500 | AB40: ='销售帐NORTE TOOLS'!N289 -> 0 | AC40: 0
A41: ZHEMAX | B41: 财玛克思 | C41: 主营业务收入 | D41: =SUM(E41:P41) -> 0 | E41: =ROUND(R41*$R$3,2) -> 0 | F41: =ROUND(S41*$S$3,2) -> 0 | G41: =ROUND(T41*$T$3,2) -> 0 | H41: =ROUND(U41*$U$3,2) -> 0 | I41: =ROUND(V41*V$3,2) -> 0 | J41: =ROUND(W41*W$3,2) -> 0 | K41: =ROUND(X41*X$3,2) -> 0 | L41: =ROUND(Y41*Y$3,2) -> 0 | M41: =ROUND(Z41*Z$3,2) -> 0 | N41: =ROUND(AC41*AC$3,2) -> 0 | O41: =ROUND(AB41*AB$3,2) -> 0 | P41: =ROUND(AC41*AC$3,2) -> 0 | Q41: =SUM(R41:AC41) -> 0 | R41: ='销售帐 - ZHEMAX'!$L5 -> 0 | S41: ='销售帐 - ZHEMAX'!$L8 -> 0 | T41: ='销售帐 - ZHEMAX'!L15 -> 0 | U41: ='销售帐 - ZHEMAX'!$L26 -> 0 | V41: ='销售帐 - ZHEMAX'!$L79 -> 0 | W41: ='销售帐 - ZHEMAX'!$L128 -> 0 | X41: ='销售帐 - ZHEMAX'!$L143 -> 0 | Y41: ='销售帐 - ZHEMAX'!$L166 -> 0 | Z41: ='销售帐 - ZHEMAX'!$L173 -> 0 | AA41: ='销售帐 - ZHEMAX'!$L176 -> 0 | AB41: ='销售帐 - ZHEMAX'!$L179 -> 0 | AC41: ='销售帐 - ZHEMAX'!$L198 -> 0 | AE41: =E41+E42 -> 0 | AF41: =Y41+Y42 -> 0
A42: ZHEMAX | B42: 财玛克思 | C42: 财务费用--刷卡费 | D42: =SUM(E42:P42) -> 0 | E42: =ROUND(R42*$R$3,2) -> 0 | F42: =ROUND(S42*$S$3,2) -> 0 | G42: =ROUND(T42*$T$3,2) -> 0 | H42: =ROUND(U42*$U$3,2) -> 0 | I42: =ROUND(V42*V$3,2) -> 0 | J42: =ROUND(W42*W$3,2) -> 0 | K42: =ROUND(X42*X$3,2) -> 0 | L42: =ROUND(Y42*Y$3,2) -> 0 | M42: =ROUND(Z42*Z$3,2) -> 0 | N42: =ROUND(AC42*AC$3,2) -> 0 | O42: =ROUND(AB42*AB$3,2) -> 0 | P42: =ROUND(AC42*AC$3,2) -> 0 | Q42: =SUM(R42:AC42) -> 0 | R42: ='销售帐 - ZHEMAX'!$Q5 -> 0 | S42: ='销售帐 - ZHEMAX'!$Q8 -> 0 | T42: ='销售帐 - ZHEMAX'!Q15 -> 0 | U42: ='销售帐 - ZHEMAX'!$Q26 -> 0 | V42: ='销售帐 - ZHEMAX'!$Q79 -> 0 | W42: ='销售帐 - ZHEMAX'!$Q128 -> 0 | X42: ='销售帐 - ZHEMAX'!$Q143 -> 0 | Y42: ='销售帐 - ZHEMAX'!$Q166 -> 0 | Z42: ='销售帐 - ZHEMAX'!$Q173 -> 0 | AA42: ='销售帐 - ZHEMAX'!$Q176 -> 0 | AB42: ='销售帐 - ZHEMAX'!$Q179 -> 0 | AC42: ='销售帐 - ZHEMAX'!$Q198 -> 0
A43: ZHEMAX | B43: 财玛克思 | C43: 博莱多收款 | D43: =SUM(E43:P43) -> 0 | E43: =ROUND(R43*$R$3,2) -> 0 | F43: =ROUND(S43*$S$3,2) -> 0 | G43: =ROUND(T43*$T$3,2) -> 0 | H43: =ROUND(U43*$U$3,2) -> 0 | I43: =ROUND(V43*V$3,2) -> 0 | J43: =ROUND(W43*W$3,2) -> 0 | K43: =ROUND(X43*X$3,2) -> 0 | L43: =ROUND(Y43*Y$3,2) -> 0 | M43: =ROUND(Z43*Z$3,2) -> 0 | N43: =ROUND(AC43*AC$3,2) -> 0 | O43: =ROUND(AB43*AB$3,2) -> 0 | P43: =ROUND(AC43*AC$3,2) -> 0 | Q43: =SUM(R43:AC43) -> 0 | R43: ='销售帐 - ZHEMAX'!$O5 -> 0 | S43: ='销售帐 - ZHEMAX'!$O8 -> 0 | T43: ='销售帐 - ZHEMAX'!O15 -> 0 | U43: ='销售帐 - ZHEMAX'!$O26 -> 0 | V43: ='销售帐 - ZHEMAX'!$O79 -> 0 | W43: ='销售帐 - ZHEMAX'!$O128 -> 0 | X43: ='销售帐 - ZHEMAX'!$O143 -> 0 | Y43: ='销售帐 - ZHEMAX'!$O166 -> 0 | Z43: ='销售帐 - ZHEMAX'!$O173 -> 0 | AA43: ='销售帐 - ZHEMAX'!$O176 -> 0 | AB43: ='销售帐 - ZHEMAX'!$O179 -> 0 | AC43: ='销售帐 - ZHEMAX'!$O198 -> 0
A44: ZHEMAX | B44: 财玛克思 | C44: 刷卡收款 | D44: =SUM(E44:P44) -> 0 | E44: =ROUND(R44*$R$3,2) -> 0 | F44: =ROUND(S44*$S$3,2) -> 0 | G44: =ROUND(T44*$T$3,2) -> 0 | H44: =ROUND(U44*$U$3,2) -> 0 | I44: =ROUND(V44*V$3,2) -> 0 | J44: =ROUND(W44*W$3,2) -> 0 | K44: =ROUND(X44*X$3,2) -> 0 | L44: =ROUND(Y44*Y$3,2) -> 0 | M44: =ROUND(Z44*Z$3,2) -> 0 | N44: =ROUND(AC44*AC$3,2) -> 0 | O44: =ROUND(AB44*AB$3,2) -> 0 | P44: =ROUND(AC44*AC$3,2) -> 0 | Q44: =SUM(R44:AC44) -> 0 | R44: ='销售帐 - ZHEMAX'!$P5 -> 0 | S44: ='销售帐 - ZHEMAX'!$P8 -> 0 | T44: ='销售帐 - ZHEMAX'!P15 -> 0 | U44: ='销售帐 - ZHEMAX'!$P26 -> 0 | V44: ='销售帐 - ZHEMAX'!$P79 -> 0 | W44: ='销售帐 - ZHEMAX'!$P128 -> 0 | X44: ='销售帐 - ZHEMAX'!$P143 -> 0 | Y44: ='销售帐 - ZHEMAX'!$P166 -> 0 | Z44: ='销售帐 - ZHEMAX'!$P173 -> 0 | AA44: ='销售帐 - ZHEMAX'!$P176 -> 0 | AB44: ='销售帐 - ZHEMAX'!$P179 -> 0 | AC44: ='销售帐 - ZHEMAX'!$P198 -> 0
A45: ZHEMAX | B45: 财玛克思 | C45: 现款-现金、银行存款 | D45: =SUM(E45:P45) -> 0 | E45: =ROUND(R45*$R$3,2) -> 0 | F45: =ROUND(S45*$S$3,2) -> 0 | G45: =ROUND(T45*$T$3,2) -> 0 | H45: =ROUND(U45*$U$3,2) -> 0 | I45: =ROUND(V45*V$3,2) -> 0 | J45: =ROUND(W45*W$3,2) -> 0 | K45: =ROUND(X45*X$3,2) -> 0 | L45: =ROUND(Y45*Y$3,2) -> 0 | M45: =ROUND(Z45*Z$3,2) -> 0 | N45: =ROUND(AC45*AC$3,2) -> 0 | O45: =ROUND(AB45*AB$3,2) -> 0 | P45: =ROUND(AC45*AC$3,2) -> 0 | Q45: =SUM(R45:AC45) -> 0 | R45: ='销售帐 - ZHEMAX'!$M5+'销售帐 - ZHEMAX'!$N5 -> 0 | S45: ='销售帐 - ZHEMAX'!$M8+'销售帐 - ZHEMAX'!$N8 -> 0 | T45: ='销售帐 - ZHEMAX'!M15+'销售帐 - ZHEMAX'!N15 -> 0 | U45: ='销售帐 - ZHEMAX'!$M26+'销售帐 - ZHEMAX'!$N26 -> 0 | V45: ='销售帐 - ZHEMAX'!$M79+'销售帐 - ZHEMAX'!$N79 -> 0 | W45: ='销售帐 - ZHEMAX'!$M128+'销售帐 - ZHEMAX'!$N128 -> 0 | X45: ='销售帐 - ZHEMAX'!$M143+'销售帐 - ZHEMAX'!$N143 -> 0 | Y45: ='销售帐 - ZHEMAX'!$M166+'销售帐 - ZHEMAX'!$N166 -> 0 | Z45: ='销售帐 - ZHEMAX'!$M173+'销售帐 - ZHEMAX'!$N173 -> 0 | AA45: ='销售帐 - ZHEMAX'!$M176+'销售帐 - ZHEMAX'!$N176 -> 0 | AB45: ='销售帐 - ZHEMAX'!$M179+'销售帐 - ZHEMAX'!$N179 -> 0 | AC45: ='销售帐 - ZHEMAX'!$M198+'销售帐 - ZHEMAX'!$N198 -> 0

Sheet 销售帐 -ARGOTECH
A1: 2026年巴西销售发票总帐(ARGOTECH阿家达 )
A2: 阿家达 | D2: =L2+R2-M2-N2-O2-P2 -> -9.0221874e-10 | F2: =SUBTOTAL(9,F4:F4284) -> 2587 | H2: =SUBTOTAL(9,H4:H4284) -> 2190983.5 | J2: =SUBTOTAL(9,J4:J4284) -> 2194448.6 | K2: =SUBTOTAL(9,K4:K4284) -> 2587 | L2: =SUBTOTAL(9,L4:L4284) -> 2192159.6 | M2: =SUBTOTAL(9,M4:M4284) -> 4939 | N2: =SUBTOTAL(9,N4:N4284) -> 701289.33 | O2: =SUBTOTAL(9,O4:O4284) -> 1282973.4 | P2: =SUBTOTAL(9,P4:P4284) -> 205246.87 | R2: =SUBTOTAL(9,R4:R4284) -> 2289.03 | T2: =J2-L2-R2 -> 2.6147973e-10
A3: 发生日期 | B3: 销售单号 | C3: 编码 | D3: 商品型号 | E3: 客户单位 | F3: 数量 | G3: 单价 | H3: 金额 | I3: 税率 | J3: 含税金额 | K3: 数量 | L3: 总金额 | M3: 现金 | N3: 银行存款 | O3: BOLETO | P3: 刷卡/COM | Q3: 退货 DEVOLUÇÃO | R3: 卡费/Taxa de cartão de | S3: 卡率 | T3: 备注/OBSERVAÇÕES
A4: 46027 | B4: 2328/2111 | D4: 销售 | E4: Equipodonto Assistencia | K4: 1 | L4: =M4+P4+O4+N4-R4 -> 1135.75 | N4: 1135.75 | T4: 05/01/2026- Argotech | BC4: 2100002016547 | BD4: 550W
A5: 46027 | B5: 2328/2111 | C5: 2100002016998 | D5: =VLOOKUP(C5,$BC:$BD,2,0) -> 1500W-4 | E5: EQUIPODONTO ASSISTENCIA TECNICA ODONTOLOGICA LTDA | F5: 1 | G5: 1100 | H5: =F5*G5 -> 1100 | I5: 0.0325 | J5: =ROUND(H5+H5*I5,2) -> 1135.75 | L5: =M5+P5+O5+N5-R5 -> 0 | BC5: 2100002016608 | BD5: 1200W-2
A6: 46027 | B6: 2330/2112 | D6: 销售 | E6: WG Odonto Manutencao | H6: =F6*G6 -> 0 | J6: =ROUND((H6*I6+H6),2) -> 0 | K6: 1 | L6: =M6+P6+O6+N6-R6 -> 552.22 | N6: 552.22 | T6: 05/01/2026-Argotech | BC6: 2100002016622 | BD6: 1100*2-50L
A7: 46027 | B7: 2330/2112 | C7: 2100002017018 | D7: =VLOOKUP(C7,$BC:$BD,2,0) -> COMP 750W 220V | E7: WG ODONTO MANUTENCAO E ASSISTENCIA TECNICA LTDA | F7: 1 | G7: 534.84 | H7: =F7*G7 -> 534.84 | I7: 0.0325 | J7: =ROUND(H7+H7*I7,2) -> 552.22 | L7: =M7+P7+O7+N7-R7 -> 0 | BC7: 2100002016639 | BD7: 配件
A8: 46027 | B8: 2332/2113 | D8: 销售 | E8: Felipe Martiniano | H8: =F8*G8 -> 0 | J8: =ROUND(H8+H8*I8,2) -> 0 | K8: 1 | L8: =M8+P8+O8+N8-R8 -> 583 | N8: =484.5+98.5 -> 583 | T8: 05/01/2026-Argotech | BC8: 2100002016691 | BD8: 1200-8L
A9: 46027 | B9: 2332/2113 | C9: 2100002017001 | D9: =VLOOKUP(C9,$BC:$BD,2,0) -> COMP 550W 110V | E9: FELIPE MARTINIANO ASSUNCAO | F9: 1 | G9: 469.25 | H9: =F9*G9 -> 469.25 | I9: 0.0325 | J9: =ROUND(H9+H9*I9,2)+98.5 -> 583 | L9: =M9+P9+O9+N9-R9 -> 0 | BC9: 2100002016738 | BD9: 1100-25L
A10: 46027 | B10: 2335/2114 | D10: 销售 | E10: VRV Ferramentas | H10: =F10*G10 -> 0 | J10: =ROUND(H10+H10*I10,2) -> 0 | K10: 1 | L10: =M10+P10+O10+N10-R10 -> 645.33 | P10: 661 | R10: =ROUND(P10*S10,2) -> 15.67 | S10: 0.0237 | T10: 05/01/2026-Argotech | BC10: 2100002016745 | BD10: 1100*2 50L
A11: 46027 | B11: 2335/2114 | C11: 2100002017032 | D11: =VLOOKUP(C11,$BC:$BD,2,0) -> 1100 8L | E11: VRV FERRAMENTAS | F11: 1 | G11: 661 | H11: =F11*G11 -> 661 | J11: =ROUND(H11+H11*I11,2) -> 661 | L11: =M11+P11+O11+N11-R11 -> 0 | BC11: 2100002016752 | BD11: 1200 25L
A12: 46028 | B12: 2333/2115 | D12: 销售-内部 | E12: Norte Tools | H12: =F12*G12 -> 0 | J12: =ROUND(H12+H12*I12,2) -> 0 | T12: 07/04/2026-Argotech | BC12: 2100002016769 | BD12: 1100- 8L 127V
A13: 46028 | B13: 2337/2116 | D13: 销售 | E13: Odontek Equipamentos | H13: =F13*G13 -> 0 | J13: =ROUND(H13+H13*I13,2) -> 0 | K13: 9 | L13: =M13+P13+O13+N13-R13 -> 570 | N13: 570 | T13: 06/01/2026-Argotech | BC13: 2100002016790 | BD13: 1100 25L
A14: 46028 | B14: 2337/2116 | C14: 2100002017414 | D14: =VLOOKUP(C14,$BC:$BD,2,0) -> 配件 | E14: ODONTEK EQUIPAMENTOS ODONTOLOGICOS LTDA | F14: 1 | G14: 450 | H14: =F14*G14 -> 450 | J14: =ROUND(H14+H14*I14,2) -> 450 | L14: =M14+P14+O14+N14-R14 -> 0 | BC14: 2100002016837 | BD14: 1200*2-50L
A15: 46028 | B15: 2337/2116 | C15: 2100002016639 | D15: =VLOOKUP(C15,$BC:$BD,2,0) -> 配件 | E15: ODONTEK EQUIPAMENTOS ODONTOLOGICOS LTDA | F15: 8 | G15: 15 | H15: =F15*G15 -> 120 | J15: =ROUND(H15+H15*I15,2) -> 120 | L15: =M15+P15+O15+N15-R15 -> 0 | BC15: 2100002016875 | BD15: USK-750W
A16: 46028 | B16: 2329/2117 | D16: 销售 | E16: Ferragens Home | H16: =F16*G16 -> 0 | J16: =ROUND(H16+H16*I16,2) -> 0 | K16: 5 | L16: =M16+P16+O16+N16-R16 -> 4462.71 | P16: 4495.53 | R16: =ROUND(P16*S16,2) -> 32.82 | S16: 0.0073 | T16: 06/01/2026-Argotech | BC16: 2100002016899 | BD16: COMP-550W
A17: 46028 | B17: 2329/2117 | C17: 2100002017049 | D17: =VLOOKUP(C17,$BC:$BD,2,0) -> 1100*2 50L | E17: FERRAGENS HOME HOUSE COM. DE EQUIP. E MAQUINAS LTDA | F17: 1 | G17: 1524 | H17: =F17*G17 -> 1524 | J17: =ROUND(H17+H17*I17,2) -> 1524 | L17: =M17+P17+O17+N17-R17 -> 0 | BC17: 2100002016905 | BD17: COMP-750W
A18: 46028 | B18: 2329/2117 | C18: 2100002017469 | D18: =VLOOKUP(C18,$BC:$BD,2,0) -> BM-1902 25L 127V | E18: FERRAGENS HOME HOUSE COM. DE EQUIP. E MAQUINAS LTDA | F18: 1 | G18: 640 | H18: =F18*G18 -> 640 | J18: =ROUND(H18+H18*I18,2) -> 640 | L18: =M18+P18+O18+N18-R18 -> 0 | BC18: 2100002016912 | BD18: BM-1902-25L/127V
A19: 46028 | B19: 2329/2117 | C19: 2100002016776 | D19: =VLOOKUP(C19,$BC:$BD,2,0) -> 1200- 8L | E19: FERRAGENS HOME HOUSE COM. DE EQUIP. E MAQUINAS LTDA | F19: 2 | G19: 714.57 | H19: =F19*G19 -> 1429.14 | J19: =ROUND(H19+H19*I19,2) -> 1429.14 | L19: =M19+P19+O19+N19-R19 -> 0 | BC19: 2100002016967 | BD19: BM-1902-25L/127V
A20: 46028 | B20: 2329/2117 | C20: 2100002016752 | D20: =VLOOKUP(C20,$BC:$BD,2,0) -> 1200 25L | E20: FERRAGENS HOME HOUSE COM. DE EQUIP. E MAQUINAS LTDA | F20: 1 | G20: 902.39 | H20: =F20*G20 -> 902.39 | J20: =ROUND(H20+H20*I20,2) -> 902.39 | L20: =M20+P20+O20+N20-R20 -> 0 | BC20: 2100002016929 | BD20: BM-1902-25L
A21: 46028 | B21: 2336/2118 | D21: 取消 | E21: Clubemais Saude | H21: =F21*G21 -> 0 | J21: =ROUND(H21+H21*I21,2) -> 0 | L21: =M21+P21+O21+N21-R21 -> 0 | BC21: 2100002016974 | BD21: BM-1902-25L
A22: 46028 | B22: 2343/2119 | D22: 销售 | E22: Thiago Lourenço | H22: =F22*G22 -> 0 | J22: =ROUND(H22+H22*I22,2) -> 0 | K22: 2 | L22: =M22+P22+O22+N22-R22 -> 1206.4 | N22: 1206.4 | T22: 06/01/2026-Argotech | BC22: 2100002017124 | BD22: BM-1902-25L 220V
A23: 46028 | B23: 2343/2119 | C23: 2100002017018 | D23: =VLOOKUP(C23,$BC:$BD,2,0) -> COMP 750W 220V | E23: THIAGO LOURENCO DO AMARAL | F23: 2 | G23: 603.2 | H23: =F23*G23 -> 1206.4 | J23: =ROUND(H23+H23*I23,2) -> 1206.4 | L23: =M23+P23+O23+N23-R23 -> 0 | BC23: 2100002017131 | BD23: BM-1902 25L 127V
A24: 46028 | B24: 2344/2120 | D24: 销售 | E24: Jeferson Antonio | H24: =F24*G24 -> 0 | J24: =ROUND(H24+H24*I24,2) -> 0 | K24: 1 | L24: =M24+P24+O24+N24-R24 -> 390.52 | P24: 400 | R24: =ROUND(P24*S24,2) -> 9.48 | S24: 0.0237 | T24: 06/01/2026-Argotech | BC24: 2100002017193 | BD24: BM-1902-25L 220V
A25: 46028 | B25: 2344/2120 | C25: 2100002017414 | D25: =VLOOKUP(C25,$BC:$BD,2,0) -> 配件 | E25: JEFERSON ANTONIO PEREIRA ----1100 -220 V | F25: 1 | G25: 400 | H25: =F25*G25 -> 400 | J25: =ROUND(H25+H25*I25,2) -> 400 | L25: =M25+P25+O25+N25-R25 -> 0 | BC25: 2100002017285 | BD25: BM-1902 25L 127V
A26: 46027 | B26: 2334/2121 | D26: 销售 | E26: Protec Comercio | H26: =F26*G26 -> 0 | J26: =ROUND(H26+H26*I26,2) -> 0 | K26: 7 | L26: =M26+P26+O26+N26-R26 -> 4736.39 | N26: 4736.39 | T26: 06/01/2026-Argotech | BC26: 2100002017247 | BD26: BM-1902-25L 220V
A27: 46028 | B27: 2334/2121 | C27: 2100002016615 | D27: =VLOOKUP(C27,$BC:$BD,2,0) -> 1500W-2 | E27: PROTEC COMERCIO E MANUTENCAO DE EQUIPAMENTOS DE SAUDE LTDA | F27: 6 | G27: 639 | H27: =F27*G27 -> 3834 | J27: =ROUND(H27+H27*I27,2) -> 3834 | L27: =M27+P27+O27+N27-R27 -> 0 | BC27: 2100002017469 | BD27: BM-1902 25L 127V
A28: 46028 | B28: 2334/2121 | C28: 2100002016752 | D28: =VLOOKUP(C28,$BC:$BD,2,0) -> 1200 25L | E28: PROTEC COMERCIO E MANUTENCAO DE EQUIPAMENTOS DE SAUDE LTDA | F28: 1 | G28: 902.39 | H28: =F28*G28 -> 902.39 | J28: =ROUND(H28+H28*I28,2) -> 902.39 | L28: =M28+P28+O28+N28-R28 -> 0 | BC28: 2100002017292 | BD28: BM-1902 25L
A29: 46028 | B29: 2342/2122 | D29: 销售 | E29: WG Odonto Manutencao | H29: =F29*G29 -> 0 | J29: =ROUND(H29+H29*I29,2) -> 0 | K29: 1 | L29: =M29+P29+O29+N29-R29 -> 552.22 | N29: 552.22 | T29: 06/01/2026-Argotech | BC29: 2100002017520 | BD29: BM-1902-25L 220V E
A30: 46028 | B30: 2342/2122 | C30: 2100002017018 | D30: =VLOOKUP(C30,$BC:$BD,2,0) -> COMP 750W 220V | E30: WG ODONTO MANUTENCAO E ASSISTENCIA TECNICA LTDA | F30: 1 | G30: 534.84 | H30: =F30*G30 -> 534.84 | I30: 0.0325 | J30: =ROUND(H30+H30*I30,2) -> 552.22 | L30: =M30+P30+O30+N30-R30 -> 0 | BC30: 2100002017544 | BD30: BM-1902-50L 220V E
A31: 46029 | B31: 2345/2123 | D31: 销售 | E31: PALACIO DAS FERRAMENTAS | H31: =F31*G31 -> 0 | J31: =ROUND(H31+H31*I31,2) -> 0 | K31: 20 | L31: =M31+P31+O31+N31-R31 -> 13180 | O31: 13180 | T31: 06/02/2026-Argotech | BC31: 2100002017568 | BD31: BM-1902-50L 127V E
A32: 46029 | B32: 2345/2123 | C32: 2100002017032 | D32: =VLOOKUP(C32,$BC:$BD,2,0) -> 1100 8L | E32: PALACIO DAS FERRAMENTAS E PARAFUSOS LTDA | F32: 20 | G32: 659 | H32: =F32*G32 -> 13180 | J32: =ROUND(H32+H32*I32,2) -> 13180 | L32: =M32+P32+O32+N32-R32 -> 0 | BC32: 2100002017537 | BD32: BM-1902-50L 127V E
A33: 46029 | B33: 2347/2124 | D33: 销售 | E33: Ferragens Home | H33: =F33*G33 -> 0 | J33: =ROUND(H33+H33*I33,2) -> 0 | K33: 6 | L33: =M33+P33+O33+N33-R33 -> 4256.12 | P33: 4287.42 | R33: =ROUND(P33*S33,2) -> 31.3 | S33: 0.0073 | T33: 07/01/2026-Argotech | BC33: 2100002016981 | BD33: 1500-50L
A34: 46029 | B34: 2347/2124 | C34: 2100002016776 | D34: =VLOOKUP(C34,$BC:$BD,2,0) -> 1200- 8L | E34: FERRAGENS HOME HOUSE COM. DE EQUIP. E MAQUINAS LTDA | F34: 6 | G34: 714.57 | H34: =F34*G34 -> 4287.42 | J34: =ROUND(H34+H34*I34,2) -> 4287.42 | L34: =M34+P34+O34+N34-R34 -> 0 | BC34: 2100002017414 | BD34: 配件
A35: 46029 | B35: 2350/2125 | D35: 销售 | E35: francisco Norberto | H35: =F35*G35 -> 0 | J35: =ROUND(H35+H35*I35,2) -> 0 | K35: 1 | L35: =M35+P35+O35+N35-R35 -> 1050.28 | P35: 1058 | R35: =ROUND(P35*S35,2) -> 7.72 | S35: 0.0073 | T35: 07/01/2026-Argotech | BC35: 2100002017490 | BD35: 1500W-4
A36: 46029 | B36: 2350/2125 | C36: 2100002017490 | D36: =VLOOKUP(C36,$BC:$BD,2,0) -> 1500W-4 | E36: FRANCISCO NORBERTO DA SILVA | F36: 1 | G36: 1058 | H36: =F36*G36 -> 1058 | J36: =ROUND(H36+H36*I36,2) -> 1058 | L36: =M36+P36+O36+N36-R36 -> 0 | BC36: 6973858620017 | BD36: 550-8L
A37: 46028 | B37: 2341/2126 | D37: 销售 | E37: Assistecdonto LTDA | H37: =F37*G37 -> 0 | J37: =ROUND(H37+H37*I37,2) -> 0 | K37: 22 | L37: =M37+P37+O37+N37-R37 -> 5354.93 | N37: 5354.93 | T37: 07/01/2026-Argotech | BC37: 2100002017810 | BD37: 550-8L
A38: 46029 | B38: 2341/2126 | C38: 2100002017148 | D38: =VLOOKUP(C38,$BC:$BD,2,0) -> 1500W-4 | E38: ASSISTECDONTO LTDA | F38: 2 | G38: 1058 | H38: =F38*G38 -> 2116 | I38: 0.0325 | J38: =ROUND(H38+H38*I38,2) -> 2184.77 | L38: =M38+P38+O38+N38-R38 -> 0 | BC38: 2100002017803 | BD38: 750-25L
A39: 46029 | B39: 2341/2126 | C39: 2100002016875 | D39: =VLOOKUP(C39,$BC:$BD,2,0) -> USK-750W | E39: ASSISTECDONTO LTDA | F39: 4 | G39: 632 | H39: =F39*G39 -> 2528 | I39: 0.0325 | J39: =ROUND(H39+H39*I39,2) -> 2610.16 | L39: =M39+P39+O39+N39-R39 -> 0 | BC39: 6973858620084 | BD39: 750-25L
A40: 46029 | B40: 2341/2126 | C40: 2100002017216 | D40: 配件 | E40: ASSISTECDONTO LTDA | F40: 10 | G40: 20 | H40: =F40*G40 -> 200 | J40: =ROUND(H40+H40*I40,2) -> 200 | L40: =M40+P40+O40+N40-R40 -> 0 | BC40: 2100002017483 | BD40: 750-25L
A41: 46029 | B41: 2341/2126 | C41: 2100002016639 | D41: =VLOOKUP(C41,$BC:$BD,2,0) -> 配件 | E41: ASSISTECDONTO LTDA | F41: 6 | G41: 60 | H41: =F41*G41 -> 360 | J41: =ROUND(H41+H41*I41,2) -> 360 | L41: =M41+P41+O41+N41-R41 -> 0 | BC41: 2100002017513 | BD41: 750-25L
A42: 46030 | B42: 2352/2127 | D42: 销售 | E42: VT FERRAMENTAS | H42: =F42*G42 -> 0 | J42: =ROUND(H42+H42*I42,2) -> 0 | K42: 1 | L42: =M42+P42+O42+N42-R42 -> 665 | N42: 665 | T42: 08/01/2026-Argotech | BC42: 2100002017650 | BD42: 750-30L
A43: 46030 | B43: 2352/2127 | C43: 2100002017032 | D43: =VLOOKUP(C43,$BC:$BD,2,0) -> 1100 8L | E43: VT FERRAMENTAS LTDA | F43: 1 | G43: 665 | H43: =F43*G43 -> 665 | J43: =ROUND(H43+H43*I43,2) -> 665 | L43: =M43+P43+O43+N43-R43 -> 0 | BC43: 6973858620024 | BD43: 550*2-50L
A44: 46029 | B44: 2349/2128 | D44: 销售 | E44: MP2 MAQUINAS | H44: =F44*G44 -> 0 | J44: =ROUND(H44+H44*I44,2) -> 0 | K44: 1 | L44: =M44+P44+O44+N44-R44 -> 1749.06 | N44: 1749.06 | T44: 07/01/2026-Argotech | BC44: 6973858620048 | BD44: 1200 -25L
A45: 46030 | B45: 2349/2128 | C45: 2100002016936 | D45: =VLOOKUP(C45,$BC:$BD,2,0) -> 1500 50L | E45: MP2 MAQUINAS E FERRAMENTAS LTDA | F45: 1 | G45: 1694 | H45: =F45*G45 -> 1694 | I45: 0.0325 | J45: =ROUND(H45+H45*I45,2) -> 1749.06 | L45: =M45+P45+O45+N45-R45 -> 0 | BC45: 6973858620055 | BD45: 1200*2-50L
A46: 46029 | B46: 2346/2129 | D46: 销售 | E46: GALLARDO COMERCIO | H46: =F46*G46 -> 0 | J46: =ROUND(H46+H46*I46,2) -> 0 | K46: 7 | L46: =M46+P46+O46+N46-R46 -> 7439 | N46: 7439 | T46: 07/01/2026-Argotech | BC46: 6973858620085 | BD46: 1100-8L
A47: 46030 | B47: 2346/2129 | C47: 2100002017483 | D47: =VLOOKUP(C47,$BC:$BD,2,0) -> 750-25L | E47: GALLARDO COMERCIO DE EQUIPAMENTOS ODONTO MEDICOS LTDA | F47: 5 | G47: 846 | H47: =F47*G47 -> 4230 | J47: =ROUND(H47+H47*I47,2) -> 4230 | L47: =M47+P47+O47+N47-R47 -> 0 | BC47: 6973858620086 | BD47: 1100-25L
A48: 46030 | B48: 2346/2129 | C48: 2100002017476 | D48: =VLOOKUP(C48,$BC:$BD,2,0) -> 550*2-50L | E48: GALLARDO COMERCIO DE EQUIPAMENTOS ODONTO MEDICOS LTDA | F48: 1 | G48: 1685 | H48: =F48*G48 -> 1685 | J48: =ROUND(H48+H48*I48,2) -> 1685 | L48: =M48+P48+O48+N48-R48 -> 0 | BC48: 6973858620087 | BD48: 1100*2-50L
A49: 46030 | B49: 2346/2129 | C49: 2100002017049 | D49: =VLOOKUP(C49,$BC:$BD,2,0) -> 1100*2 50L | E49: GALLARDO COMERCIO DE EQUIPAMENTOS ODONTO MEDICOS LTDA | F49: 1 | G49: 1524 | H49: =F49*G49 -> 1524 | J49: =ROUND(H49+H49*I49,2) -> 1524 | L49: =M49+P49+O49+N49-R49 -> 0 | BC49: 2100002016844 | BD49: USK-550W-220V
A50: 46030 | B50: 2357/2130 | D50: 销售 | E50: CARVALHO MARMORES | H50: =F50*G50 -> 0 | J50: =ROUND(H50+H50*I50,2) -> 0 | K50: 7 | L50: =M50+P50+O50+N50-R50 -> 210 | N50: 210 | T50: 08/01/2026-Argotech | BC50: 2100002016882 | BD50: USK-550W-127V
A51: 46030 | B51: 2357/2130 | C51: 2100002017414 | D51: =VLOOKUP(C51,$BC:$BD,2,0) -> 配件 | E51: CARVALHO MARMORES E GRANITOS LTDA | F51: 2 | G51: 15 | H51: =F51*G51 -> 30 | J51: =ROUND(H51+H51*I51,2) -> 30 | L51: =M51+P51+O51+N51-R51 -> 0 | BC51: 2100002016615 | BD51: 1500W-2
A52: 46030 | B52: 2357/2130 | C52: 2100002017414 | D52: =VLOOKUP(C52,$BC:$BD,2,0) -> 配件 | E52: CARVALHO MARMORES E GRANITOS LTDA | F52: 2 | G52: 40 | H52: =F52*G52 -> 80 | J52: =ROUND(H52+H52*I52,2) -> 80 | L52: =M52+P52+O52+N52-R52 -> 0 | BC52: 2100002017018 | BD52: COMP 750W 220V
A53: 46030 | B53: 2357/2130 | C53: 2100002017414 | D53: =VLOOKUP(C53,$BC:$BD,2,0) -> 配件 | E53: CARVALHO MARMORES E GRANITOS LTDA | F53: 2 | G53: 10 | H53: =F53*G53 -> 20 | J53: =ROUND(H53+H53*I53,2) -> 20 | L53: =M53+P53+O53+N53-R53 -> 0 | BC53: 2100002017001 | BD53: COMP 550W 110V
A54: 46030 | B54: 2357/2130 | C54: 2100002017414 | D54: =VLOOKUP(C54,$BC:$BD,2,0) -> 配件 | E54: CARVALHO MARMORES E GRANITOS LTDA | F54: 1 | G54: 80 | H54: =F54*G54 -> 80 | J54: =ROUND(H54+H54*I54,2) -> 80 | L54: =M54+P54+O54+N54-R54 -> 0 | BC54: 2100002017049 | BD54: 1100*2 50L
A55: 46030 | B55: 2354/2131 | D55: 销售 | E55: Ferragens Home | H55: =F55*G55 -> 0 | J55: =ROUND(H55+H55*I55,2) -> 0 | K55: 3 | L55: =M55+P55+O55+N55-R55 -> 2110.48 | P55: 2126 | R55: =ROUND(P55*S55,2) -> 15.52 | S55: 0.0073 | T55: 08/01/2026-Argotech | BC55: 2100002017162 | BD55: COMP750W 220V
A56: 46030 | B56: 2354/2131 | C56: 2100002017483 | D56: =VLOOKUP(C56,$BC:$BD,2,0) -> 750-25L | E56: FERRAGENS HOME HOUSE COM. DE EQUIP. E MAQUINAS LTDA | F56: 1 | G56: 846 | H56: =F56*G56 -> 846 | J56: =ROUND(H56+H56*I56,2) -> 846 | L56: =M56+P56+O56+N56-R56 -> 0 | BC56: 2100002017025 | BD56: 1100 8L 127V
A57: 46030 | B57: 2354/2131 | C57: 2100002017469 | D57: =VLOOKUP(C57,$BC:$BD,2,0) -> BM-1902 25L 127V | E57: FERRAGENS HOME HOUSE COM. DE EQUIP. E MAQUINAS LTDA | F57: 2 | G57: 640 | H57: =F57*G57 -> 1280 | J57: =ROUND(H57+H57*I57,2) -> 1280 | L57: =M57+P57+O57+N57-R57 -> 0 | BC57: 2100002017032 | BD57: 1100 8L
A58: 46030 | B58: 2356/2132 | D58: 销售 | E58: KLM LTDA | H58: =F58*G58 -> 0 | J58: =ROUND(H58+H58*I58,2) -> 0 | K58: 1 | L58: =M58+P58+O58+N58-R58 -> 1098.5 | N58: 1098.5 | T58: 07/01/2026-Argotech | BC58: 2100002017056 | BD58: 1200 8L
A59: 46030 | B59: 2356/2132 | C59: 2100002016998 | D59: =VLOOKUP(C59,$BC:$BD,2,0) -> 1500W-4 | E59: KLM LTDA | F59: 1 | G59: 1063.92 | H59: =F59*G59 -> 1063.92 | I59: 0.0325 | J59: =ROUND(H59+H59*I59,2) -> 1098.5 | L59: =M59+P59+O59+N59-R59 -> 0 | BC59: 2100002016998 | BD59: 1500W-4
A60: 46030 | B60: 2358/2133 | D60: 销售 | E60: DENTAL TEC | H60: =F60*G60 -> 0 | J60: =ROUND(H60+H60*I60,2) -> 0 | K60: 3 | L60: =M60+P60+O60+N60-R60 -> 3377 | N60: 3377 | T60: 08/01/2026-Argotech | BC60: 2100002017148 | BD60: 1500W-4
A61: 46030 | B61: 2358/2133 | C61: 2100002017483 | D61: =VLOOKUP(C61,$BC:$BD,2,0) -> 750-25L | E61: DENTAL TEC COMERCIO E SERVICOS LTDA | F61: 2 | G61: 846 | H61: =F61*G61 -> 1692 | J61: =ROUND(H61+H61*I61,2) -> 1692 | L61: =M61+P61+O61+N61-R61 -> 0 | BC61: 2100002016936 | BD61: 1500 50L
A62: 46030 | B62: 2358/2133 | C62: 2100002017476 | D62: =VLOOKUP(C62,$BC:$BD,2,0) -> 550*2-50L | E62: DENTAL TEC COMERCIO E SERVICOS LTDA | F62: 1 | G62: 1685 | H62: =F62*G62 -> 1685 | J62: =ROUND(H62+H62*I62,2) -> 1685 | L62: =M62+P62+O62+N62-R62 -> 0 | BC62: 2100002017117 | BD62: 1100 2-50L
A63: 46030 | B63: 2338/2134 | D63: 销售 | E63: LOJAS DAS FERRAMENTAS | H63: =F63*G63 -> 0 | J63: =ROUND(H63+H63*I63,2) -> 0 | K63: 2 | L63: =M63+P63+O63+N63-R63 -> 1284 | N63: 1284 | T63: 08/01/2026-Argotech | BC63: 2100002017155 | BD63: COMP 550W 220V
A64: 46030 | B64: 2338/2134 | C64: 2100002017193 | D64: =VLOOKUP(C64,$BC:$BD,2,0) -> BM-1902-25L 220V | E64: LOJAO DAS FERRAMENTAS LTDA | F64: 2 | G64: 642 | H64: =F64*G64 -> 1284 | J64: =ROUND(H64+H64*I64,2) -> 1284 | L64: =M64+P64+O64+N64-R64 -> 0 | BC64: 2100002017476 | BD64: 550*2-50L
A65: 46029 | B65: 2311/2135 | D65: 销售 | E65: J C NEPOMUCENO | H65: =F65*G65 -> 0 | J65: =ROUND(H65+H65*I65,2) -> 0 | K65: 20 | L65: =M65+P65+O65+N65-R65 -> 563.54 | N65: 563.54 | T65: 07/01/2026-Argotech | BC65: 2100002017209 | BD65: 550*2-50L
A66: 46030 | B66: 2311/2135 | C66: 2100002017179 | D66: =VLOOKUP(C66,$BC:$BD,2,0) -> E71T-GS 1KG 0.8MM | E66: J C NEPOMUCENO FERRAMENTAS | F66: 20 | G66: 27.29 | H66: =F66*G66 -> 545.8 | I66: 0.0325 | J66: =ROUND(H66+H66*I66,2) -> 563.54 | L66: =M66+P66+O66+N66-R66 -> 0 | BC66: 2100002017230 | BD66: 1200*2-50L
A67: 46030 | B67: 2353/2136 | D67: 销售 | E67: EQUIPAR PRODUTOS | H67: =F67*G67 -> 0 | J67: =ROUND(H67+H67*I67,2) -> 0 | K67: 3 | L67: =M67+P67+O67+N67-R67 -> 4572 | N67: 4572 | T67: 08/01/2026-Argotech | BC67: 2100002017308 | BD67: 1500 50L
A68: 46030 | B68: 2353/2136 | C68: 2100002017049 | D68: =VLOOKUP(C68,$BC:$BD,2,0) -> 1100*2 50L | E68: EQUIPAR PRODUTOS MEDICOS HOSPITALARES LTDA | F68: 3 | G68: 1524 | H68: =F68*G68 -> 4572 | J68: =ROUND(H68+H68*I68,2) -> 4572 | L68: =M68+P68+O68+N68-R68 -> 0 | BC68: 0002 | BD68: E71T-GS 1KG 1MM
A69: 46030 | B69: 2365/2137 | D69: 销售 | E69: Rubens De Almeida | H69: =F69*G69 -> 0 | J69: =ROUND(H69+H69*I69,2) -> 0 | K69: 1 | L69: =M69+P69+O69+N69-R69 -> 1487.06 | P69: 1498 | R69: =ROUND(P69*S69,2) -> 10.94 | S69: 0.0073 | T69: 08/01/2026-Argotech | BC69: 2100002017452 | BD69: 1200*2-50L
A70: 46030 | B70: 2365/2137 | C70: 2100002017452 | D70: =VLOOKUP(C70,$BC:$BD,2,0) -> 1200*2-50L | E70: RUBENS DE ALMEIDA GIL | F70: 1 | G70: 1498 | H70: =F70*G70 -> 1498 | J70: =ROUND(H70+H70*I70,2) -> 1498 | L70: =M70+P70+O70+N70-R70 -> 0 | BC70: 2100002017179 | BD70: E71T-GS 1KG 0.8MM
A71: 46030 | B71: /2138 | D71: 进口发票 | E71: IMPORTAÇAO | H71: =F71*G71 -> 0 | J71: =ROUND(H71+H71*I71,2) -> 0 | L71: =M71+P71+O71+N71-R71 -> 0 | BC71: 2100002017254 | BD71: 1500 - 50L
A72: 46030 | B72: /2139 | D72: 进口发票 | E72: IMPORTAÇAO | H72: =F72*G72 -> 0 | J72: =ROUND(H72+H72*I72,2) -> 0 | L72: =M72+P72+O72+N72-R72 -> 0 | BC72: 2100002017551 | BD72: 750-25L
A73: 46030 | B73: /2140 | D73: 进口发票 | E73: IMPORTAÇAO | H73: =F73*G73 -> 0 | J73: =ROUND(H73+H73*I73,2) -> 0 | L73: =M73+P73+O73+N73-R73 -> 0 | BC73: 2100002017599 | BD73: 1100-25L - 127V E
A74: 46030 | B74: 2370/2141 | D74: 销售 | E74: TECNODONTO LTDA | H74: =F74*G74 -> 0 | J74: =ROUND(H74+H74*I74,2) -> 0 | K74: 1 | L74: =M74+P74+O74+N74-R74 -> 1685 | N74: 1685 | T74: 08/01/2026-ARGOTECH | BC74: 2100002017605 | BD74: 1100-25L - 220V E
A75: 46030 | B75: 2370/2141 | C75: 2100002017476 | D75: =VLOOKUP(C75,$BC:$BD,2,0) -> 550*2-50L | E75: TECNODONTO LTDA | F75: 1 | G75: 1685 | H75: =F75*G75 -> 1685 | J75: =ROUND(H75+H75*I75,2) -> 1685 | L75: =M75+P75+O75+N75-R75 -> 0 | BC75: 2100002017612 | BD75: 1100*2 50L 127V E
A76: 46030 | B76: 2364/2142 | D76: 销售 | E76: Ferragens Home | H76: =F76*G76 -> 0 | J76: =ROUND(H76+H76*I76,2) -> 0 | K76: 1 | L76: =M76+P76+O76+N76-R76 -> 1487.06 | P76: 1498 | R76: =ROUND(P76*S76,2) -> 10.94 | S76: 0.0073 | T76: 08/01/2026-ARGOTECH | BC76: 2100002017629 | BD76: 1100*2 50L 220V E
A77: 46030 | B77: 2364/2142 | C77: 2100002017230 | D77: =VLOOKUP(C77,$BC:$BD,2,0) -> 1200*2-50L | E77: FERRAGENS HOME HOUSE COM. DE EQUIP. E MAQUINAS LTDA | F77: 1 | G77: 1498 | H77: =F77*G77 -> 1498 | J77: =ROUND(H77+H77*I77,2) -> 1498 | L77: =M77+P77+O77+N77-R77 -> 0 | BC77: 2100002016776 | BD77: 1200- 8L
A78: 46030 | B78: 2360/2143 | D78: 销售-内部 | E78: Norte Tools | H78: =F78*G78 -> 0 | J78: =ROUND(H78+H78*I78,2) -> 0 | T78: 12/04/2026-Argotech | BC78: 2100002017681 | BD78: BM-1902-25L-220V
A79: 46030 | B79: 2361/2144 | D79: 销售 | E79: R C NEPOMUCENO | H79: =F79*G79 -> 0 | J79: =ROUND(H79+H79*I79,2) -> 0 | K79: 3 | L79: =M79+P79+O79+N79-R79 -> 2558.7 | N79: 2558.7 | T79: 08/01/2026-Argotech | BC79: 2100002017339 | BD79: ER70S-6 1KG 0.8MM
A80: 46030 | B80: 2361/2144 | C80: 2100002017483 | D80: =VLOOKUP(C80,$BC:$BD,2,0) -> 750-25L | E80: R C NEPOMUCENO FERRAMENTAS | F80: 3 | G80: 852.9 | H80: =F80*G80 -> 2558.7 | J80: =ROUND(H80+H80*I80,2) -> 2558.7 | L80: =M80+P80+O80+N80-R80 -> 0 | BC80: 2100002017346 | BD80: ER70S-6 1KG 1.0MM
A81: 46031 | B81: 2375/2145 | D81: 销售 | E81: GENIOBOX COMERCIAL | H81: =F81*G81 -> 0 | J81: =ROUND(H81+H81*I81,2) -> 0 | K81: 1 | L81: =M81+P81+O81+N81-R81 -> 660 | N81: 660 | T81: 09/01/2025-Argotech | BC81: 2100002017674 | BD81: BM-1902-25L-127V
A82: 46031 | B82: 2375/2145 | C82: 2100002017032 | D82: =VLOOKUP(C82,$BC:$BD,2,0) -> 1100 8L | E82: GENIOBOX COMERCIAL LTDA | F82: 1 | G82: 660 | H82: =F82*G82 -> 660 | J82: =ROUND(H82+H82*I82,2) -> 660 | L82: =M82+P82+O82+N82-R82 -> 0 | BC82: 2100002017797 | BD82: BM-1902-25L 127V E
A83: 46031 | B83: 2376/2146 | D83: 销售 | E83: GENIOBOX COMERCIAL | H83: =F83*G83 -> 0 | J83: =ROUND(H83+H83*I83,2) -> 0 | K83: 1 | L83: =M83+P83+O83+N83-R83 -> 660 | N83: 660 | T83: 09/01/2026-Agotech
A84: 46031 | B84: 2376/2146 | C84: 2100002017032 | D84: =VLOOKUP(C84,$BC:$BD,2,0) -> 1100 8L | E84: GENIOBOX COMERCIAL LTDA | F84: 1 | G84: 660 | H84: =F84*G84 -> 660 | J84: =ROUND(H84+H84*I84,2) -> 660 | L84: =M84+P84+O84+N84-R84 -> 0
A85: 46031 | B85: 2374/2147 | D85: 取消 | E85: CANCELADA | H85: =F85*G85 -> 0 | J85: =ROUND(H85+H85*I85,2) -> 0 | L85: =M85+P85+O85+N85-R85 -> 0
A86: 46034 | B86: 2378/2148 | D86: 销售 | E86: Ferragens Home | H86: =F86*G86 -> 0 | J86: =ROUND(H86+H86*I86,2) -> 0 | K86: 6 | L86: =M86+P86+O86+N86-R86 -> 4072.44 | P86: 4102.39 | R86: =ROUND(P86*S86,2) -> 29.95 | S86: 0.0073 | T86: 12/01/2026-Argotech
A87: 46034 | B87: 2378/2148 | C87: 2100002017292 | D87: =VLOOKUP(C87,$BC:$BD,2,0) -> BM-1902 25L | E87: FERRAGENS HOME HOUSE COM. DE EQUIP. E MAQUINAS LTDA | F87: 1 | G87: 640 | H87: =F87*G87 -> 640 | J87: =ROUND(H87+H87*I87,2) -> 640 | L87: =M87+P87+O87+N87-R87 -> 0
A88: 46034 | B88: 2378/2148 | C88: 2100002017469 | D88: =VLOOKUP(C88,$BC:$BD,2,0) -> BM-1902 25L 127V | E88: FERRAGENS HOME HOUSE COM. DE EQUIP. E MAQUINAS LTDA | F88: 2 | G88: 640 | H88: =F88*G88 -> 1280 | J88: =ROUND(H88+H88*I88,2) -> 1280 | L88: =M88+P88+O88+N88-R88 -> 0
A89: 46034 | B89: 2378/2148 | C89: 2100002016752 | D89: =VLOOKUP(C89,$BC:$BD,2,0) -> 1200 25L | E89: FERRAGENS HOME HOUSE COM. DE EQUIP. E MAQUINAS LTDA | F89: 1 | G89: 902.39 | H89: =F89*G89 -> 902.39 | J89: =ROUND(H89+H89*I89,2) -> 902.39 | L89: =M89+P89+O89+N89-R89 -> 0
A90: 46034 | B90: 2378/2148 | C90: 2100002016776 | D90: =VLOOKUP(C90,$BC:$BD,2,0) -> 1200- 8L | E90: FERRAGENS HOME HOUSE COM. DE EQUIP. E MAQUINAS LTDA | F90: 2 | G90: 640 | H90: =F90*G90 -> 1280 | J90: =ROUND(H90+H90*I90,2) -> 1280 | L90: =M90+P90+O90+N90-R90 -> 0
A91: 46031 | B91: 2373/2149 | D91: 销售 | E91: CLEYTON FRANCELLO | H91: =F91*G91 -> 0 | J91: =ROUND(H91+H91*I91,2) -> 0 | K91: 12 | L91: =M91+P91+O91+N91-R91 -> 288 | N91: 288 | T91: 46031
A92: 46034 | B92: 2373/2149 | C92: 2100002017278 | D92: 配件 | E92: CLEYTON FRANCELLINO BARROS | F92: 4 | G92: 27 | H92: =F92*G92 -> 108 | J92: =ROUND(H92+H92*I92,2) -> 108 | L92: =M92+P92+O92+N92-R92 -> 0
A93: 46034 | B93: 2373/2149 | C93: 2100002017278 | D93: 配件 | E93: CLEYTON FRANCELLINO BARROS | F93: 4 | G93: 15 | H93: =F93*G93 -> 60 | J93: =ROUND(H93+H93*I93,2) -> 60 | L93: =M93+P93+O93+N93-R93 -> 0
A94: 46034 | B94: 2373/2149 | C94: 2100002017278 | D94: 配件 | E94: CLEYTON FRANCELLINO BARROS | F94: 4 | G94: 30 | H94: =F94*G94 -> 120 | J94: =ROUND(H94+H94*I94,2) -> 120 | L94: =M94+P94+O94+N94-R94 -> 0
A95: 46034 | B95: 2379/2150 | D95: 销售 | E95: JH MAQUINAS | H95: =F95*G95 -> 0 | J95: =ROUND(H95+H95*I95,2) -> 0 | K95: 1 | L95: =M95+P95+O95+N95-R95 -> 1524 | N95: 1524 | T95: 46034
A96: 46034 | B96: 2379/2150 | C96: 2100002017049 | D96: =VLOOKUP(C96,$BC:$BD,2,0) -> 1100*2 50L | E96: JH MAQUINAS E FERRAMENTAS LTDA | F96: 1 | G96: 1524 | H96: =F96*G96 -> 1524 | J96: =ROUND(H96+H96*I96,2) -> 1524 | L96: =M96+P96+O96+N96-R96 -> 0
A97: 46034 | B97: 2363/2151 | D97: 取消 | E97: CANCELADA | H97: =F97*G97 -> 0 | J97: =ROUND(H97+H97*I97,2) -> 0 | L97: =M97+P97+O97+N97-R97 -> 0
A98: 46034 | B98: /2152 | D98: 运输 发票 | E98: REMESSA | H98: =F98*G98 -> 0 | J98: =ROUND(H98+H98*I98,2) -> 0 | L98: =M98+P98+O98+N98-R98 -> 0
A99: 46034 | B99: 2380/2153 | D99: 销售 | E99: Rubens De Almeida | H99: =F99*G99 -> 0 | J99: =ROUND(H99+H99*I99,2) -> 0 | K99: 1 | L99: =M99+P99+O99+N99-R99 -> 530.94 | P99: 534.84 | R99: =ROUND(P99*S99,2) -> 3.9 | S99: 0.0073 | T99: 13/01/2026-Argotech
A100: 46035 | B100: 2380/2153 | C100: 2100002017018 | D100: =VLOOKUP(C100,$BC:$BD,2,0) -> COMP 750W 220V | E100: RUBENS DE ALMEIDA GIL | F100: 1 | G100: 534.84 | H100: =F100*G100 -> 534.84 | J100: =ROUND(H100+H100*I100,2) -> 534.84 | L100: =M100+P100+O100+N100-R100 -> 0
...

Sheet 销售帐CAIYA
A1: 2026年巴西销售发票总帐(CAIYA )
A2: 界野 | D2: =L2+R2-M2-N2-O2-P2 -> -5.0022209e-12 | F2: =SUBTOTAL(9,F4:F721) -> 223 | H2: =SUBTOTAL(9,H4:H721) -> 44886.94 | J2: =SUBTOTAL(9,J4:J721) -> 44886.48 | K2: =SUBTOTAL(9,K4:K721) -> 220 | L2: =SUBTOTAL(9,L4:L721) -> 44823.47 | M2: =SUBTOTAL(9,M4:M721) -> 0 | N2: =SUBTOTAL(9,N4:N721) -> 17533.3 | O2: =SUBTOTAL(9,O4:O721) -> 24694.58 | P2: =SUBTOTAL(9,P4:P721) -> 2658.6 | Q2: =SUBTOTAL(9,Q4:Q721) -> 0 | R2: =J2-L2-Q2 -> 63.01
A3: 发生日期 | B3: 销售单号 | C3: 编码 | D3: 商品型号 | E3: 客户单位 | F3: 数量 | G3: 单价 | H3: 金额 | I3: 税率 | J3: 含税金额 | K3: 数量 | L3: 总金额 | M3: 现金 | N3: 银行存款 | O3: BOLETO | P3: 刷卡/cartão | Q3: 退货 DEVOLUÇÃO | R3: 手续费/comissão | S3: 卡率 | T3: 备注/OBSERVAÇÕES
A4: 46027 | B4: 4198/3630 | D4: 销售-内部 | E4: Norte Tools | L4: =M4+P4+O4+N4-Q4 -> 0 | T4: 07/04/2026-Caiya | BC4: 8424608028624 | BD4: US/MMA 280 BIVOLT
A5: 46027 | B5: 4201/3631 | D5: 销售 | E5: Nova Parafer | H5: =F5*G5 -> 0 | J5: =ROUND((H5*I5+H5),2) -> 0 | L5: =M5+P5+O5+N5-Q5 -> 1598.7 | O5: 1598.7 | T5: 06/02/2026,08/03/2026 e 07/04/2026-CAIYA | BC5: 8002126321436 | BD5: MINI MMA-190
A6: 46029 | B6: 4201/3631 | C6: 8424608028624 | D6: =VLOOKUP(C6,$BC:$BD,2,0) -> US/MMA 280 BIVOLT | E6: NOVA PARAFER-COMERCIO DE FERRAGENS LTDA - EPP | F6: 3 | G6: 532.9 | H6: =F6*G6 -> 1598.7 | J6: =ROUND(H6+H6*I6,2) -> 1598.7 | L6: =M6+P6+O6+N6-Q6 -> 0 | BC6: 8424608028419 | BD6: BC-430
A7: 46027 | B7: 4199/3632 | D7: 销售 | E7: lojao Das Ferramentas | H7: =F7*G7 -> 0 | J7: =ROUND(H7+H7*I7,2) -> 0 | K7: 14 | L7: =M7+P7+O7+N7-Q7 -> 2658.46 | N7: 2658.46 | R7: 0 | T7: 06/01/2026-Caiya
A8: 46030 | B8: 4199/3632 | C8: 8002126321436 | D8: =VLOOKUP(C8,$BC:$BD,2,0) -> MINI MMA-190 | E8: LOJAO DAS FERRAMENTAS LTDA | F8: 14 | G8: 189.89 | H8: =F8*G8 -> 2658.46 | J8: =ROUND(H8+H8*I8,2) -> 2658.46 | L8: =M8+P8+O8+N8-Q8 -> 0
A9: 46027 | B9: 4200/3633 | D9: 销售 | E9: Silva Ferragens | H9: =F9*G9 -> 0 | J9: =ROUND(H9+H9*I9,2) -> 0 | K9: 14 | L9: =M9+P9+O9+N9-Q9 -> 2658.46 | O9: 2658.46 | R9: 0 | T9: 08/02/2026, 08/03/2026 e 08/04/2026-Caiya
A10: 46030 | B10: 4200/3633 | C10: 8002126321436 | D10: =VLOOKUP(C10,$BC:$BD,2,0) -> MINI MMA-190 | E10: SILVA FERRAGENS LTDA | F10: 14 | G10: 189.89 | H10: =F10*G10 -> 2658.46 | J10: =ROUND(H10+H10*I10,2) -> 2658.46 | L10: =M10+P10+O10+N10-Q10 -> 0
A11: 46027 | B11: 4202/3634 | D11: 销售 | E11: Garavelo Parafusos | H11: =F11*G11 -> 0 | J11: =ROUND(H11+H11*I11,2) -> 0 | K11: 14 | L11: =M11+P11+O11+N11-Q11 -> 2658.46 | O11: 2658.46 | R11: 0 | T11: 14/02/2026,16/03/2026 e 14/04/2026
A12: 46035 | B12: 4202/3634 | C12: 8002126321436 | D12: =VLOOKUP(C12,$BC:$BD,2,0) -> MINI MMA-190 | E12: GARAVELO PARAFUSOS LTDA | F12: 14 | G12: 189.89 | H12: =F12*G12 -> 2658.46 | J12: =ROUND(H12+H12*I12,2) -> 2658.46 | L12: =M12+P12+O12+N12-Q12 -> 0
A13: 46027 | B13: 4203/3635 | D13: 销售 | E13: R C Nepomuceno | H13: =F13*G13 -> 0 | J13: =ROUND(H13+H13*I13,2) -> 0 | K13: 14 | L13: =M13+P13+O13+N13-Q13 -> 2658.46 | N13: 2658.46 | R13: 0 | T13: 13/01/2026- Caiya
A14: 46035 | B14: 4203/3635 | C14: 8002126321436 | D14: =VLOOKUP(C14,$BC:$BD,2,0) -> MINI MMA-190 | E14: R C NEPOMUCENO DE FERRAMENTAS | F14: 14 | G14: 189.89 | H14: =F14*G14 -> 2658.46 | J14: =ROUND(H14+H14*I14,2) -> 2658.46 | L14: =M14+P14+O14+N14-Q14 -> 0
A15: 46027 | B15: 4204/3636 | D15: 销售-内部 | E15: Norte Tools | H15: =F15*G15 -> 0 | J15: =ROUND(H15+H15*I15,2) -> 0 | L15: =M15+P15+O15+N15-Q15 -> 0 | R15: 0 | T15: 20/04/2026-Caiya
A16: 46042 | B16: 4205/3637 | D16: 销售 | E16: Industria e Comercio | H16: =F16*G16 -> 0 | J16: =ROUND(H16+H16*I16,2) -> 0 | K16: 4 | L16: =M16+P16+O16+N16-Q16 -> 1195.64 | O16: 1195.64 | R16: 0 | T16: 23/02/2026-CAIYA
A17: 46045 | B17: 4205/3637 | C17: 8002126321436 | D17: =VLOOKUP(C17,$BC:$BD,2,0) -> MINI MMA-190 | E17: INDUSTRIA E COMERCIO DE BOMBAS VERISSIMO LTDA | F17: 4 | G17: 298.91 | H17: =F17*G17 -> 1195.64 | J17: =ROUND(H17+H17*I17,2) -> 1195.64 | L17: =M17+P17+O17+N17-Q17 -> 0
A18: 46048 | B18: 4206/3638 | D18: 销售-内部 | E18: Norte Tools | H18: =F18*G18 -> 0 | J18: =ROUND(H18+H18*I18,2) -> 0 | L18: =M18+P18+O18+N18-Q18 -> 0 | R18: 0 | T18: 29/03/2026-CAIYA
A19: 46049 | B19: /3639 | D19: 运输 发票 | E19: REMESSA | H19: =F19*G19 -> 0 | J19: =ROUND(H19+H19*I19,2) -> 0 | L19: =M19+P19+O19+N19-Q19 -> 0 | R19: 0
A20: 46050 | B20: /3640 | D20: 运输 发票 | E20: REMESSA | H20: =F20*G20 -> 0 | J20: =ROUND(H20+H20*I20,2) -> 0 | L20: =M20+P20+O20+N20-Q20 -> 0 | R20: 0
A21: 46052 | B21: 4208/3641 | D21: 销售 | E21: Fabio Souza | H21: =F21*G21 -> 0 | J21: =ROUND(H21+H21*I21,2) -> 0 | K21: 14 | L21: =M21+P21+O21+N21-Q21 -> 2658 | N21: 2658 | R21: 0 | T21: 30/01/2026-CAIYA
A22: 46052 | B22: 4208/3641 | C22: 8002126321436 | D22: =VLOOKUP(C22,$BC:$BD,2,0) -> MINI MMA-190 | E22: FABIO SOUZA DE JESUS | F22: 14 | G22: 189.89 | H22: =F22*G22 -> 2658.46 | J22: =ROUND(H22+H22*I22,2)-0.46 -> 2658 | L22: =M22+P22+O22+N22-Q22 -> 0
A23: 46053 | B23: 本月合计 | F23: =SUBTOTAL(9,F4:F22) -> 77 | H23: =SUBTOTAL(9,H4:H22) -> 16086.64 | J23: =SUBTOTAL(9,J4:J22) -> 16086.18 | K23: =SUBTOTAL(9,K4:K22) -> 74 | L23: =SUBTOTAL(9,L4:L22) -> 16086.18 | M23: =SUBTOTAL(9,M4:M22) -> 0 | N23: =SUBTOTAL(9,N4:N22) -> 7974.92 | O23: =SUBTOTAL(9,O4:O22) -> 8111.26 | P23: =SUBTOTAL(9,P4:P22) -> 0 | Q23: =SUBTOTAL(9,Q4:Q22) -> 0 | R23: =ROUND(J23-L23-Q23,2) -> 0 | T23: =J23-L23-R23 -> 0
A24: 46062 | B24: 4207/3642 | D24: 销售 | E24: Batista e silva | H24: =F24*G24 -> 0 | J24: =ROUND(H24+H24*I24,2) -> 0 | K24: 14 | L24: =SUM(M24+N24+O24+P24-Q24-R24) -> 2659.86 | O24: 2659.86 | T24: 10/03/2026, 10/04/2026 e 10/05/2026-CAIYA
A25: 46062 | B25: 4207/3642 | C25: 8002126321436 | D25: =VLOOKUP(C25,$BC:$BD,2,0) -> MINI MMA-190 | E25: BATISTA E SILVA COMERCIO DE FERRAGENS E MATERIAIS | F25: 14 | G25: 189.99 | H25: =F25*G25 -> 2659.86 | J25: =ROUND(H25+H25*I25,2) -> 2659.86 | L25: =SUM(M25+N25+O25+P25-Q25-R25) -> 0
A26: 46063 | B26: 4209/3643 | D26: 销售 | E26: VL Ferramentas | H26: =F26*G26 -> 0 | J26: =ROUND(H26+H26*I26,2) -> 0 | K26: 14 | L26: =SUM(M26+N26+O26+P26-Q26-R26) -> 2595.59 | P26: 2658.6 | R26: =ROUND(P26*S26,2) -> 63.01 | S26: 0.0237 | T26: 06/02/2026-CAIYA
A27: 46063 | B27: 4209/3643 | C27: 8002126321436 | D27: =VLOOKUP(C27,$BC:$BD,2,0) -> MINI MMA-190 | E27: VL FERRAMENTAS EIRELI - ME | F27: 14 | G27: 189.9 | H27: =F27*G27 -> 2658.6 | J27: =ROUND(H27+H27*I27,2) -> 2658.6 | L27: =SUM(M27+N27+O27+P27-Q27-R27) -> 0
A28: 46064 | B28: 4210/3644 | D28: 销售 | E28: J C Nepomuceno | H28: =F28*G28 -> 0 | J28: =ROUND(H28+H28*I28,2) -> 0 | K28: 16 | L28: =SUM(M28+N28+O28+P28-Q28-R28) -> 3038.24 | N28: 3038.24 | R28: =P28*S28 -> 0 | T28: 11/02/2026-CAIYA
A29: 46064 | B29: 4210/3644 | C29: 8002126321436 | D29: =VLOOKUP(C29,$BC:$BD,2,0) -> MINI MMA-190 | E29: J C NEPOMUCENO FERRAMENTAS - ME | F29: 16 | G29: 189.89 | H29: =F29*G29 -> 3038.24 | J29: =ROUND(H29+H29*I29,2) -> 3038.24 | L29: =SUM(M29+N29+O29+P29-Q29-R29) -> 0
A30: 46065 | B30: 4211/3645 | D30: 销售 | E30: Lider Comercio | H30: =F30*G30 -> 0 | J30: =ROUND(H30+H30*I30,2) -> 0 | K30: 14 | L30: =SUM(M30+N30+O30+P30-Q30-R30) -> 2658.46 | O30: 2658.46 | R30: =P30*S30 -> 0 | T30: 14/03/2026,13/04/2026 e 13/05/2026- CAIYA
A31: 46065 | B31: 4211/3645 | C31: 8002126321436 | D31: =VLOOKUP(C31,$BC:$BD,2,0) -> MINI MMA-190 | E31: LIDER COMERCIO DE FERRAGENS FERRAM. E VIDROS LTDA-ME | F31: 14 | G31: 189.89 | H31: =F31*G31 -> 2658.46 | J31: =ROUND(H31+H31*I31,2) -> 2658.46 | L31: =SUM(M31+N31+O31+P31-Q31-R31) -> 0
A32: 46066 | B32: 4213/3646 | D32: 销售 | E32: VT Ferramentas | H32: =F32*G32 -> 0 | J32: =ROUND(H32+H32*I32,2) -> 0 | K32: 14 | L32: =SUM(M32+N32+O32+P32-Q32-R32) -> 2658.46 | N32: 2658.46 | R32: =P32*S32 -> 0 | T32: 13/02/2026-CAIYA
A33: 46066 | B33: 4213/3646 | C33: 8002126321436 | D33: =VLOOKUP(C33,$BC:$BD,2,0) -> MINI MMA-190 | E33: VT FERRAMENTAS LTDA | F33: 14 | G33: 189.89 | H33: =F33*G33 -> 2658.46 | J33: =ROUND(H33+H33*I33,2) -> 2658.46 | L33: =SUM(M33+N33+O33+P33-Q33-R33) -> 0
A34: 46066 | B34: 4215/3647 | D34: 销售 | E34: Geniobox Comercial | H34: =F34*G34 -> 0 | J34: =ROUND(H34+H34*I34,2) -> 0 | K34: 1 | L34: =SUM(M34+N34+O34+P34-Q34-R34) -> 221.54 | N34: 221.54 | R34: =P34*S34 -> 0 | T34: 13/02/2026-CAIYA
A35: 46066 | B35: 4215/3647 | C35: 8002126321436 | D35: =VLOOKUP(C35,$BC:$BD,2,0) -> MINI MMA-190 | E35: GENIOBOX COMERCIAL LTDA | F35: 1 | G35: 221.54 | H35: =F35*G35 -> 221.54 | J35: =ROUND(H35+H35*I35,2) -> 221.54 | L35: =SUM(M35+N35+O35+P35-Q35-R35) -> 0
A36: 46071 | B36: 4216/3648 | D36: 销售 | E36: NS Com De Ferr e Acessorios | H36: =F36*G36 -> 0 | J36: =ROUND(H36+H36*I36,2) -> 0 | K36: 2 | L36: =SUM(M36+N36+O36+P36-Q36-R36) -> 1390.2 | O36: 1390.2 | R36: =P36*S36 -> 0 | T36: 18/03/2026 e 02/04/2026 -CAIYA
A37: 46071 | B37: 4216/3648 | C37: 8424608028419 | D37: =VLOOKUP(C37,$BC:$BD,2,0) -> #N/A | E37: NS COM DE FERR E ACESSORIOS LTDA | F37: 2 | G37: 695.1 | H37: =F37*G37 -> 1390.2 | J37: =ROUND(H37+H37*I37,2) -> 1390.2 | L37: =SUM(M37+N37+O37+P37-Q37-R37) -> 0
A38: 46072 | B38: 4217/3649 | D38: 销售 | E38: Geniobox Comercial | H38: =F38*G38 -> 0 | J38: =ROUND(H38+H38*I38,2) -> 0 | K38: 1 | L38: =SUM(M38+N38+O38+P38-Q38-R38) -> 221.54 | N38: 221.54 | R38: =P38*S38 -> 0 | T38: 19/02/2026-CAIYA
A39: 46072 | B39: 4217/3649 | C39: 8002126321436 | D39: =VLOOKUP(C39,$BC:$BD,2,0) -> MINI MMA-190 | E39: GENIOBOX COMERCIAL LTDA | F39: 1 | G39: 221.54 | H39: =F39*G39 -> 221.54 | J39: =ROUND(H39+H39*I39,2) -> 221.54 | L39: =SUM(M39+N39+O39+P39-Q39-R39) -> 0
A40: 46077 | B40: 4219/3650 | D40: 销售 | E40: Geniobox Comercial | H40: =F40*G40 -> 0 | J40: =ROUND(H40+H40*I40,2) -> 0 | K40: 4 | L40: =SUM(M40+N40+O40+P40-Q40-R40) -> 760 | N40: 760 | R40: =P40*S40 -> 0 | T40: 24/02/2026-MA99819帐户
A41: 46077 | B41: 4219/3650 | C41: 8002126321436 | D41: =VLOOKUP(C41,$BC:$BD,2,0) -> MINI MMA-190 | E41: GENIOBOX COMERCIAL LTDA | F41: 4 | G41: 190 | H41: =F41*G41 -> 760 | J41: =ROUND(H41+H41*I41,2) -> 760 | L41: =SUM(M41+N41+O41+P41-Q41-R41) -> 0
A42: 46078 | B42: 4221/3651 | D42: 销售 | E42: Mais Ferramentas | H42: =F42*G42 -> 0 | J42: =ROUND(H42+H42*I42,2) -> 0 | K42: 14 | L42: =SUM(M42+N42+O42+P42-Q42-R42) -> 2658.6 | N42: 2658.6 | R42: =P42*S42 -> 0 | T42: 24/02/2026-CAIYA
A43: 46078 | B43: 4221/3651 | C43: 8002126321436 | D43: =VLOOKUP(C43,$BC:$BD,2,0) -> MINI MMA-190 | E43: MAIS FERRAMENTAS MT LTDA | F43: 14 | G43: 189.9 | H43: =F43*G43 -> 2658.6 | J43: =ROUND(H43+H43*I43,2) -> 2658.6 | L43: =SUM(M43+N43+O43+P43-Q43-R43) -> 0
A44: 46078 | B44: 4218/3652 | D44: 销售 | E44: Garavelo Parafusos | H44: =F44*G44 -> 0 | J44: =ROUND(H44+H44*I44,2) -> 0 | K44: 52 | L44: =SUM(M44+N44+O44+P44-Q44-R44) -> 9874.8 | O44: 9874.8 | R44: =P44*S44 -> 0 | T44: 11/03/2026, 26/03/2026, 11/04/2026 e 26/04/2026
A45: 46078 | B45: 4218/3652 | C45: 8002126321436 | D45: =VLOOKUP(C45,$BC:$BD,2,0) -> MINI MMA-190 | E45: GARAVELO PARAFUSOS LTDA | F45: 52 | G45: 189.9 | H45: =F45*G45 -> 9874.8 | J45: =ROUND(H45+H45*I45,2) -> 9874.8 | L45: =SUM(M45+N45+O45+P45-Q45-R45) -> 0
A46: 46080 | B46: 4222/3653 | D46: 销售-内部 | E46: Norte tools | H46: =F46*G46 -> 0 | J46: =ROUND(H46+H46*I46,2) -> 0 | L46: =SUM(M46+N46+O46+P46-Q46-R46) -> 0 | R46: =P46*S46 -> 0 | T46: 02/06/2026-CAIYA
A47: 46081 | B47: 本月合计 | F47: =SUBTOTAL(9,F24:F46) -> 146 | H47: =SUBTOTAL(9,H24:H46) -> 28800.3 | J47: =SUBTOTAL(9,J24:J46) -> 28800.3 | K47: =SUBTOTAL(9,K24:K46) -> 146 | L47: =SUBTOTAL(9,L24:L46) -> 28737.29 | M47: =SUBTOTAL(9,M24:M46) -> 0 | N47: =SUBTOTAL(9,N24:N46) -> 9558.38 | O47: =SUBTOTAL(9,O24:O46) -> 16583.32 | P47: =SUBTOTAL(9,P24:P46) -> 2658.6 | Q47: =SUBTOTAL(9,Q24:Q46) -> 0 | R47: =SUBTOTAL(9,R24:R46) -> 63.01 | T47: =J47-L47-R47 -> 2.0392577e-12
A55: 46112 | B55: 本月合计 | F55: =SUBTOTAL(9,F48:F54) -> 0 | H55: =SUBTOTAL(9,H48:H54) -> 0 | I55: =SUBTOTAL(9,I48:I54) -> 0 | J55: =SUBTOTAL(9,J48:J54) -> 0 | K55: =SUBTOTAL(9,K48:K54) -> 0 | L55: =SUBTOTAL(9,L48:L54) -> 0 | M55: =SUBTOTAL(9,M48:M54) -> 0 | N55: =SUBTOTAL(9,N48:N54) -> 0 | O55: =SUBTOTAL(9,O48:O54) -> 0 | ... Q55: =SUBTOTAL(9,Q48:Q54) -> 0 | R55: =ROUND(J55-L55-Q55,2) -> 0
A60: 46142 | B60: 本月合计 | F60: =SUBTOTAL(9,F56:F59) -> 0 | H60: =SUBTOTAL(9,H56:H59) -> 0 | I60: =SUBTOTAL(9,I56:I59) -> 0 | J60: =SUBTOTAL(9,J56:J59) -> 0 | K60: =SUBTOTAL(9,K56:K59) -> 0 | L60: =SUBTOTAL(9,L56:L59) -> 0 | M60: =SUBTOTAL(9,M56:M59) -> 0 | N60: =SUBTOTAL(9,N56:N59) -> 0 | O60: =SUBTOTAL(9,O56:O59) -> 0 | ... Q60: =SUBTOTAL(9,Q56:Q59) -> 0 | R60: =ROUND(J60-L60-Q60,2) -> 0
A65: 46173 | B65: 本月合计 | F65: =SUBTOTAL(9,F61:F64) -> 0 | H65: =SUBTOTAL(9,H61:H64) -> 0 | I65: =SUBTOTAL(9,I61:I64) -> 0 | J65: =SUBTOTAL(9,J61:J64) -> 0 | K65: =SUBTOTAL(9,K61:K64) -> 0 | L65: =SUBTOTAL(9,L61:L64) -> 0 | M65: =SUBTOTAL(9,M61:M64) -> 0 | N65: =SUBTOTAL(9,N61:N64) -> 0 | O65: =SUBTOTAL(9,O61:O64) -> 0 | ... Q65: =SUBTOTAL(9,Q61:Q64) -> 0 | R65: =ROUND(J65-L65-Q65,2) -> 0
A80: 46203 | B80: 本月合计 | F80: =SUBTOTAL(9,F66:F79) -> 0 | H80: =SUBTOTAL(9,H66:H79) -> 0 | J80: =SUBTOTAL(9,J66:J79) -> 0 | K80: =SUBTOTAL(9,K66:K79) -> 0 | L80: =SUBTOTAL(9,L66:L79) -> 0 | M80: =SUBTOTAL(9,M66:M79) -> 0 | N80: =SUBTOTAL(9,N66:N79) -> 0 | O80: =SUBTOTAL(9,O66:O79) -> 0 | P80: =SUBTOTAL(9,P66:P79) -> 0 | Q80: =SUBTOTAL(9,Q66:Q79) -> 0 | R80: =ROUND(J80-L80-Q80,2) -> 0
A92: 46234 | B92: 本月合计 | F92: =SUBTOTAL(9,F81:F91) -> 0 | H92: =SUBTOTAL(9,H81:H91) -> 0 | J92: =SUBTOTAL(9,J81:J91) -> 0 | K92: =SUBTOTAL(9,K81:K91) -> 0 | L92: =SUBTOTAL(9,L81:L91) -> 0 | M92: =SUBTOTAL(9,M81:M91) -> 0 | N92: =SUBTOTAL(9,N81:N91) -> 0 | O92: =SUBTOTAL(9,O81:O91) -> 0 | P92: =SUBTOTAL(9,P81:P91) -> 0 | Q92: =SUBTOTAL(9,Q81:Q91) -> 0 | R92: =ROUND(J92-L92-Q92,2) -> 0
A106: 46265 | B106: 本月合计 | F106: =SUBTOTAL(9,F93:F105) -> 0 | H106: =SUBTOTAL(9,H93:H105) -> 0 | J106: =SUBTOTAL(9,J93:J105) -> 0 | K106: =SUBTOTAL(9,K93:K105) -> 0 | L106: =SUBTOTAL(9,L93:L105) -> 0 | M106: =SUBTOTAL(9,M93:M105) -> 0 | N106: =SUBTOTAL(9,N93:N105) -> 0 | O106: =SUBTOTAL(9,O93:O105) -> 0 | P106: =SUBTOTAL(9,P93:P105) -> 0 | Q106: =SUBTOTAL(9,Q93:Q105) -> 0 | R106: =ROUND(J106-L106-Q106,2) -> 0
A116: 46295 | B116: 本月合计 | F116: =SUBTOTAL(9,F107:F115) -> 0 | H116: =SUBTOTAL(9,H107:H115) -> 0 | I116: =SUBTOTAL(9,I107:I115) -> 0 | J116: =SUBTOTAL(9,J107:J115) -> 0 | K116: =SUBTOTAL(9,K107:K115) -> 0 | L116: =SUBTOTAL(9,L107:L115) -> 0 | M116: =SUBTOTAL(9,M107:M115) -> 0 | N116: =SUBTOTAL(9,N107:N115) -> 0 | O116: =SUBTOTAL(9,O107:O115) -> 0 | ... Q116: =SUBTOTAL(9,Q107:Q115) -> 0 | R116: =ROUND(J116-L116-Q116,2) -> 0
A125: 46326 | B125: 本月合计 | F125: =SUBTOTAL(9,F117:F124) -> 0 | H125: =SUBTOTAL(9,H117:H124) -> 0 | J125: =SUBTOTAL(9,J117:J124) -> 0 | K125: =SUBTOTAL(9,K117:K124) -> 0 | L125: =SUBTOTAL(9,L117:L124) -> 0 | M125: =SUBTOTAL(9,M117:M124) -> 0 | N125: =SUBTOTAL(9,N117:N124) -> 0 | O125: =SUBTOTAL(9,O117:O124) -> 0 | P125: =SUBTOTAL(9,P117:P124) -> 0 | Q125: =SUBTOTAL(9,Q117:Q124) -> 0 | R125: =ROUND(J125-L125-Q125,2) -> 0
A153: 46356 | B153: 本月合计 | F153: =SUBTOTAL(9,F126:F152) -> 0 | H153: =SUBTOTAL(9,H126:H152) -> 0 | J153: =SUBTOTAL(9,J126:J152) -> 0 | K153: =SUBTOTAL(9,K126:K152) -> 0 | L153: =SUBTOTAL(9,L126:L152) -> 0 | M153: =SUBTOTAL(9,M126:M152) -> 0 | N153: =SUBTOTAL(9,N126:N152) -> 0 | O153: =SUBTOTAL(9,O126:O152) -> 0 | P153: =SUBTOTAL(9,P126:P152) -> 0 | Q153: =SUBTOTAL(9,Q126:Q152) -> 0 | R153: =ROUND(J153-L153-Q153,2) -> 0
A161: 46387 | B161: 本月合计 | F161: =SUBTOTAL(9,F154:F160) -> 0 | H161: =SUBTOTAL(9,H154:H160) -> 0 | I161: =SUBTOTAL(9,I154:I160) -> 0 | J161: =SUBTOTAL(9,J154:J160) -> 0 | K161: =SUBTOTAL(9,K154:K160) -> 0 | L161: =SUBTOTAL(9,L154:L160) -> 0 | M161: =SUBTOTAL(9,M154:M160) -> 0 | N161: =SUBTOTAL(9,N154:N160) -> 0 | O161: =SUBTOTAL(9,O154:O160) -> 0 | ... Q161: =SUBTOTAL(9,Q154:Q160) -> 0 | R161: =ROUND(J161-L161-Q161,2) -> 0

Sheet 销售帐 - COMPBRASIL
A1: 2026年巴西销售发票总帐(COMPBRASIL )
A2: 江帝伯拉ZO | D2: =L2+Q2-N2-M2-O2-P2 -> 0 | F2: =SUBTOTAL(9,F4:F1486) -> 0 | H2: =SUBTOTAL(9,H4:H1486) -> 0 | J2: =SUBTOTAL(9,J4:J1486) -> 0 | K2: =SUBTOTAL(9,K4:K1486) -> 0 | L2: =SUBTOTAL(9,L4:L1486) -> 0 | M2: =SUBTOTAL(9,M4:M1486) -> 0 | N2: =SUBTOTAL(9,N4:N1486) -> 0 | O2: =SUBTOTAL(9,O4:O1486) -> 0 | P2: =SUBTOTAL(9,P4:P1486) -> 0 | Q2: =SUBTOTAL(9,Q4:Q1486) -> 0 | R2: =L2+Q2-J2 -> 0
A3: 发生日期 | B3: 销售单号 | C3: 编码 | D3: 商品型号 | E3: 客户单位 | F3: 数量 | G3: 单价 | H3: 金额 | I3: 税率 | J3: 含税金额 | K3: 数量 | L3: 总金额 | M3: 现金 | N3: 银行存款 | O3: BOLETO | P3: 刷卡/COM | Q3: 卡费/Taxa de cartão de | R3: 备注 / OBSERVAÇÕES | S3: 说明/Descrição | T3: 1期时间 | U3: 金额 | V3: 2期时间 | W3: 金额 | X3: 3期时间 | Y3: 金额 | Z3: 4期时间 | AA3: 金额 | AB3: 5期时间 | AC3: 金额 | AD3: 6期时间 | AE3: 金额 | AF3: 7期时间 | AG3: 金额 | AH3: 8期时间 | AI3: 金额 | AJ3: 合计金额 | AK3: 误差
A27: 46053 | B27: 本月合计 | F27: =SUBTOTAL(9,F4:F26) -> 0 | H27: =SUBTOTAL(9,H4:H26) -> 0 | J27: =SUBTOTAL(9,J4:J26) -> 0 | K27: =SUBTOTAL(9,K4:K26) -> 0 | L27: =SUBTOTAL(9,L4:L26) -> 0 | M27: =SUBTOTAL(9,M4:M26) -> 0 | N27: =SUBTOTAL(9,N4:N26) -> 0 | O27: =SUBTOTAL(9,O4:O26) -> 0 | P27: =SUBTOTAL(9,P4:P26) -> 0 | Q27: =SUBTOTAL(9,Q4:Q26) -> 0 | R27: =ROUND(J27-L27-Q27,2) -> 0
A35: 46081 | B35: 本月合计 | F35: =SUBTOTAL(9,F28:F34) -> 0 | H35: =SUBTOTAL(9,H28:H34) -> 0 | I35: =SUBTOTAL(9,I28:I34) -> 0 | J35: =SUBTOTAL(9,J28:J34) -> 0 | K35: =SUBTOTAL(9,K28:K34) -> 0 | L35: =SUBTOTAL(9,L28:L34) -> 0 | M35: =SUBTOTAL(9,M28:M34) -> 0 | N35: =SUBTOTAL(9,N28:N34) -> 0 | O35: =SUBTOTAL(9,O28:O34) -> 0 | ... Q35: =SUBTOTAL(9,Q28:Q34) -> 0 | R35: =ROUND(J35-L35-Q35,2) -> 0
A40: 46112 | B40: 本月合计 | F40: =SUBTOTAL(9,F36:F39) -> 0 | H40: =SUBTOTAL(9,H36:H39) -> 0 | I40: =SUBTOTAL(9,I36:I39) -> 0 | J40: =SUBTOTAL(9,J36:J39) -> 0 | K40: =SUBTOTAL(9,K36:K39) -> 0 | L40: =SUBTOTAL(9,L36:L39) -> 0 | M40: =SUBTOTAL(9,M36:M39) -> 0 | N40: =SUBTOTAL(9,N36:N39) -> 0 | O40: =SUBTOTAL(9,O36:O39) -> 0 | ... Q40: =SUBTOTAL(9,Q36:Q39) -> 0 | R40: =ROUND(J40-L40-Q40,2) -> 0
A82: 46142 | B82: 本月合计 | F82: =SUBTOTAL(9,F41:F81) -> 0 | H82: =SUBTOTAL(9,H41:H81) -> 0 | I82: =SUBTOTAL(9,I41:I81) -> 0 | J82: =SUBTOTAL(9,J41:J81) -> 0 | K82: =SUBTOTAL(9,K41:K81) -> 0 | L82: =SUBTOTAL(9,L41:L81) -> 0 | M82: =SUBTOTAL(9,M41:M81) -> 0 | N82: =SUBTOTAL(9,N41:N81) -> 0 | O82: =SUBTOTAL(9,O41:O81) -> 0 | ... Q82: =SUBTOTAL(9,Q41:Q81) -> 0 | R82: =ROUND(J82-L82-Q82,2) -> 0
A270: 46173 | B270: 本月合计 | F270: =SUBTOTAL(9,F83:F269) -> 0 | H270: =SUBTOTAL(9,H83:H269) -> 0 | I270: =SUBTOTAL(9,I83:I269) -> 0 | J270: =SUBTOTAL(9,J83:J269) -> 0 | K270: =SUBTOTAL(9,K83:K269) -> 0 | L270: =SUBTOTAL(9,L83:L269) -> 0 | M270: =SUBTOTAL(9,M83:M269) -> 0 | N270: =SUBTOTAL(9,N83:N269) -> 0 | O270: =SUBTOTAL(9,O83:O269) -> 0 | ... Q270: =SUBTOTAL(9,Q83:Q269) -> 0 | R270: =ROUND(J270-L270-Q270,2) -> 0
A387: 46203 | B387: 本月合计 | F387: =SUBTOTAL(9,F271:F386) -> 0 | H387: =SUBTOTAL(9,H271:H386) -> 0 | I387: =SUBTOTAL(9,I271:I386) -> 0 | J387: =SUBTOTAL(9,J271:J386) -> 0 | K387: =SUBTOTAL(9,K271:K386) -> 0 | L387: =SUBTOTAL(9,L271:L386) -> 0 | M387: =SUBTOTAL(9,M271:M386) -> 0 | N387: =SUBTOTAL(9,N271:N386) -> 0 | O387: =SUBTOTAL(9,O271:O386) -> 0 | ... Q387: =SUBTOTAL(9,Q271:Q386) -> 0 | R387: =ROUND(J387-L387-Q387,2) -> 0
A479: 46234 | B479: 本月合计 | F479: =SUBTOTAL(9,F388:F478) -> 0 | H479: =SUBTOTAL(9,H388:H478) -> 0 | I479: =SUBTOTAL(9,I388:I478) -> 0 | J479: =SUBTOTAL(9,J388:J478) -> 0 | K479: =SUBTOTAL(9,K388:K478) -> 0 | L479: =SUBTOTAL(9,L388:L478) -> 0 | M479: =SUBTOTAL(9,M388:M478) -> 0 | N479: =SUBTOTAL(9,N388:N478) -> 0 | O479: =SUBTOTAL(9,O388:O478) -> 0 | ... Q479: =SUBTOTAL(9,Q388:Q478) -> 0 | R479: =ROUND(J479-L479-Q479,2) -> 0
A578: 46265 | B578: 本月合计 | F578: =SUBTOTAL(9,F480:F577) -> 0 | H578: =SUBTOTAL(9,H480:H577) -> 0 | I578: =SUBTOTAL(9,I480:I577) -> 0 | J578: =SUBTOTAL(9,J480:J577) -> 0 | K578: =SUBTOTAL(9,K480:K577) -> 0 | L578: =SUBTOTAL(9,L480:L577) -> 0 | M578: =SUBTOTAL(9,M480:M577) -> 0 | N578: =SUBTOTAL(9,N480:N577) -> 0 | O578: =SUBTOTAL(9,O480:O577) -> 0 | ... Q578: =SUBTOTAL(9,Q480:Q577) -> 0 | R578: =ROUND(J578-L578-Q578,2) -> 0
A645: 46295 | B645: 本月合计 | F645: =SUBTOTAL(9,F579:F644) -> 0 | H645: =SUBTOTAL(9,H579:H644) -> 0 | I645: =SUBTOTAL(9,I579:I644) -> 0 | J645: =SUBTOTAL(9,J579:J644) -> 0 | K645: =SUBTOTAL(9,K579:K644) -> 0 | L645: =SUBTOTAL(9,L579:L644) -> 0 | M645: =SUBTOTAL(9,M579:M644) -> 0 | N645: =SUBTOTAL(9,N579:N644) -> 0 | O645: =SUBTOTAL(9,O579:O644) -> 0 | ... Q645: =SUBTOTAL(9,Q579:Q644) -> 0 | R645: =ROUND(J645-L645-Q645,2) -> 0
A733: 46326 | B733: 本月合计 | F733: =SUBTOTAL(9,F646:F732) -> 0 | H733: =SUBTOTAL(9,H646:H732) -> 0 | J733: =SUBTOTAL(9,J646:J732) -> 0 | K733: =SUBTOTAL(9,K646:K732) -> 0 | L733: =SUBTOTAL(9,L646:L732) -> 0 | M733: =SUBTOTAL(9,M646:M732) -> 0 | N733: =SUBTOTAL(9,N646:N732) -> 0 | O733: =SUBTOTAL(9,O646:O732) -> 0 | P733: =SUBTOTAL(9,P646:P732) -> 0 | Q733: =SUBTOTAL(9,Q646:Q732) -> 0 | R733: =ROUND(J733-L733-Q733,2) -> 0
A798: 46356 | B798: 本月合计 | F798: =SUBTOTAL(9,F734:F797) -> 0 | H798: =SUBTOTAL(9,H734:H797) -> 0 | I798: =SUBTOTAL(9,I734:I797) -> 0 | J798: =SUBTOTAL(9,J734:J797) -> 0 | K798: =SUBTOTAL(9,K734:K797) -> 0 | L798: =SUBTOTAL(9,L734:L797) -> 0 | M798: =SUBTOTAL(9,M734:M797) -> 0 | N798: =SUBTOTAL(9,N734:N797) -> 0 | O798: =SUBTOTAL(9,O734:O797) -> 0 | ... Q798: =SUBTOTAL(9,Q734:Q797) -> 0 | R798: =ROUND(J798-L798-Q798,2) -> 0
A809: 46387 | B809: 本月合计 | F809: =SUBTOTAL(9,F799:F808) -> 0 | H809: =SUBTOTAL(9,H799:H808) -> 0 | I809: =SUBTOTAL(9,I799:I808) -> 0 | J809: =SUBTOTAL(9,J799:J808) -> 0 | K809: =SUBTOTAL(9,K799:K808) -> 0 | L809: =SUBTOTAL(9,L799:L808) -> 0 | M809: =SUBTOTAL(9,M799:M808) -> 0 | N809: =SUBTOTAL(9,N799:N808) -> 0 | O809: =SUBTOTAL(9,O799:O808) -> 0 | ... Q809: =SUBTOTAL(9,Q799:Q808) -> 0 | R809: =L809+Q809-J809 -> 0

Sheet 销售帐DEYUN
A1: 2026年巴西销售发票总帐(DEYUN)
A2: 德永 | D2: =L2+Q2-N2-M2-O2-P2 -> 0 | F2: =SUBTOTAL(9,F4:F571) -> 3 | H2: =SUBTOTAL(9,H4:H571) -> 10105.5 | J2: =SUBTOTAL(9,J4:J571) -> 10105.5 | K2: =SUBTOTAL(9,K4:K571) -> 3 | L2: =SUBTOTAL(9,L4:L571) -> 10105.5 | M2: =SUBTOTAL(9,M4:M571) -> 0 | N2: =SUBTOTAL(9,N4:N571) -> 0 | O2: =SUBTOTAL(9,O4:O571) -> 10105.5 | P2: =SUBTOTAL(9,P4:P571) -> 0 | Q2: =SUBTOTAL(9,Q4:Q571) -> 0 | R2: =L2+Q2-J2 -> 0
A3: 发生日期 | B3: 销售单号 | C3: 编码 | D3: 商品型号 | E3: 客户单位 | F3: 数量 | G3: 单价 | H3: 金额 | I3: 税率 | J3: 含税金额 | K3: 数量 | L3: 总金额 | M3: 现金 | N3: 银行存款 | O3: BOLETO | P3: 刷卡/cartão | Q3: 退货 DEVOLUÇÃO | R3: 手续费/comissão | S3: 卡率 | T3: 备注/OBSERVAÇÕES
A4: 46027 | B4: 4061/3496 | D4: 销售-内部 | E4: Norte Tools | T4: 07/04/2026-Deyun
A5: 46028 | B5: 4062/3497 | D5: 销售 | E5: NOVA PARAFER | H5: =F5*G5 -> 0 | J5: =ROUND((H5*I5+H5),2) -> 0 | K5: 3 | L5: =M5+P5+O5+N5-R5 -> 10105.5 | O5: 10105.5 | T5: 06/02/2026,08/03/2026 e 07/02/2026-Deyun
A6: 46029 | B6: 4062/3497 | C6: 781 | D6: AK-MIG/MMA220A | E6: NOVA PARAFER-COMERCIO DE FERRAGENS LTDA - EPP | F6: 3 | G6: 3368.5 | H6: =F6*G6 -> 10105.5 | J6: =ROUND(H6+H6*I6,2) -> 10105.5
A7: 46035 | B7: 4063/3498 | D7: 销售-内部 | E7: Norte Tools | R7: 0 | T7: 14/04/2026-DEYUN
A8: 46042 | B8: 4064/3499 | D8: 销售-内部 | E8: Norte Tools | H8: =F8*G8 -> 0 | J8: =ROUND((H8*I8+H8),2) -> 0 | R8: 0 | T8: 20/04/2026-Deyun
A9: 46048 | B9: 4066/3500 | D9: 销售-内部 | E9: Norte Tools | R9: 0 | T9: 29/03/2026-DEYUN
A10: 46049 | B10: /3501 | D10: 运输 发票 | E10: REMESSA | H10: =F10*G10 -> 0 | J10: =ROUND((H10*I10+H10),2) -> 0 | R10: 0
A11: 46050 | B11: /3502 | D11: 运输 发票 | E11: REMESSA | L11: =M11+P11+O11+N11-Q11 -> 0 | R11: 0
A12: 46052 | B12: 4067/3503 | D12: 销售-内部 | E12: Norte Tools | H12: =F12*G12 -> 0 | J12: =ROUND((H12*I12+H12),2) -> 0 | R12: 0 | T12: 30/05/2026-DEYUN
A13: 46053 | B13: 本月合计 | F13: =SUBTOTAL(9,F4:F12) -> 3 | H13: =SUBTOTAL(9,H4:H12) -> 10105.5 | J13: =SUBTOTAL(9,J4:J12) -> 10105.5 | K13: =SUBTOTAL(9,K4:K12) -> 3 | L13: =SUBTOTAL(9,L4:L12) -> 10105.5 | M13: =SUBTOTAL(9,M4:M12) -> 0 | N13: =SUBTOTAL(9,N4:N12) -> 0 | O13: =SUBTOTAL(9,O4:O12) -> 10105.5 | P13: =SUBTOTAL(9,P4:P12) -> 0 | Q13: =SUBTOTAL(9,Q4:Q12) -> 0 | R13: =SUBTOTAL(9,R4:R12) -> 0 | T13: =J13-L13-R13 -> 0
A14: 46058 | B14: 4068/3504 | D14: 销售-内部 | T14: 06/05/2026-DEYUN
A15: 46064 | B15: 4069/3505 | D15: 销售-内部 | T15: 12/05/2026- DEYUN
A16: 46077 | B16: 4070/3506 | D16: 销售-内部 | T16: 25/05/2026-DEYUN
A17: 46081 | B17: 本月合计 | F17: =SUBTOTAL(9,F14:F16) -> 0 | H17: =SUBTOTAL(9,H14:H16) -> 0 | I17: =SUBTOTAL(9,I14:I16) -> 0 | J17: =SUBTOTAL(9,J14:J16) -> 0 | K17: =SUBTOTAL(9,K14:K16) -> 0 | L17: =SUBTOTAL(9,L14:L16) -> 0 | M17: =SUBTOTAL(9,M14:M16) -> 0 | N17: =SUBTOTAL(9,N14:N16) -> 0 | O17: =SUBTOTAL(9,O14:O16) -> 0 | ... Q17: =SUBTOTAL(9,Q14:Q16) -> 0 | R17: =L17+Q17-J17 -> 0
A23: 46112 | B23: 本月合计 | F23: =SUBTOTAL(9,F18:F22) -> 0 | H23: =SUBTOTAL(9,H18:H22) -> 0 | I23: =SUBTOTAL(9,I18:I22) -> 0 | J23: =SUBTOTAL(9,J18:J22) -> 0 | K23: =SUBTOTAL(9,K18:K22) -> 0 | L23: =SUBTOTAL(9,L18:L22) -> 0 | M23: =SUBTOTAL(9,M18:M22) -> 0 | N23: =SUBTOTAL(9,N18:N22) -> 0 | O23: =SUBTOTAL(9,O18:O22) -> 0 | ... Q23: =SUBTOTAL(9,Q18:Q22) -> 0 | R23: =L23+Q23-J23 -> 0
A32: 46173 | B32: 本月合计 | F32: =SUBTOTAL(9,F24:F31) -> 0 | H32: =SUBTOTAL(9,H24:H31) -> 0 | I32: =SUBTOTAL(9,I24:I31) -> 0 | J32: =SUBTOTAL(9,J24:J31) -> 0 | K32: =SUBTOTAL(9,K24:K31) -> 0 | L32: =SUBTOTAL(9,L24:L31) -> 0 | M32: =SUBTOTAL(9,M24:M31) -> 0 | N32: =SUBTOTAL(9,N24:N31) -> 0 | O32: =SUBTOTAL(9,O24:O31) -> 0 | ... Q32: =SUBTOTAL(9,Q24:Q31) -> 0 | R32: =L32+Q32-J32 -> 0
A37: 46203 | B37: 本月合计 | F37: =SUBTOTAL(9,F33:F36) -> 0 | G37: =SUBTOTAL(9,G33:G36) -> 0 | H37: =SUBTOTAL(9,H33:H36) -> 0 | I37: =SUBTOTAL(9,I33:I36) -> 0 | J37: =SUBTOTAL(9,J33:J36) -> 0 | K37: =SUBTOTAL(9,K33:K36) -> 0 | L37: =SUBTOTAL(9,L33:L36) -> 0 | M37: =SUBTOTAL(9,M33:M36) -> 0 | ... Q37: =SUBTOTAL(9,Q33:Q36) -> 0 | R37: =L37+Q37-J37 -> 0
A48: 46234 | B48: 本月合计 | F48: =SUBTOTAL(9,F38:F47) -> 0 | H48: =SUBTOTAL(9,H38:H47) -> 0 | I48: =SUBTOTAL(9,I38:I47) -> 0 | J48: =SUBTOTAL(9,J38:J47) -> 0 | K48: =SUBTOTAL(9,K38:K47) -> 0 | L48: =SUBTOTAL(9,L38:L47) -> 0 | M48: =SUBTOTAL(9,M38:M47) -> 0 | N48: =SUBTOTAL(9,N38:N47) -> 0 | O48: =SUBTOTAL(9,O38:O47) -> 0 | ... Q48: =SUBTOTAL(9,Q38:Q47) -> 0 | R48: =L48+Q48-J48 -> 0
A61: 46265 | B61: 本月合计 | F61: =SUBTOTAL(9,F49:F60) -> 0 | H61: =SUBTOTAL(9,H49:H60) -> 0 | I61: =SUBTOTAL(9,I49:I60) -> 0 | J61: =SUBTOTAL(9,J49:J60) -> 0 | K61: =SUBTOTAL(9,K49:K60) -> 0 | L61: =SUBTOTAL(9,L49:L60) -> 0 | M61: =SUBTOTAL(9,M49:M60) -> 0 | N61: =SUBTOTAL(9,N49:N60) -> 0 | O61: =SUBTOTAL(9,O49:O60) -> 0 | ... Q61: =SUBTOTAL(9,Q49:Q60) -> 0 | R61: =L61+Q61-J61 -> 0
A74: 46295 | B74: 本月合计 | F74: =SUBTOTAL(9,F62:F73) -> 0 | H74: =SUBTOTAL(9,H62:H73) -> 0 | I74: =SUBTOTAL(9,I62:I73) -> 0 | J74: =SUBTOTAL(9,J62:J73) -> 0 | K74: =SUBTOTAL(9,K62:K73) -> 0 | L74: =SUBTOTAL(9,L62:L73) -> 0 | M74: =SUBTOTAL(9,M62:M73) -> 0 | N74: =SUBTOTAL(9,N62:N73) -> 0 | O74: =SUBTOTAL(9,O62:O73) -> 0 | ... Q74: =SUBTOTAL(9,Q62:Q73) -> 0 | R74: =L74+Q74-J74 -> 0
A86: 46326 | B86: 本月合计 | F86: =SUBTOTAL(9,F75:F85) -> 0 | H86: =SUBTOTAL(9,H75:H85) -> 0 | I86: =SUBTOTAL(9,I75:I85) -> 0 | J86: =SUBTOTAL(9,J75:J85) -> 0 | K86: =SUBTOTAL(9,K75:K85) -> 0 | L86: =SUBTOTAL(9,L75:L85) -> 0 | M86: =SUBTOTAL(9,M75:M85) -> 0 | N86: =SUBTOTAL(9,N75:N85) -> 0 | O86: =SUBTOTAL(9,O75:O85) -> 0 | ... Q86: =SUBTOTAL(9,Q75:Q85) -> 0 | R86: =L86+Q86-J86 -> 0
A96: 46356 | B96: 本月合计 | F96: =SUBTOTAL(9,F87:F95) -> 0 | H96: =SUBTOTAL(9,H87:H95) -> 0 | I96: =SUBTOTAL(9,I87:I95) -> 0 | J96: =SUBTOTAL(9,J87:J95) -> 0 | K96: =SUBTOTAL(9,K87:K95) -> 0 | L96: =SUBTOTAL(9,L87:L95) -> 0 | M96: =SUBTOTAL(9,M87:M95) -> 0 | N96: =SUBTOTAL(9,N87:N95) -> 0 | O96: =SUBTOTAL(9,O87:O95) -> 0 | ... Q96: =SUBTOTAL(9,Q87:Q95) -> 0 | R96: =L96+Q96-J96 -> 0
A107: 46387 | B107: 本月合计 | F107: =SUBTOTAL(9,F97:F106) -> 0 | H107: =SUBTOTAL(9,H97:H106) -> 0 | I107: =SUBTOTAL(9,I97:I106) -> 0 | J107: =SUBTOTAL(9,J97:J106) -> 0 | K107: =SUBTOTAL(9,K97:K106) -> 0 | L107: =SUBTOTAL(9,L97:L106) -> 0 | M107: =SUBTOTAL(9,M97:M106) -> 0 | N107: =SUBTOTAL(9,N97:N106) -> 0 | O107: =SUBTOTAL(9,O97:O106) -> 0 | ... Q107: =SUBTOTAL(9,Q97:Q106) -> 0 | R107: =L107+Q107-J107 -> 0
A110: 45299 | B110: 3619/3057 | C110: DEYUN | D110: ADEMIR | E110: FERRAGENS HOME HOUSE COM. EQUIP. E MAQUINAS LTDA

Sheet 销售帐 MARTELUX
A1: 2026年巴西销售发票总帐(MARTELUX)
A2: 麻德罗克思 | D2: =L2+R2-M2-N2-O2-P2 -> 0 | F2: =SUBTOTAL(9,F4:F2630) -> 515 | H2: =SUBTOTAL(9,H4:H2630) -> 212253.61 | J2: =SUBTOTAL(9,J4:J2630) -> 216264.76 | K2: =SUBTOTAL(9,K4:K2630) -> 513 | L2: =SUBTOTAL(9,L4:L2630) -> 215805.8 | M2: =SUBTOTAL(9,M4:M2630) -> 0 | N2: =SUBTOTAL(9,N4:N2630) -> 73845.94 | O2: =SUBTOTAL(9,O4:O2630) -> 116116.09 | P2: =SUBTOTAL(9,P4:P2630) -> 26302.73 | R2: =SUBTOTAL(9,R4:R2630) -> 458.96424 | T2: =SUBTOTAL(9,T4:T2630) -> 5.1727511e-12 | U2: =SUBTOTAL(9,U4:U2630) -> 0
A3: 发生日期 | B3: 销售单号 | C3: 编码 | D3: 商品型号 | E3: 客户单位 | F3: 数量 | G3: 单价 | H3: 金额 | I3: 税率 | J3: 含税金额 | K3: 数量 | L3: 总金额 | M3: 现金 | N3: 银行存款 | O3: BOLETO | P3: 刷卡/COM | Q3: 退货 DEVOLUÇÃO | R3: 卡费/Taxa de cartão de | S3: 卡率 | T3: 备注/OBSERVAÇÕES | U3: 说明/Descrição | W3: 客户编码
A4: 46028 | B4: 2988/2625 | D4: 销售 | E4: VT Ferramentas | K4: 6 | L4: =M4+P4+O4+N4-R4 -> 1679.24 | P4: 1720 | R4: =ROUND(P4*S4,2) -> 40.76 | S4: 0.0237 | T4: 06/01/2026-Martelux | BC4: 51 | BD4: MIG MMAVTIG LIFT201
A5: 46028 | B5: 2988/2625 | C5: 2100002017377 | D5: =VLOOKUP(C5,$BC:$BD,2,0) -> V-AK230MINI | E5: VT FERRAMENTAS LTDA | F5: 4 | G5: 230 | H5: =F5*G5 -> 920 | J5: =ROUND(F5*G5+H5*I5,2) -> 920 | L5: =M5+P5+O5+N5-R5 -> 0 | BC5: 131 | BD5: AK-MIG/MMA/LIT-TIG 130A
A6: 46028 | B6: 2988/2625 | C6: 2100002017520 | D6: =VLOOKUP(C6,$BC:$BD,2,0) -> MIG203 | E6: VT FERRAMENTAS LTDA | F6: 2 | G6: 400 | H6: =F6*G6 -> 800 | J6: =ROUND(F6*G6+H6*I6,2) -> 800 | L6: =M6+P6+O6+N6-R6 -> 0 | BC6: 134 | BD6: MIGMMATIG (LIFT)300
A7: 46027 | B7: 2985/2626 | D7: 销售-内部 | E7: Norte Tools | H7: =F7*G7 -> 0 | J7: =ROUND(F7*G7+H7*I7,2) -> 0 | L7: =M7+P7+O7+N7-R7 -> 0 | T7: 07/04/2026-Martelux | BC7: 2100002016448 | BD7: USK-2/1100W
A8: 46028 | B8: 2992/2627 | D8: 销售 | E8: VT Ferramentas | H8: =F8*G8 -> 0 | J8: =ROUND(F8*G8+H8*I8,2) -> 0 | K8: 1 | L8: =M8+P8+O8+N8-R8 -> 1012 | N8: 1012 | T8: 06/01/2026-Martelux | BC8: 2100002016677 | BD8: 12V/1.5AH
A9: 46028 | B9: 2992/2627 | C9: 2100002017872 | D9: =VLOOKUP(C9,$BC:$BD,2,0) -> MIG/MAG/MMA LIFT 250 | E9: VT FERRAMENTAS LTDA | F9: 1 | G9: 1012 | H9: =F9*G9 -> 1012 | J9: =ROUND(F9*G9+H9*I9,2) -> 1012 | L9: =M9+P9+O9+N9-R9 -> 0 | BC9: 2100002016752 | BD9: 配件
A10: 46028 | B10: 2993/2628 | D10: 销售 | E10: C.LIJUN | H10: =F10*G10 -> 0 | J10: =ROUND(F10*G10+H10*I10,2) -> 0 | K10: 1 | L10: =M10+P10+O10+N10-R10 -> 1592 | N10: 1592 | T10: 07/01/2026-Martelux | U10: =J10-H10 -> 0 | BC10: 2100002016769 | BD10: VC 18V-6
A11: 46028 | B11: 2993/2628 | C11: 2100002018145 | D11: =VLOOKUP(C11,$BC:$BD,2,0) -> MIG/MMA/TIG LIFT 300 | E11: C. LIJUN | F11: 1 | G11: 1592 | H11: =F11*G11 -> 1592 | J11: =ROUND(F11*G11+H11*I11,2) -> 1592 | L11: =M11+P11+O11+N11-R11 -> 0 | BC11: 2100002016868 | BD11: 750W UNIDADE
A12: 46028 | B12: 2991/2629 | D12: 销售 | E12: Nova Parafer | H12: =F12*G12 -> 0 | J12: =ROUND(F12*G12+H12*I12,2) -> 0 | K12: 6 | L12: =M12+P12+O12+N12-R12 -> 1750.43 | O12: 1750.43 | T12: 06/02/2026,08/03/2026 e 07/04/2026- Martelux | BC12: 2100002016936 | BD12: MIG MMA/TIG LIFT 201
A13: 46029 | B13: 2991/2629 | C13: 8002126321931 | D13: =VLOOKUP(C13,$BC:$BD,2,0) -> 3001/220V | E13: NOVA PARAFER-COMERCIO DE FERRAGENS LTDA | F13: 6 | G13: 267.65 | H13: =F13*G13 -> 1605.9 | J13: =ROUND(F13*G13+H13*I13,2)+144.53 -> 1750.43 | L13: =M13+P13+O13+N13-R13 -> 0 | BC13: 2100002017056 | BD13: 750W-4
A14: 46028 | B14: 2989/2630 | D14: 销售 | E14: UNIAO DAS FERRAMENTAS | H14: =F14*G14 -> 0 | J14: =ROUND(F14*G14+H14*I14,2) -> 0 | K14: 13 | L14: =M14+P14+O14+N14-R14 -> 3445 | O14: 3445 | T14: 06/02/2026,08/03/2026 e 07/04/2026- Martelux | U14: =J14-H14 -> 0 | BC14: 2100002017063 | BD14: 1200W-2 CABECOTE
A15: 46029 | B15: 2989/2630 | C15: 2100002017377 | D15: =VLOOKUP(C15,$BC:$BD,2,0) -> V-AK230MINI | E15: UNIAO DAS FERRAMENTAS LTDA | F15: 13 | G15: 265 | H15: =F15*G15 -> 3445 | J15: =ROUND(F15*G15+H15*I15,2) -> 3445 | L15: =M15+P15+O15+N15-R15 -> 0 | BC15: 2100002017070 | BD15: 1500W-4
A16: 46028 | B16: 2990/2631 | D16: 销售 | E16: Nova Parafer | H16: =F16*G16 -> 0 | J16: =ROUND(F16*G16+H16*I16,2) -> 0 | K16: 20 | L16: =M16+P16+O16+N16-R16 -> 5600 | N16: 5600 | T16: 06/01/226-Martelux | BC16: 2100002017087 | BD16: 1500W-2
A17: 46029 | B17: 2990/2631 | C17: 8002126322167 | D17: =VLOOKUP(C17,$BC:$BD,2,0) -> MINI MMA 225 BIVOLT | E17: NOVA PARAFER-COMERCIO DE FERRAGENS LTDA | F17: 20 | G17: 280 | H17: =F17*G17 -> 5600 | J17: =ROUND(F17*G17+H17*I17,2) -> 5600 | L17: =M17+P17+O17+N17-R17 -> 0 | BC17: 2100002017179 | BD17: MINI MMA-225 BIVOLT
A18: 46030 | B18: 2998/2632 | D18: 销售 | E18: CARVALHO MARMORES | H18: =F18*G18 -> 0 | J18: =ROUND(F18*G18+H18*I18,2) -> 0 | K18: 3 | L18: =M18+P18+O18+N18-R18 -> 1134 | N18: 1134 | T18: 08/01/2025-Martelux | U18: =J18-H18 -> 0 | BC18: 2100002017193 | BD18: MIG/MAG/MMA/TIG LIFT 255 BIVOLT
A19: 46030 | B19: 2998/2632 | C19: 2100002016448 | D19: =VLOOKUP(C19,$BC:$BD,2,0) -> USK-2/1100W | E19: CARVALHO MARMORES E GRANITOS LTDA | F19: 3 | G19: 378 | H19: =F19*G19 -> 1134 | J19: =ROUND(F19*G19+H19*I19,2) -> 1134 | L19: =M19+P19+O19+N19-R19 -> 0 | BC19: 2100002017377 | BD19: V-AK230MINI
A20: 46030 | B20: 2997/2633 | D20: 销售 | E20: Sidneia P Menezes | H20: =F20*G20 -> 0 | J20: =ROUND(F20*G20+H20*I20,2) -> 0 | K20: 20 | L20: =M20+P20+O20+N20-R20 -> 5708.46 | P20: =3000+2800 -> 5800 | R20: =ROUND(3000*2.37%+2800*0.73%,2) -> 91.54 | S20: 2.37%/0.73% | T20: 08/01/2025-Martelux | BC20: 2100002017384 | BD20: AK-MIG/MMA140T
A21: 46030 | B21: 2997/2633 | C21: 8002126322167 | D21: =VLOOKUP(C21,$BC:$BD,2,0) -> MINI MMA 225 BIVOLT | E21: SIDNEIA P. MENEZES COMERCIO DE FERRAMENTAS | F21: 20 | G21: 290 | H21: =F21*G21 -> 5800 | J21: =ROUND(F21*G21+H21*I21,2) -> 5800 | L21: =M21+P21+O21+N21-R21 -> 0 | BC21: 2100002017391 | BD21: AK-WSME200A
A22: 46029 | B22: 2996/2634 | D22: 销售 | E22: J C Nepomuceno | H22: =F22*G22 -> 0 | J22: =ROUND(F22*G22+H22*I22,2) -> 0 | K22: 13 | L22: =M22+P22+O22+N22-R22 -> 7959.2 | N22: 7959.2 | T22: 07/01/2026-Martelux | U22: =J22-H22 -> 0 | BC22: 2100002017452 | BD22: AK-CUT40
A23: 46030 | B23: 2996/2634 | C23: 2100002018206 | D23: =VLOOKUP(C23,$BC:$BD,2,0) -> MAX 65B DB | E23: J C NEPOMUCENO FERRAMENTAS | F23: 5 | G23: 692 | H23: =F23*G23 -> 3460 | I23: 0.052 | J23: =ROUND(F23*G23+H23*I23,2)+359.98 -> 3999.9 | L23: =M23+P23+O23+N23-R23 -> 0 | BC23: 2100002017445 | BD23: AK-CUT100A
A24: 46030 | B24: 2996/2634 | C24: 2100002017520 | D24: =VLOOKUP(C24,$BC:$BD,2,0) -> MIG203 | E24: J C NEPOMUCENO FERRAMENTAS | F24: 5 | G24: 400 | H24: =F24*G24 -> 2000 | J24: =ROUND(F24*G24+H24*I24,2) -> 2000 | L24: =M24+P24+O24+N24-R24 -> 0 | BC24: 2100002017520 | BD24: MIG203
A25: 46030 | B25: 2996/2634 | C25: 80021263221811 | D25: =VLOOKUP(C25,$BC:$BD,2,0) -> MIG MMA/TIG(LIFT)-200 | E25: J C NEPOMUCENO FERRAMENTAS | F25: 3 | G25: 653.1 | H25: =F25*G25 -> 1959.3 | J25: =ROUND(F25*G25+H25*I25,2) -> 1959.3 | L25: =M25+P25+O25+N25-R25 -> 0 | BC25: 2100002017582 | BD25: 配件
A26: 46030 | B26: 3001/2635 | D26: 销售 | E26: Polgas Distribuidora | H26: =F26*G26 -> 0 | J26: =ROUND(F26*G26+H26*I26,2) -> 0 | K26: 4 | L26: =M26+P26+O26+N26-R26 -> 3358.47 | P26: 3440 | R26: =ROUND(P26*S26,2) -> 81.53 | S26: 0.0237 | T26: 08/01/2026-Martelux | U26: =J26-H26 -> 0 | BC26: 2100002017629 | BD26: US MMA-220 BIVOLT
A27: 46030 | B27: 3001/2635 | C27: 2100002017704 | D27: =VLOOKUP(C27,$BC:$BD,2,0) -> AK-MMA/LIFT TIG 220A | E27: POLGAS DISTRIBUIDORA DE GAS LTDA | F27: 4 | G27: 860 | H27: =F27*G27 -> 3440 | J27: =ROUND(F27*G27+H27*I27,2) -> 3440 | L27: =M27+P27+O27+N27-R27 -> 0 | BC27: 2100002017636 | BD27: US/MMA-250 BIVOLT
A28: 46030 | B28: 3000/2636 | D28: 销售-内部 | E28: NORTE TOOLS | L28: =M28+P28+O28+N28-R28 -> 0 | T28: 12/04/2026-Martelux | BC28: 2100002017650 | BD28: AK-MMA/LIFT TIG170A BIVOLT
A29: 46030 | B29: 2999/2637 | D29: 销售 | E29: R C NEPOMUCENO | H29: =F29*G29 -> 0 | J29: =ROUND(F29*G29+H29*I29,2) -> 0 | K29: 10 | L29: =M29+P29+O29+N29-R29 -> 5599.92 | N29: 5599.92 | T29: 08/01/2026-Matelux | U29: =J29-H29 -> 0 | BC29: 2100002017698 | BD29: AK-MMA/LIFT TIG170A
A30: 46031 | B30: 2999/2637 | C30: 2100002018206 | D30: =VLOOKUP(C30,$BC:$BD,2,0) -> MAX 65B DB | E30: R C NEPOMUCENO FERRAMENTAS | F30: 4 | G30: 692 | H30: =F30*G30 -> 2768 | I30: 0.052 | J30: =ROUND(F30*G30+H30*I30,2) -> 2911.94 | L30: =M30+P30+O30+N30-R30 -> 0 | BC30: 2100002017728 | BD30: AK-MIG/MMA/LIFT TIG 150A
A31: 46031 | B31: 2999/2637 | C31: 2100002017520 | D31: =VLOOKUP(C31,$BC:$BD,2,0) -> MIG203 | E31: R C NEPOMUCENO FERRAMENTAS | F31: 6 | G31: 400 | H31: =F31*G31 -> 2400 | J31: =ROUND(F31*G31+H31*I31,2)+287.98 -> 2687.98 | L31: =M31+P31+O31+N31-R31 -> 0 | BC31: 2100002017742 | BD31: MIG/MMA/TIG (LIFT) 300
A32: 46029 | B32: 2994/2638 | D32: 销售 | E32: VT Ferramentas | H32: =F32*G32 -> 0 | J32: =ROUND(F32*G32+H32*I32,2) -> 0 | K32: 6 | L32: =M32+P32+O32+N32-R32 -> 1679.24 | P32: 1720 | R32: =ROUND(P32*S32,2) -> 40.76 | S32: 0.0237 | T32: 09/01/2026-Martelux | BC32: 2100002017865 | BD32: MIG/MMA/TIG LIFT 200
A33: 46031 | B33: 2994/2638 | C33: 2100002017520 | D33: =VLOOKUP(C33,$BC:$BD,2,0) -> MIG203 | E33: VT FERRAMENTAS LTDA | F33: 2 | G33: 400 | H33: =F33*G33 -> 800 | J33: =ROUND(F33*G33+H33*I33,2) -> 800 | L33: =M33+P33+O33+N33-R33 -> 0 | BC33: 2100002017872 | BD33: MIG/MAG/MMA LIFT 250
A34: 46031 | B34: 2994/2638 | C34: 2100002017377 | D34: =VLOOKUP(C34,$BC:$BD,2,0) -> V-AK230MINI | E34: VT FERRAMENTAS LTDA | F34: 4 | G34: 230 | H34: =F34*G34 -> 920 | J34: =ROUND(F34*G34+H34*I34,2) -> 920 | L34: =M34+P34+O34+N34-R34 -> 0 | BC34: 2100002017896 | BD34: PHJ1.8-20-128W
A35: 46035 | B35: 3005/2639 | D35: 销售 | E35: Geniobox Comercial | H35: =F35*G35 -> 0 | J35: =ROUND(F35*G35+H35*I35,2) -> 0 | K35: 1 | L35: =M35+P35+O35+N35-R35 -> 280 | N35: 280 | R35: 0 | T35: 13/01/2026-Martelux | U35: =J35-H35 -> 0 | BC35: 2100002017902 | BD35: PHJ2.0-25- 250W
A36: 46035 | B36: 3005/2639 | C36: 8002126322167 | D36: =VLOOKUP(C36,$BC:$BD,2,0) -> MINI MMA 225 BIVOLT | E36: GENIOBOX COMERCIAL LTDA | F36: 1 | G36: 280 | H36: =F36*G36 -> 280 | J36: =ROUND(F36*G36+H36*I36,2) -> 280 | L36: =M36+P36+O36+N36-R36 -> 0 | BC36: 2100002017933 | BD36: QDX1.5-13 370W
A37: 46035 | B37: 3006/2640 | D37: 销售-内部 | E37: Norte Tools | H37: =F37*G37 -> 0 | J37: =ROUND(F37*G37+H37*I37,2) -> 0 | L37: =M37+P37+O37+N37-R37 -> 0 | T37: 14/04/2026-Martelux | U37: =J37-H37 -> 0 | BC37: 2100002017940 | BD37: QDX1.5-20 - 550W
A38: 46037 | B38: 3008/2641 | D38: 销售 | E38: Geniobox Comercial | H38: =F38*G38 -> 0 | J38: =ROUND(F38*G38+H38*I38,2) -> 0 | K38: 1 | L38: =M38+P38+O38+N38-R38 -> 280 | N38: 280 | R38: 0 | T38: 15/01/2026-Martelux | U38: =J38-H38 -> 0 | BC38: 2100002017971 | BD38: WQD10-10-0 75PP
A39: 46037 | B39: 3008/2641 | C39: 8002126322167 | D39: =VLOOKUP(C39,$BC:$BD,2,0) -> MINI MMA 225 BIVOLT | E39: GENIOBOX COMERCIAL LTDA | F39: 1 | G39: 280 | H39: =F39*G39 -> 280 | J39: =ROUND(F39*G39+H39*I39,2) -> 280 | L39: =M39+P39+O39+N39-R39 -> 0 | BC39: 2100002018008 | BD39: PT-31 - PONTEIRA
A40: 46041 | B40: 3011/2642 | D40: 销售 | E40: Ferragens Home | H40: =F40*G40 -> 0 | J40: =ROUND(F40*G40+H40*I40,2) -> 0 | K40: 1 | L40: =M40+P40+O40+N40-R40 -> 1580.38 | P40: 1592 | R40: =ROUND(P40*S40,2) -> 11.62 | S40: 0.0073 | T40: 19/01/2026-Martelux | BC40: 2100002018015 | BD40: P80
A41: 46041 | B41: 3011/2642 | C41: 2100002018145 | D41: =VLOOKUP(C41,$BC:$BD,2,0) -> MIG/MMA/TIG LIFT 300 | E41: FERRAGENS HOME HOUSE COM. DE EQUIP E MAQUINAS LTDA | F41: 1 | G41: 1592 | H41: =F41*G41 -> 1592 | J41: =ROUND(F41*G41+H41*I41,2) -> 1592 | L41: =M41+P41+O41+N41-R41 -> 0 | BC41: 2100002018022 | BD41: PARTES E PECAS USO EM
A42: 46038 | B42: 3009/2643 | D42: 销售 | E42: V S Da Silva | H42: =F42*G42 -> 0 | J42: =ROUND(F42*G42+H42*I42,2) -> 0 | K42: 24 | L42: =M42+P42+O42+N42-R42 -> 6463.09 | O42: 6463.09 | R42: 0 | T42: 19/02/2026,19/03/2026 e 19/04/2026- Martelux | U42: =J42-H42 -> 0 | BC42: 2100002018053 | BD42: DB 1800-70/220V
A43: 46041 | B43: 3009/2643 | C43: 8002126321931 | D43: =VLOOKUP(C43,$BC:$BD,2,0) -> 3001/220V | E43: V.S DA SILVA MAQUINAS, FERRAGENS E FERRAMENTAS IND LTDA | F43: 24 | G43: 247.06 | H43: =F43*G43 -> 5929.44 | J43: =ROUND(F43*G43+H43*I43,2)+533.65 -> 6463.09 | L43: =M43+P43+O43+N43-R43 -> 0 | BC43: 2100002018060 | BD43: DB 1600-30/220V
A44: 46042 | B44: 3015/2644 | D44: 销售-内部 | E44: Norte Tools | H44: =F44*G44 -> 0 | J44: =ROUND(F44*G44+H44*I44,2) -> 0 | L44: =M44+P44+O44+N44-R44 -> 0 | R44: 0 | T44: 20/04/2026-Martelux | BC44: 2100002018077 | BD44: USK810/220V
A45: 46042 | B45: 3018/2645 | D45: 销售 | E45: Edilson Silva | H45: =F45*G45 -> 0 | J45: =ROUND(F45*G45+H45*I45,2) -> 0 | K45: 10 | L45: =M45+P45+O45+N45-R45 -> 4000 | N45: 4000 | R45: 0 | T45: 20/01/2026-Martelux | U45: =J45-H45 -> 0 | BC45: 2100002018084 | BD45: RH 1500-6
A46: 46043 | B46: 3018/2645 | C46: 2100002017520 | D46: =VLOOKUP(C46,$BC:$BD,2,0) -> MIG203 | E46: EDILSON SILVA DOS SANTOS | F46: 10 | G46: 400 | H46: =F46*G46 -> 4000 | J46: =ROUND(F46*G46+H46*I46,2) -> 4000 | L46: =M46+P46+O46+N46-R46 -> 0 | BC46: 2100002018145 | BD46: MIG/MMA/TIG LIFT 300
A47: 46042 | B47: 3017/2646 | D47: 销售 | E47: VT Ferramentas | H47: =F47*G47 -> 0 | J47: =ROUND(F47*G47+H47*I47,2) -> 0 | K47: 4 | L47: =M47+P47+O47+N47-R47 -> 1148 | O47: 1148 | R47: 0 | T47: 30/01/2026-Martelux | U47: =J47-H47 -> 0 | BC47: 2100002018176 | BD47: MMCT-200
A48: 46043 | B48: 3017/2646 | C48: 2100002017377 | D48: =VLOOKUP(C48,$BC:$BD,2,0) -> V-AK230MINI | E48: VT FERRAMENTAS LTDA | F48: 4 | G48: 287 | H48: =F48*G48 -> 1148 | J48: =ROUND(F48*G48+H48*I48,2) -> 1148 | L48: =M48+P48+O48+N48-R48 -> 0 | BC48: 2100002018190 | BD48: 配件
A49: 46042 | B49: 3014/2647 | D49: 销售 | E49: J C Nepomuceno | H49: =F49*G49 -> 0 | J49: =ROUND(F49*G49+H49*I49,2) -> 0 | K49: 3 | L49: =M49+P49+O49+N49-R49 -> 2025 | N49: 2025 | R49: 0 | T49: 21/01/2026-Martelux | U49: =J49-H49 -> 0 | BC49: 6976735420724 | BD49: AK-MIG/MMA/LIFT-TIG 130A
A50: 46043 | B50: 3014/2647 | C50: 80021263221811 | D50: =VLOOKUP(C50,$BC:$BD,2,0) -> MIG MMA/TIG(LIFT)-200 | E50: J C NEPOMUCENO FERRAMENTAS | F50: 3 | G50: 675 | H50: =F50*G50 -> 2025 | J50: =ROUND(F50*G50+H50*I50,2) -> 2025 | L50: =M50+P50+O50+N50-R50 -> 0 | BC50: 8002126321580 | BD50: MINI-MMA-219 220V USK
A51: 46043 | B51: 3020/2648 | D51: 销售 | E51: MG MEDICAL | H51: =F51*G51 -> 0 | J51: =ROUND(F51*G51+H51*I51,2) -> 0 | K51: 1 | L51: =M51+P51+O51+N51-R51 -> 639 | N51: 639 | R51: 0 | T51: 22/01/2026-MARTELUX | BC51: 8002126321696 | BD51: MAX850-115
A52: 46043 | B52: 3020/2648 | C52: 2100002017087 | D52: =VLOOKUP(C52,$BC:$BD,2,0) -> 1500W-2 | E52: MG MEDICAL COMERCIO E IMPORTACAO LTDA | F52: 1 | G52: 639 | H52: =F52*G52 -> 639 | J52: =ROUND(F52*G52+H52*I52,2) -> 639 | L52: =M52+P52+O52+N52-R52 -> 0 | BC52: 8002126321719 | BD52: USK-01-12V
A53: 46041 | B53: 3013/2649 | D53: 销售 | E53: Marmoraria Garbarino | H53: =F53*G53 -> 0 | J53: =ROUND(F53*G53+H53*I53,2) -> 0 | K53: 1 | L53: =M53+P53+O53+N53-R53 -> 902.91 | P53: 924.83 | R53: =ROUND(P53*S53,2) -> 21.92 | S53: 0.0237 | T53: 19/01/2026-Martelux | U53: =J53-H53 -> 0 | BC53: 8002126321870 | BD53: 2801/220V
A54: 46044 | B54: 3013/2649 | C54: 2100002018206 | D54: =VLOOKUP(C54,$BC:$BD,2,0) -> MAX 65B DB | E54: MARMORARIA GARBARINO LTDA | F54: 1 | G54: 800 | H54: =F54*G54 -> 800 | I54: 0.052 | J54: =ROUND(F54*G54+H54*I54,2)+83.23 -> 924.83 | L54: =M54+P54+O54+N54-R54 -> 0 | BC54: 8002126321931 | BD54: 3001/220V
A55: 46041 | B55: /2650 | D55: 运输 发票 | E55: REMESSA | H55: =F55*G55 -> 0 | J55: =ROUND(F55*G55+H55*I55,2) -> 0 | L55: =M55+P55+O55+N55-R55 -> 0 | R55: 0 | BC55: 8002126322037 | BD55: MINI MMA 210 BIVOLT
A56: 46044 | B56: 3021/2651 | D56: 销售 | E56: Bazzo Maquinas | H56: =F56*G56 -> 0 | J56: =ROUND(F56*G56+H56*I56,2) -> 0 | K56: 60 | L56: =M56+P56+O56+N56-R56 -> 37384.8 | O56: 37384.8 | R56: 0 | T56: 23/02/2026,23/03/2026 e 23/04/2026 | U56: =J56-H56 -> 0 | BC56: 8002126322068 | BD56: MAX-32EGB
A57: 46045 | B57: 3021/2651 | C57: 80021263221811 | D57: =VLOOKUP(C57,$BC:$BD,2,0) -> MIG MMA/TIG(LIFT)-200 | E57: BAZZO MAQUINAS LTDA | F57: 60 | G57: 623.08 | H57: =F57*G57 -> 37384.8 | J57: =ROUND(F57*G57+H57*I57,2) -> 37384.8 | L57: =M57+P57+O57+N57-R57 -> 0 | BC57: 8002126322167 | BD57: MINI MMA 225 BIVOLT
A58: 46044 | B58: 3022/2652 | D58: 销售 | E58: Emporio Das Ferramentas | H58: =F58*G58 -> 0 | J58: =ROUND(F58*G58+H58*I58,2) -> 0 | L58: =M58+P58+O58+N58-R58 -> 2370.27 | P58: 2387.7 | R58: =ROUND(P58*S58,2) -> 17.43 | S58: 0.0073 | T58: 23/01/2026-MARTELUX | BC58: 8002126322181 | BD58: MIG MMA/TIG(LIFT)-200
A59: 46045 | B59: 3022/2652 | C59: 2100002017193 | D59: =VLOOKUP(C59,$BC:$BD,2,0) -> MIG/MAG/MMA/TIG LIFT 255 BIVOLT | E59: EMPORIO DAS FERRAMENTAS AUTOMOTIVAS EIRELI | F59: 2 | G59: 1193.85 | H59: =F59*G59 -> 2387.7 | J59: =ROUND(F59*G59+H59*I59,2) -> 2387.7 | L59: =M59+P59+O59+N59-R59 -> 0 | BC59: 8424608028204 | BD59: MIG/MAG/MMA/TIG(LIFT)-250
A60: 46045 | B60: 3026/2653 | D60: 销售 | E60: Daiane Da Silva | H60: =F60*G60 -> 0 | J60: =ROUND(F60*G60+H60*I60,2) -> 0 | K60: 1 | L60: =M60+P60+O60+N60-R60 -> 1193.85 | N60: 1193.85 | R60: 0 | T60: 23/01/2026-MARTELUX | U60: =J60-H60 -> 0 | BC60: 8424608028211 | BD60: MIG MMA/TIG LIFT 255 BIVOLT
A61: 46045 | B61: 3026/2653 | C61: 2100002017193 | D61: =VLOOKUP(C61,$BC:$BD,2,0) -> MIG/MAG/MMA/TIG LIFT 255 BIVOLT | E61: DAIANE DA SILVA BELTRAMINI | F61: 1 | G61: 1193.85 | H61: =F61*G61 -> 1193.85 | J61: =ROUND(F61*G61+H61*I61,2) -> 1193.85 | L61: =M61+P61+O61+N61-R61 -> 0 | BC61: 84246080282723 | BD61: CD 21V-13I
A62: 46045 | B62: 3025/2654 | D62: 销售 | E62: Fabio Souza | H62: =F62*G62 -> 0 | J62: =ROUND(F62*G62+H62*I62,2) -> 0 | K62: 1 | L62: =M62+P62+O62+N62-R62 -> 304 | N62: 304 | R62: 0 | T62: 23/01/2026-MARTELUZ | U62: =J62-H62 -> 0 | BC62: 8424608028501 | BD62: KW-21V/4"
A63: 46045 | B63: 3025/2654 | C63: 8002126321931 | D63: =VLOOKUP(C63,$BC:$BD,2,0) -> 3001/220V | E63: FABIO SOUZA DE JESUS | F63: 1 | G63: 278 | H63: =F63*G63 -> 278 | J63: =ROUND(F63*G63+H63*I63,2)+26 -> 304 | L63: =M63+P63+O63+N63-R63 -> 0 | BC63: 8424608028518 | BD63: KW-21V/10"
A64: 46048 | B64: 3028/2655 | D64: 销售 | E64: Pezzitron Equipamentos | H64: =F64*G64 -> 0 | J64: =ROUND(F64*G64+H64*I64,2) -> 0 | K64: 1 | L64: =M64+P64+O64+N64-R64 -> 639 | N64: 639 | R64: 0 | T64: 26/01/2026-MARTELUX | U64: =J64-H64 -> 0 | BC64: 8424608028549 | BD64: 21V-2822
A65: 46048 | B65: 3028/2655 | C65: 2100002017087 | D65: =VLOOKUP(C65,$BC:$BD,2,0) -> 1500W-2 | E65: PEZZITRON EQUIPAMENTOS LTDA | F65: 1 | G65: 639 | H65: =F65*G65 -> 639 | J65: =ROUND(F65*G65+H65*I65,2) -> 639 | L65: =M65+P65+O65+N65-R65 -> 0 | BC65: 8424608028693 | BD65: BC 21.5V-1.1A
A66: 46048 | B66: 3029/2656 | D66: 销售 | E66: V.S DA SILVA | H66: =F66*G66 -> 0 | J66: =ROUND(F66*G66+H66*I66,2) -> 0 | K66: 10 | L66: =M66+P66+O66+N66-R66 -> 3312.41 | O66: 3312.41 | R66: 0 | T66: 26/02/2026,26/03/226 e 26/04/2026-MARTELUX | BC66: 8424608028761 | BD66: IW 21V-12.7
A67: 46048 | B67: 3029/2656 | C67: 2100002018077 | D67: =VLOOKUP(C67,$BC:$BD,2,0) -> USK810/220V | E67: V.S DA SILVA MAQUINAS, FERRAGENS E FERRAMENTAS IND LTDA | F67: 10 | G67: 286.53 | H67: =F67*G67 -> 2865.3 | I67: 0.052 | J67: =ROUND(F67*G67+H67*I67,2)+298.11 -> 3312.41 | L67: =M67+P67+O67+N67-R67 -> 0 | BC67: 8424608028952 | BD67: MIG203
A68: 46045 | B68: 3023/2657 | D68: 销售 | E68: R C NEPOMUCENO | H68: =F68*G68 -> 0 | J68: =ROUND(F68*G68+H68*I68,2) -> 0 | K68: 15 | L68: =M68+P68+O68+N68-R68 -> 5553.96 | N68: 5553.96 | R68: 0 | T68: 26/01/2026-MARTELUX | U68: =J68-H68 -> 0 | BC68: 2100002018206 | BD68: MAX 65B DB
A69: 46048 | B69: 3023/2657 | C69: 2100002017377 | D69: =VLOOKUP(C69,$BC:$BD,2,0) -> V-AK230MINI | E69: R C NEPOMUCENO FERRAMENTAS | F69: 12 | G69: 230 | H69: =F69*G69 -> 2760 | J69: =ROUND(F69*G69+H69*I69,2)+143.99 -> 2903.99 | L69: =M69+P69+O69+N69-R69 -> 0 | BC69: 8002126321955 | BD69: CUT-56/HF2
A70: 46048 | B70: 3023/2657 | C70: 2100002018206 | D70: =VLOOKUP(C70,$BC:$BD,2,0) -> MAX 65B DB | E70: R C NEPOMUCENO FERRAMENTAS | F70: 2 | G70: 692 | H70: =F70*G70 -> 1384 | I70: 0.052 | J70: =ROUND(F70*G70+H70*I70,2) -> 1455.97 | L70: =M70+P70+O70+N70-R70 -> 0 | BC70: 80021263221811 | BD70: MIG MMA/TIG(LIFT)-200
A71: 46048 | B71: 3023/2657 | C71: 2100002017193 | D71: =VLOOKUP(C71,$BC:$BD,2,0) -> MIG/MAG/MMA/TIG LIFT 255 BIVOLT | E71: R C NEPOMUCENO FERRAMENTAS | F71: 1 | G71: 1194 | H71: =F71*G71 -> 1194 | J71: =ROUND(F71*G71+H71*I71,2) -> 1194 | L71: =M71+P71+O71+N71-R71 -> 0 | BC71: 2100002017421 | BD71: AK-CUT40A
A72: 46048 | B72: 3027/2658 | D72: 销售 | E72: R C NEPOMUCENO | H72: =F72*G72 -> 0 | J72: =ROUND(F72*G72+H72*I72,2) -> 0 | K72: 3 | L72: =M72+P72+O72+N72-R72 -> 690 | N72: 690 | R72: 0 | T72: 26/01/2026-MARTELUX | U72: =J72-H72 -> 0 | BC72: 2100002017414 | BD72: AK-MIG/MMA200T
A73: 46048 | B73: 3027/2658 | C73: 2100002017377 | D73: =VLOOKUP(C73,$BC:$BD,2,0) -> V-AK230MINI | E73: R C NEPOMUCENO FERRAMENTAS | F73: 3 | G73: 230 | H73: =F73*G73 -> 690 | J73: =ROUND(F73*G73+H73*I73,2) -> 690 | L73: =M73+P73+O73+N73-R73 -> 0 | BC73: 2100002017735 | BD73: AK-MIG/MMA/LIFT TIG 170A
A74: 46048 | B74: 3030/2659 | D74: 销售-内部 | E74: Norte Tools | H74: =F74*G74 -> 0 | J74: =ROUND(F74*G74+H74*I74,2) -> 0 | L74: =M74+P74+O74+N74-R74 -> 0 | R74: 0 | T74: 27/04/2026-MARTELUX | BC74: 2100002017681 | BD74: AK-MINI/MMA120A
A75: 46049 | B75: 3032/2660 | D75: 销售 | E75: VT Ferramentas | H75: =F75*G75 -> 0 | J75: =ROUND(F75*G75+H75*I75,2) -> 0 | K75: 1 | L75: =M75+P75+O75+N75-R75 -> 397.08 | P75: 400 | R75: =ROUND(P75*S75,2) -> 2.92 | S75: 0.0073 | T75: 27/01/2026-MARTELUX | U75: =J75-H75 -> 0 | BC75: 2100002017438 | BD75: AK-CUT60A
A76: 46049 | B76: 3032/2660 | C76: 2100002017520 | D76: =VLOOKUP(C76,$BC:$BD,2,0) -> MIG203 | E76: VT FERRAMENTAS LTDA | F76: 1 | G76: 400 | H76: =F76*G76 -> 400 | J76: =ROUND(F76*G76+H76*I76,2) -> 400 | L76: =M76+P76+O76+N76-R76 -> 0 | BC76: 2100002017704 | BD76: AK-MMA/LIFT TIG 220A
A77: 46049 | B77: /2661 | D77: 运输 发票 | E77: REMESSA | H77: =F77*G77 -> 0 | J77: =ROUND(F77*G77+H77*I77,2) -> 0 | L77: =M77+P77+O77+N77-R77 -> 0 | R77: 0 | BC77: 2100002018312 | BD77: 3SDM2/11-0.5HP
A78: 46049 | B78: /2662 | D78: 运输 发票 | E78: REMESSA | H78: =F78*G78 -> 0 | J78: =ROUND(F78*G78+H78*I78,2) -> 0 | L78: =M78+P78+O78+N78-R78 -> 0 | R78: 0 | U78: =J78-H78 -> 0 | BC78: 2100002018299 | BD78: 3SDM2/6-0.33HP
A79: 46050 | B79: /2663 | D79: 运输 发票 | E79: REMESSA | H79: =F79*G79 -> 0 | J79: =ROUND(F79*G79+H79*I79,2) -> 0 | L79: =M79+P79+O79+N79-R79 -> 0 | R79: 0 | BC79: 8424608028464 | BD79: HG 2000-650
A80: 46050 | B80: /2664 | D80: 运输 发票 | E80: REMESSA | H80: =F80*G80 -> 0 | J80: =ROUND(F80*G80+H80*I80,2) -> 0 | L80: =M80+P80+O80+N80-R80 -> 0 | R80: 0 | U80: =J80-H80 -> 0 | BC80: 2100002018183 | BD80: AK-CUT100
A81: 46049 | B81: 3031/2665 | D81: 销售 | E81: THIAGO MENDES | H81: =F81*G81 -> 0 | J81: =ROUND(F81*G81+H81*I81,2) -> 0 | K81: 15 | L81: =M81+P81+O81+N81-R81 -> 5525 | O81: 5525 | R81: 0 | T81: 05/03/2026, 05/04/2026 e 05/05/2026 | BC81: 2100002018152 | BD81: AK-TIG200A
A82: 46051 | B82: 3031/2665 | C82: 2100002017520 | D82: =VLOOKUP(C82,$BC:$BD,2,0) -> MIG203 | E82: THIAGO MENDES SILVA | F82: 5 | G82: 575 | H82: =F82*G82 -> 2875 | J82: =ROUND(F82*G82+H82*I82,2) -> 2875 | L82: =M82+P82+O82+N82-R82 -> 0
A83: 46051 | B83: 3031/2665 | C83: 2100002017377 | D83: =VLOOKUP(C83,$BC:$BD,2,0) -> V-AK230MINI | E83: THIAGO MENDES SILVA | F83: 10 | G83: 265 | H83: =F83*G83 -> 2650 | J83: =ROUND(F83*G83+H83*I83,2) -> 2650 | L83: =M83+P83+O83+N83-R83 -> 0
A84: 46050 | B84: 3036/2666 | D84: 销售 | E84: M.L.GOMES DO CARMO | H84: =F84*G84 -> 0 | J84: =ROUND(F84*G84+H84*I84,2) -> 0 | K84: 2 | L84: =M84+P84+O84+N84-R84 -> 1800 | O84: 1800 | R84: 0 | T84: 03/03/2026-MARTELUX | U84: =J84-H84 -> 0
A85: 46051 | B85: 3036/2666 | C85: 80021263221811 | D85: =VLOOKUP(C85,$BC:$BD,2,0) -> MIG MMA/TIG(LIFT)-200 | E85: M.L.GOMES DO CARMO TINTAS LTDA | F85: 2 | G85: 900 | H85: =F85*G85 -> 1800 | J85: =ROUND(F85*G85+H85*I85,2) -> 1800 | L85: =M85+P85+O85+N85-R85 -> 0
A86: 46050 | B86: 3035/2667 | D86: 销售 | E86: BRENNER DE ANDRADE | H86: =F86*G86 -> 0 | J86: =ROUND(F86*G86+H86*I86,2) -> 0 | K86: 1 | L86: =M86+P86+O86+N86-R86 -> 450 | O86: 450 | R86: 0 | T86: 03/03/2026,03/04/2023 e 03/05/2026-MARTELUX
A87: 46051 | B87: 3035/2667 | C87: 2100002016448 | D87: =VLOOKUP(C87,$BC:$BD,2,0) -> USK-2/1100W | E87: BRENNER DE ANDRADE FERREIRA | F87: 1 | G87: 450 | H87: =F87*G87 -> 450 | J87: =ROUND(F87*G87+H87*I87,2) -> 450 | L87: =M87+P87+O87+N87-R87 -> 0
A88: 46051 | B88: 3037/2668 | D88: 销售 | E88: VT Ferramentas | H88: =F88*G88 -> 0 | J88: =ROUND(F88*G88+H88*I88,2) -> 0 | K88: 4 | L88: =M88+P88+O88+N88-R88 -> 913.28 | P88: 920 | R88: =ROUND(P88*S88,2) -> 6.72 | S88: 0.0073 | T88: 29/01/2026-MARTELUX | U88: =J88-H88 -> 0
A89: 46051 | B89: 3037/2668 | C89: 2100002017377 | D89: =VLOOKUP(C89,$BC:$BD,2,0) -> V-AK230MINI | E89: VT FERRAMENTAS LTDA | F89: 4 | G89: 230 | H89: =F89*G89 -> 920 | J89: =ROUND(F89*G89+H89*I89,2) -> 920 | L89: =M89+P89+O89+N89-R89 -> 0
A90: 46051 | B90: 3038/2669 | D90: 销售 | E90: Geniobox Comercial | H90: =F90*G90 -> 0 | J90: =ROUND(F90*G90+H90*I90,2) -> 0 | K90: 1 | L90: =M90+P90+O90+N90-R90 -> 280 | N90: 280 | R90: 0 | T90: 29/01/2026-MARTELUX
A91: 46051 | B91: 3038/2669 | C91: 8002126322167 | D91: =VLOOKUP(C91,$BC:$BD,2,0) -> MINI MMA 225 BIVOLT | E91: GENIOBOX COMERCIAL LTDA | F91: 1 | G91: 280 | H91: =F91*G91 -> 280 | J91: =ROUND(F91*G91+H91*I91,2) -> 280 | L91: =M91+P91+O91+N91-R91 -> 0
A92: 46051 | B92: 2670/2670 | D92: 销售 | E92: Daiane Da Silva | H92: =F92*G92 -> 0 | J92: =ROUND(F92*G92+H92*I92,2) -> 0 | K92: 1 | L92: =M92+P92+O92+N92-R92 -> 1193.85 | N92: 1193.85 | R92: 0 | T92: 29/01/2026-MARTELUX | U92: =J92-H92 -> 0
A93: 46051 | B93: 2670/2670 | C93: 2100002017193 | D93: =VLOOKUP(C93,$BC:$BD,2,0) -> MIG/MAG/MMA/TIG LIFT 255 BIVOLT | E93: DAIANE DA SILVA BELTRAMINI | F93: 1 | G93: 1193.85 | H93: =F93*G93 -> 1193.85 | J93: =ROUND(F93*G93+H93*I93,2) -> 1193.85 | L93: =M93+P93+O93+N93-R93 -> 0
A94: 46051 | B94: 3039/2671 | D94: 销售 | E94: BACCARINI E CHARBEL | H94: =F94*G94 -> 0 | J94: =ROUND(F94*G94+H94*I94,2) -> 0 | K94: 20 | L94: =M94+P94+O94+N94-R94 -> 5600 | N94: 5600 | R94: 0 | T94: 29/01/2026-MARTELUX
A95: 46052 | B95: 3039/2671 | C95: 8002126322167 | D95: =VLOOKUP(C95,$BC:$BD,2,0) -> MINI MMA 225 BIVOLT | E95: BACCARINI E CHARBEL LTDA | F95: 20 | G95: 280 | H95: =F95*G95 -> 5600 | J95: =ROUND(F95*G95+H95*I95,2) -> 5600 | L95: =M95+P95+O95+N95-R95 -> 0
A96: 46052 | B96: /2672 | D96: 运输 发票 | H96: =F96*G96 -> 0 | J96: =ROUND(F96*G96+H96*I96,2) -> 0 | L96: =M96+P96+O96+N96-R96 -> 0 | R96: 0 | U96: =J96-H96 -> 0
A97: 46052 | B97: 3041/2673 | D97: 销售 | E97: Ferragens Home | K97: 1 | L97: =M97+P97+O97+N97-R97 -> 1535.71 | P97: 1547 | R97: =ROUND(P97*S97,2) -> 11.29 | S97: 0.0073 | T97: 30/01/2026-Martelux
A98: 46052 | B98: 3041/2673 | C98: 2100002017735 | D98: =VLOOKUP(C98,$BC:$BD,2,0) -> AK-MIG/MMA/LIFT TIG 170A | E98: FERRAGENS HOME HOUSE COM. DE EQUIP E MAQUINAS LTDA | F98: 1 | G98: 1547 | H98: =F98*G98 -> 1547 | J98: =ROUND(F98*G98+H98*I98,2) -> 1547 | L98: =M98+P98+O98+N98-R98 -> 0
A99: 46052 | B99: 3042/2674 | D99: 销售-内部 | E99: Norte Tools | H99: =F99*G99 -> 0 | J99: =ROUND(F99*G99+H99*I99,2) -> 0 | L99: =M99+P99+O99+N99-R99 -> 0 | R99: 0 | T99: 30/05/2026-MARTELUX | U99: =J99-H99 -> 0
A100: 46053 | B100: 本月合计 | F100: =SUBTOTAL(9,F4:F99) -> 288 | H100: =SUBTOTAL(9,H4:H99) -> 124842.14 | J100: =SUBTOTAL(9,J4:J99) -> 127306.04 | K100: =SUBTOTAL(9,K4:K99) -> 286 | L100: =SUBTOTAL(9,L4:L99) -> 126979.55 | M100: =SUBTOTAL(9,M4:M99) -> 0 | N100: =SUBTOTAL(9,N4:N99) -> 45575.78 | O100: =SUBTOTAL(9,O4:O99) -> 61278.73 | P100: =SUBTOTAL(9,P4:P99) -> 20451.53 | R100: =SUBTOTAL(9,R4:R99) -> 326.49 | T100: =J100-L100-R100 -> 5.1727511e-12
...

Sheet 销售帐NORTE TOOLS
A1: 2026年巴西销售发票总帐(NORTE TOOLS)
A2: 诺基土 | D2: =L2+R2-M2-N2-O2-P2 -> 0 | F2: =SUBTOTAL(9,F4:F1090) -> 323 | H2: =SUBTOTAL(9,H4:H1090) -> 36210 | J2: =SUBTOTAL(9,J4:J1090) -> 159377.94 | K2: =SUBTOTAL(9,K4:K1090) -> 323 | L2: =SUBTOTAL(9,L4:L1090) -> 39091.45 | M2: =SUBTOTAL(9,M4:M1090) -> 0 | N2: =SUBTOTAL(9,N4:N1090) -> 16528.88 | O2: =SUBTOTAL(9,O4:O1090) -> 16420 | P2: =SUBTOTAL(9,P4:P1090) -> 6271.13 | R2: =SUBTOTAL(9,R4:R1090) -> 128.56
A3: 发生日期 | B3: 销售单号 | C3: 编码 | D3: 商品型号 | E3: 客户单位 | F3: 数量/QUANTIDADE | G3: 单价 | H3: 金额 | I3: 税率 | J3: 含税金额 | K3: 数量 | L3: 总金额 | M3: 现金 | N3: 银行存款 | O3: BOLETO | P3: 刷卡/cartão | Q3: 退货 DEVOLUÇÃO | R3: 手续费/comissão | S3: 卡率 | T3: 备注/OBSERVAÇÕES
A4: 46028 | B4: 862/831 | D4: 销售 | E4: Eletro Astel | K4: 50 | L4: =M4+N4+O4+P4-Q4-R4 -> 2500 | O4: 2500 | T4: 28/01/2026-Norte Tools | BC4: 2100002016875 | BD4: NT23-12V
A5: 46029 | B5: 862/831 | C5: 2100002016875 | D5: =VLOOKUP(C5,$BC:$BD,2,0) -> NT23-12V | E5: ELETRO ASTEL LTDA-ME | F5: 50 | G5: 50 | H5: =F5*G5 -> 2500 | J5: =ROUND(F5*G5+H5*I5,2) -> 2500 | BC5: 2100002017902 | BD5: USK/DW26
A6: 46028 | B6: 863/832 | D6: 销售 | E6: FERRAGISTA UMA | H6: =F6*G6 -> 0 | J6: =ROUND(F6*G6+H6*I6,2) -> 0 | K6: 20 | L6: =M6+N6+O6+P6-Q6-R6 -> 1160 | O6: 1160 | T6: 08/02/2026 e 08/03/2026-Norte Tools | BC6: 2100002017865 | BD6: USK/11E
A7: 46028 | B7: 863/832 | C7: 2100002016875 | D7: =VLOOKUP(C7,$BC:$BD,2,0) -> NT23-12V | E7: FERRAGISTA UNA LTDA | F7: 20 | G7: 58 | H7: =F7*G7 -> 1160 | J7: =ROUND(F7*G7+H7*I7,2) -> 1160 | BC7: 2100002017872 | BD7: USK 11DE
A8: 46028 | B8: 864/833 | D8: 销售 | E8: Silva Ferragens | H8: =F8*G8 -> 0 | J8: =ROUND(F8*G8+H8*I8,2) -> 0 | K8: 10 | L8: =M8+N8+O8+P8-Q8-R8 -> 580 | O8: 580 | T8: 08/02/2026-Norte Tools | BC8: 2100002017858 | BD8: USK/Z1G-1316
A9: 46030 | B9: 864/833 | C9: 2100002016875 | D9: =VLOOKUP(C9,$BC:$BD,2,0) -> NT23-12V | E9: SILVA FERRAGENS LTDA | F9: 10 | G9: 58 | H9: =F9*G9 -> 580 | J9: =ROUND(F9*G9+H9*I9,2) -> 580
A10: 46030 | B10: 866/834 | D10: 销售 | E10: Garavelo Parafusos | H10: =F10*G10 -> 0 | J10: =ROUND(F10*G10+H10*I10,2) -> 0 | K10: 50 | L10: =M10+N10+O10+P10-Q10-R10 -> 2900 | O10: 2900 | R10: 0 | T10: 14/02/2026,16/03/2026 e 14/04/2026
A11: 46035 | B11: 866/834 | C11: 2100002016875 | D11: =VLOOKUP(C11,$BC:$BD,2,0) -> NT23-12V | E11: GARAVELO PARAFUSOS LTDA | F11: 50 | G11: 58 | H11: =F11*G11 -> 2900 | J11: =ROUND(F11*G11+H11*I11,2) -> 2900
A12: 46030 | B12: 835/835 | D12: 销售 | E12: Central Dos Parafusos | H12: =F12*G12 -> 0 | J12: =ROUND(F12*G12+H12*I12,2) -> 0 | K12: 30 | L12: =M12+N12+O12+P12-Q12-R12 -> 1740 | O12: 1740 | R12: 0 | T12: 21/02/2026, 21/03/2026 e 21/04/2026
A13: 46043 | B13: 835/835 | C13: 2100002016875 | D13: =VLOOKUP(C13,$BC:$BD,2,0) -> NT23-12V | E13: CENTRAL DOS PARAFUSOS DE ITUMBIARA LTDA | F13: 30 | G13: 58 | H13: =F13*G13 -> 1740 | J13: =ROUND(F13*G13+H13*I13,2) -> 1740
A14: 46042 | B14: 868/836 | D14: 销售 | E14: SB VARIEDADES | H14: =F14*G14 -> 0 | J14: =ROUND(F14*G14+H14*I14,2) -> 0 | K14: 22 | L14: =M14+N14+O14+P14-Q14-R14 -> 21142.57 | N14: 15000 | P14: 6271.13 | R14: =ROUND(P14*S14,2) -> 128.56 | S14: 0.0205 | T14: 23/01/2026-NORTE TOOLS
A15: 46045 | B15: 868/836 | C15: 2100002017902 | D15: =VLOOKUP(C15,$BC:$BD,2,0) -> USK/DW26 | E15: SB VARIEDADES | F15: 10 | G15: 330 | H15: =F15*G15 -> 3300 | I15: 0.052 | J15: =ROUND(F15*G15+H15*I15,2)+1914.33 -> 5385.93
A16: 46045 | B16: 868/836 | C16: 2100002017865 | D16: =VLOOKUP(C16,$BC:$BD,2,0) -> USK/11E | E16: SB VARIEDADES | F16: 5 | G16: 860 | H16: =F16*G16 -> 4300 | I16: 0.052 | J16: =ROUND(F16*G16+H16*I16,2) -> 4523.6
A17: 46045 | B17: 868/836 | C17: 2100002017872 | D17: =VLOOKUP(C17,$BC:$BD,2,0) -> USK 11DE | E17: SB VARIEDADES | F17: 5 | G17: 1360 | H17: =F17*G17 -> 6800 | I17: 0.052 | J17: =ROUND(F17*G17+H17*I17,2) -> 7153.6
A18: 46045 | B18: 868/836 | C18: 2100002017858 | D18: =VLOOKUP(C18,$BC:$BD,2,0) -> USK/Z1G-1316 | E18: SB VARIEDADES | F18: 2 | G18: 2000 | H18: =F18*G18 -> 4000 | I18: 0.052 | J18: =ROUND(F18*G18+H18*I18,2) -> 4208
A19: 46049 | B19: /837 | D19: 运输 发票 | E19: REMESSA | H19: =F19*G19 -> 0 | J19: =ROUND(F19*G19+H19*I19,2) -> 0 | L19: =M19+N19+O19+P19-Q19-R19 -> 0 | R19: 0
A20: 46049 | B20: /838 | D20: 运输 发票 | E20: REMESSA | H20: =F20*G20 -> 0 | J20: =ROUND(F20*G20+H20*I20,2) -> 0 | L20: =M20+N20+O20+P20-Q20-R20 -> 0 | R20: 0
A21: 46049 | B21: /839 | D21: 运输 发票 | E21: REMESSA | H21: =F21*G21 -> 0 | J21: =ROUND(F21*G21+H21*I21,2) -> 0 | L21: =M21+N21+O21+P21-Q21-R21 -> 0 | R21: 0
A22: 46049 | B22: /840 | D22: 运输 发票 | E22: REMESSA | H22: =F22*G22 -> 0 | J22: =ROUND(F22*G22+H22*I22,2) -> 0 | L22: =M22+N22+O22+P22-Q22-R22 -> 0 | R22: 0
A23: 46050 | B23: /841 | D23: 运输 发票 | E23: REMESSA | H23: =F23*G23 -> 0 | J23: =ROUND(F23*G23+H23*I23,2) -> 0 | L23: =M23+N23+O23+P23-Q23-R23 -> 0 | R23: 0
A24: 46050 | B24: /842 | D24: 运输 发票 | E24: REMESSA | H24: =F24*G24 -> 0 | J24: =ROUND(F24*G24+H24*I24,2) -> 0 | L24: =M24+N24+O24+P24-Q24-R24 -> 0 | R24: 0
A25: 46050 | B25: /843 | D25: 运输 发票 | E25: REMESSA | H25: =F25*G25 -> 0 | J25: =ROUND(F25*G25+H25*I25,2) -> 0 | L25: =M25+N25+O25+P25-Q25-R25 -> 0 | R25: 0
A26: 46049 | B26: 870/844 | D26: 销售 | E26: THIAGO MENDES | H26: =F26*G26 -> 0 | J26: =ROUND(F26*G26+H26*I26,2) -> 0 | K26: 100 | L26: =M26+N26+O26+P26-Q26-R26 -> 5800 | O26: 5800 | R26: 0 | T26: 05/03/2026,05/04/2026 e 05/05/2026-NORTE TOOLS
A27: 46051 | B27: 870/844 | C27: 2100002016875 | D27: =VLOOKUP(C27,$BC:$BD,2,0) -> NT23-12V | E27: THIAGO MENDES SILVA | F27: 100 | G27: 58 | H27: =F27*G27 -> 5800 | J27: =ROUND(F27*G27+H27*I27,2) -> 5800
A28: 46049 | B28: 871/845 | D28: 销售 | E28: LOJAS ENE | H28: =F28*G28 -> 0 | J28: =ROUND(F28*G28+H28*I28,2) -> 0 | K28: 30 | L28: =M28+N28+O28+P28-Q28-R28 -> 1740 | O28: 1740 | R28: 0 | T28: 30/03/2026,30/04/2026 e 30/05/2026-NORTE TOOLS
A29: 46052 | B29: 871/845 | C29: 2100002016875 | D29: =VLOOKUP(C29,$BC:$BD,2,0) -> NT23-12V | E29: LOJAS ENE ESSE LTDA | F29: 30 | G29: 58 | H29: =F29*G29 -> 1740 | J29: =ROUND(F29*G29+H29*I29,2) -> 1740
A30: 46052 | B30: 875/846 | D30: 销售 | E30: Fabio Souza | H30: =F30*G30 -> 0 | J30: =ROUND(F30*G30+H30*I30,2) -> 0 | K30: 1 | L30: =M30+N30+O30+P30-Q30-R30 -> 1028.88 | N30: 1028.88 | R30: 0 | T30: 30/01/2026-NORTE TOOLS
A31: 46052 | B31: 875/846 | C31: 2100002017865 | D31: =VLOOKUP(C31,$BC:$BD,2,0) -> USK/11E | E31: FABIO SOUZA DE JESUS | F31: 1 | G31: 890 | H31: =F31*G31 -> 890 | I31: 0.052 | J31: =ROUND(F31*G31+H31*I31,2)+92.6 -> 1028.88 | L31: =M31+N31+O31+P31-Q31-R31 -> 0
A32: 46053 | B32: 本月合计 | F32: =SUBTOTAL(9,F4:F31) -> 313 | H32: =SUBTOTAL(9,H4:H31) -> 35710 | J32: =SUBTOTAL(9,J4:J31) -> 38720.01 | K32: =SUBTOTAL(9,K4:K31) -> 313 | L32: =SUBTOTAL(9,L4:L31) -> 38591.45 | M32: =SUBTOTAL(9,M4:M31) -> 0 | N32: =SUBTOTAL(9,N4:N31) -> 16028.88 | O32: =SUBTOTAL(9,O4:O31) -> 16420 | P32: =SUBTOTAL(9,P4:P31) -> 6271.13 | R32: =SUBTOTAL(9,R4:R31) -> 128.56 | S32: =L32+R32-J32 -> 0 | T32: =J32-L32-R32 -> -2.3305802e-12
A33: 46077 | B33: /847 | D33: 进口发票 | E33: IMPORTACAO | L33: 0
A34: 46077 | B34: 876/848 | D34: 销售 | E34: DL Ferramentas | K34: 10 | L34: 500 | N34: 500 | T34: 24/02/2026-NORTE TOOLS
A35: 46077 | B35: 876/848 | C35: 2100002016875 | D35: =VLOOKUP(C35,$BC:$BD,2,0) -> NT23-12V | E35: DL FERRAMENTAS E UTILIDADES DOMESTICAS LTDA | F35: 10 | G35: 50 | H35: =F35*G35 -> 500 | J35: =ROUND(F35*G35+H35*I35,2) -> 500
A36: 46079 | B36: /849 | D36: 进口发票 | E36: IMPORTACAO | L36: 0 | R36: 0
A37: 46081 | B37: 本月合计 | F37: =SUBTOTAL(9,F33:F36) -> 10 | H37: =SUBTOTAL(9,H33:H36) -> 500 | J37: =SUBTOTAL(9,J33:J36) -> 500 | K37: =SUBTOTAL(9,K33:K36) -> 10 | L37: =SUBTOTAL(9,L33:L36) -> 500 | M37: =SUBTOTAL(9,M33:M36) -> 0 | N37: =SUBTOTAL(9,N33:N36) -> 500 | O37: =SUBTOTAL(9,O33:O36) -> 0 | P37: =SUBTOTAL(9,P33:P36) -> 0 | R37: =SUBTOTAL(9,R33:R36) -> 0 | S37: =L37+R37-J37 -> 0 | T37: =J37-L37-R37 -> 0
A70: 46112 | B70: 本月合计 | F70: =SUBTOTAL(9,F38:F69) -> 0 | H70: =SUBTOTAL(9,H38:H69) -> 0 | J70: =SUBTOTAL(9,J38:J69) -> 0 | K70: =SUBTOTAL(9,K38:K69) -> 0 | L70: =SUBTOTAL(9,L38:L69) -> 0 | M70: =SUBTOTAL(9,M38:M69) -> 0 | N70: =SUBTOTAL(9,N38:N69) -> 0 | O70: =SUBTOTAL(9,O38:O69) -> 0 | P70: =SUBTOTAL(9,P38:P69) -> 0 | R70: =SUBTOTAL(9,R38:R69) -> 0 | S70: =L70+R70-J70 -> 0
A89: 46142 | B89: 本月合计 | F89: =SUBTOTAL(9,F71:F88) -> 0 | H89: =SUBTOTAL(9,H71:H88) -> 0 | I89: =SUBTOTAL(9,I71:I88) -> 0 | J89: =SUBTOTAL(9,J71:J88) -> 0 | K89: =SUBTOTAL(9,K71:K88) -> 0 | L89: =SUBTOTAL(9,L71:L88) -> 0 | M89: =SUBTOTAL(9,M71:M88) -> 0 | N89: =SUBTOTAL(9,N71:N88) -> 0 | O89: =SUBTOTAL(9,O71:O88) -> 0 | P89: =SUBTOTAL(9,P71:P88) -> 0 | R89: =SUBTOTAL(9,R71:R88) -> 0 | S89: =L89+R89-J89 -> 0
A102: 46173 | B102: 本月合计 | F102: =SUBTOTAL(9,F90:F101) -> 0 | H102: =SUBTOTAL(9,H90:H101) -> 0 | I102: =SUBTOTAL(9,I90:I101) -> 0 | J102: =SUBTOTAL(9,J90:J101) -> 0 | K102: =SUBTOTAL(9,K90:K101) -> 0 | L102: =SUBTOTAL(9,L90:L101) -> 0 | M102: =SUBTOTAL(9,M90:M101) -> 0 | N102: =SUBTOTAL(9,N90:N101) -> 0 | O102: =SUBTOTAL(9,O90:O101) -> 0 | P102: =SUBTOTAL(9,P90:P101) -> 0 | R102: =SUBTOTAL(9,R90:R101) -> 0 | S102: =L102+R102-J102 -> 0
A135: 46203 | B135: 本月合计 | F135: =SUBTOTAL(9,F103:F134) -> 0 | G135: =SUBTOTAL(9,G103:G134) -> 0 | H135: =SUBTOTAL(9,H103:H134) -> 0 | I135: =SUBTOTAL(9,I103:I134) -> 0 | J135: =SUBTOTAL(9,J103:J134) -> 0 | K135: =SUBTOTAL(9,K103:K134) -> 0 | L135: =SUBTOTAL(9,L103:L134) -> 0 | M135: =SUBTOTAL(9,M103:M134) -> 0 | ... R135: =SUBTOTAL(9,R103:R134) -> 0 | S135: =L135+R135-J135 -> 0
A178: 46234 | B178: 本月合计 | F178: =SUBTOTAL(9,F136:F177) -> 0 | G178: =SUBTOTAL(9,G136:G177) -> 0 | H178: =SUBTOTAL(9,H136:H177) -> 0 | J178: =SUBTOTAL(9,J136:J177) -> 0 | K178: =SUBTOTAL(9,K136:K177) -> 0 | L178: =SUBTOTAL(9,L136:L177) -> 0 | M178: =SUBTOTAL(9,M136:M177) -> 0 | N178: =SUBTOTAL(9,N136:N177) -> 0 | O178: =SUBTOTAL(9,O136:O177) -> 0 | P178: =SUBTOTAL(9,P136:P177) -> 0 | R178: =SUBTOTAL(9,R136:R177) -> 0 | S178: =L178+R178-J178 -> 0
A235: 46265 | B235: 本月合计 | F235: =SUBTOTAL(9,F179:F234) -> 0 | G235: =SUBTOTAL(9,G179:G234) -> 0 | H235: =SUBTOTAL(9,H179:H234) -> 0 | I235: =SUBTOTAL(9,I179:I234) -> 0 | J235: =SUBTOTAL(9,J179:J234) -> 0 | K235: =SUBTOTAL(9,K179:K234) -> 0 | L235: =SUBTOTAL(9,L179:L234) -> 0 | M235: =SUBTOTAL(9,M179:M234) -> 0 | ... R235: =SUBTOTAL(9,R179:R234) -> 0 | S235: =L235+R235-J235 -> 0
A257: 46295 | B257: 本月合计 | F257: =SUBTOTAL(9,F236:F256) -> 0 | G257: =SUBTOTAL(9,G236:G256) -> 0 | H257: =SUBTOTAL(9,H236:H256) -> 0 | I257: =SUBTOTAL(9,I236:I256) -> 0 | J257: =SUBTOTAL(9,J236:J256) -> 0 | K257: =SUBTOTAL(9,K236:K256) -> 0 | L257: =SUBTOTAL(9,L236:L256) -> 0 | M257: =SUBTOTAL(9,M236:M256) -> 0 | ... P257: =SUBTOTAL(9,P236:P256) -> 0 | R257: =SUBTOTAL(9,R236:R256) -> 0 | S257: =L257+R257-J257 -> 0
A273: 46326 | B273: 本月合计 | F273: =SUBTOTAL(9,F258:F272) -> 0 | G273: =SUBTOTAL(9,G258:G272) -> 0 | H273: =SUBTOTAL(9,H258:H272) -> 0 | J273: =SUBTOTAL(9,J258:J272) -> 0 | K273: =SUBTOTAL(9,K258:K272) -> 0 | L273: =SUBTOTAL(9,L258:L272) -> 0 | M273: =SUBTOTAL(9,M258:M272) -> 0 | N273: =SUBTOTAL(9,N258:N272) -> 0 | O273: =SUBTOTAL(9,O258:O272) -> 0 | P273: =SUBTOTAL(9,P258:P272) -> 0 | R273: =SUBTOTAL(9,R258:R272) -> 0 | S273: =L273+R273-J273 -> 0
A289: 46356 | B289: 本月合计 | F289: =SUBTOTAL(9,F274:F288) -> 0 | H289: =SUBTOTAL(9,H274:H288) -> 0 | J289: =SUBTOTAL(9,J274:J288) -> 0 | K289: =SUBTOTAL(9,K274:K288) -> 0 | L289: =SUBTOTAL(9,L274:L288) -> 0 | M289: =SUBTOTAL(9,M274:M288) -> 0 | N289: =SUBTOTAL(9,N274:N288) -> 0 | O289: =SUBTOTAL(9,O274:O288) -> 0 | P289: =SUBTOTAL(9,P274:P288) -> 0 | R289: =SUBTOTAL(9,R274:R288) -> 0 | S289: =L289+R289-J289 -> 0
A296: 46387 | B296: 本月合计 | F296: =SUBTOTAL(9,F290:F295) -> 0 | H296: =SUBTOTAL(9,H290:H295) -> 0 | I296: =SUBTOTAL(9,I290:I295) -> 0 | J296: =SUBTOTAL(9,J290:J295) -> 0 | K296: =SUBTOTAL(9,K290:K295) -> 0 | L296: =SUBTOTAL(9,L290:L295) -> 0 | M296: =SUBTOTAL(9,M290:M295) -> 0 | N296: =SUBTOTAL(9,N290:N295) -> 0 | O296: =SUBTOTAL(9,O290:O295) -> 0 | P296: =SUBTOTAL(9,P290:P295) -> 0 | R296: =SUBTOTAL(9,R290:R295) -> 0 | S296: =L296+R296-J296 -> 0
J302: 105445.28
J303: 14712.65

Sheet 销售帐 - ZHEMAX
A1: 2026年巴西销售发票总帐(ZHEMAX)
A2: 财玛克思 | D2: =L2+Q2-N2-M2-O2-P2 -> 0 | F2: =SUBTOTAL(9,F4:F816) -> 0 | H2: =SUBTOTAL(9,H4:H816) -> 0 | J2: =SUBTOTAL(9,J4:J816) -> 0 | K2: =SUBTOTAL(9,K4:K816) -> 0 | L2: =SUBTOTAL(9,L4:L816) -> 0 | M2: =SUBTOTAL(9,M4:M816) -> 0 | N2: =SUBTOTAL(9,N4:N816) -> 0 | O2: =SUBTOTAL(9,O4:O816) -> 0 | P2: =SUBTOTAL(9,P4:P816) -> 0 | Q2: =SUBTOTAL(9,Q4:Q816) -> 0 | R2: =L2+Q2-J2 -> 0 | X2: 收款1期信息 | Z2: 收款2期信息 | AB2: 收款3期信息 | AD2: 收款4期信息 | AF2: 收款5期信息 | AH2: 收款6期信息 | AJ2: 收款7期信息 | AL2: 收款8期信息 | AN2: 合计金额 | AO2: 差异
A3: 发生日期 | B3: 销售单号 | C3: 编码 | D3: 商品型号 | E3: 客户单位 | F3: 数量 | G3: 单价 | H3: 金额 | I3: 税率 | J3: 含税金额 | K3: 数量 | L3: 总金额 | M3: 现金 | N3: 银行存款 | O3: BOLETO | P3: 刷卡/COM | Q3: 卡费/Taxa de cartão de | R3: 备注/OBSERVAÇÕES | T3: 1.99%卡 | U3: 3.49%卡 | V3: 1.99%卡 | W3: 3.49%卡 | X3: 日期 | Y3: 金额 | Z3: 日期 | AA3: 金额 | AB3: 日期 | AC3: 金额 | AD3: 日期 | AE3: 金额 | AF3: 日期 | AG3: 金额 | AH3: 日期 | AI3: 金额 | AJ3: 日期 | AK3: 金额 | AL3: 日期 | AM3: 金额
A5: 46053 | B5: 本月合计 | F5: =SUBTOTAL(9,F4:F4) -> 0 | H5: =SUBTOTAL(9,H4:H4) -> 0 | J5: =SUBTOTAL(9,J4:J4) -> 0 | K5: =SUBTOTAL(9,K4:K4) -> 0 | L5: =SUBTOTAL(9,L4:L4) -> 0 | M5: =SUBTOTAL(9,M4:M4) -> 0 | N5: =SUBTOTAL(9,N4:N4) -> 0 | O5: =SUBTOTAL(9,O4:O4) -> 0 | P5: =SUBTOTAL(9,P4:P4) -> 0 | Q5: =SUBTOTAL(9,Q4:Q4) -> 0 | R5: =L5+Q5-J5 -> 0
A8: 46081 | B8: 本月合计 | F8: =SUBTOTAL(9,F6:F7) -> 0 | H8: =SUBTOTAL(9,H6:H7) -> 0 | I8: =SUBTOTAL(9,I6:I7) -> 0 | J8: =SUBTOTAL(9,J6:J7) -> 0 | K8: =SUBTOTAL(9,K6:K7) -> 0 | L8: =SUBTOTAL(9,L6:L7) -> 0 | M8: =SUBTOTAL(9,M6:M7) -> 0 | N8: =SUBTOTAL(9,N6:N7) -> 0 | O8: =SUBTOTAL(9,O6:O7) -> 0 | ... Q8: =SUBTOTAL(9,Q6:Q7) -> 0 | R8: =L8+Q8-J8 -> 0
A15: 46112 | B15: 本月合计 | F15: =SUBTOTAL(9,F9:F14) -> 0 | H15: =SUBTOTAL(9,H9:H14) -> 0 | I15: =SUBTOTAL(9,I9:I14) -> 0 | J15: =SUBTOTAL(9,J9:J14) -> 0 | K15: =SUBTOTAL(9,K9:K14) -> 0 | L15: =SUBTOTAL(9,L9:L14) -> 0 | M15: =SUBTOTAL(9,M9:M14) -> 0 | N15: =SUBTOTAL(9,N9:N14) -> 0 | O15: =SUBTOTAL(9,O9:O14) -> 0 | ... Q15: =SUBTOTAL(9,Q9:Q14) -> 0 | R15: =L15+Q15-J15 -> 0
A26: 46142 | B26: 本月合计 | F26: =SUBTOTAL(9,F16:F25) -> 0 | H26: =SUBTOTAL(9,H16:H25) -> 0 | J26: =SUBTOTAL(9,J16:J25) -> 0 | K26: =SUBTOTAL(9,K16:K25) -> 0 | L26: =SUBTOTAL(9,L16:L25) -> 0 | M26: =SUBTOTAL(9,M16:M25) -> 0 | N26: =SUBTOTAL(9,N16:N25) -> 0 | O26: =SUBTOTAL(9,O16:O25) -> 0 | P26: =SUBTOTAL(9,P16:P25) -> 0 | Q26: =SUBTOTAL(9,Q16:Q25) -> 0 | R26: =L26+Q26-J26 -> 0
A79: 46173 | B79: 本月合计 | F79: =SUBTOTAL(9,F27:F78) -> 0 | H79: =SUBTOTAL(9,H27:H78) -> 0 | J79: =SUBTOTAL(9,J27:J78) -> 0 | K79: =SUBTOTAL(9,K27:K78) -> 0 | L79: =SUBTOTAL(9,L27:L78) -> 0 | M79: =SUBTOTAL(9,M27:M78) -> 0 | N79: =SUBTOTAL(9,N27:N78) -> 0 | O79: =SUBTOTAL(9,O27:O78) -> 0 | P79: =SUBTOTAL(9,P27:P78) -> 0 | Q79: =SUBTOTAL(9,Q27:Q78) -> 0 | R79: =L79+Q79-J79 -> 0
A128: 46203 | B128: 本月合计 | F128: =SUBTOTAL(9,F80:F127) -> 0 | H128: =SUBTOTAL(9,H80:H127) -> 0 | J128: =SUBTOTAL(9,J80:J127) -> 0 | K128: =SUBTOTAL(9,K80:K127) -> 0 | L128: =SUBTOTAL(9,L80:L127) -> 0 | M128: =SUBTOTAL(9,M80:M127) -> 0 | N128: =SUBTOTAL(9,N80:N127) -> 0 | O128: =SUBTOTAL(9,O80:O127) -> 0 | P128: =SUBTOTAL(9,P80:P127) -> 0 | Q128: =SUBTOTAL(9,Q80:Q127) -> 0 | R128: =L128+Q128-J128 -> 0
A143: 46234 | B143: 本月合计 | F143: =SUBTOTAL(9,F129:F142) -> 0 | H143: =SUBTOTAL(9,H129:H142) -> 0 | J143: =SUBTOTAL(9,J129:J142) -> 0 | K143: =SUBTOTAL(9,K129:K142) -> 0 | L143: =SUBTOTAL(9,L129:L142) -> 0 | M143: =SUBTOTAL(9,M129:M142) -> 0 | N143: =SUBTOTAL(9,N129:N142) -> 0 | O143: =SUBTOTAL(9,O129:O142) -> 0 | P143: =SUBTOTAL(9,P129:P142) -> 0 | Q143: =SUBTOTAL(9,Q129:Q142) -> 0 | R143: =L143+Q143-J143 -> 0
A166: 46265 | B166: 本月合计 | F166: =SUBTOTAL(9,F144:F165) -> 0 | H166: =SUBTOTAL(9,H144:H165) -> 0 | I166: =SUBTOTAL(9,I144:I165) -> 0 | J166: =SUBTOTAL(9,J144:J165) -> 0 | K166: =SUBTOTAL(9,K144:K165) -> 0 | L166: =SUBTOTAL(9,L144:L165) -> 0 | M166: =SUBTOTAL(9,M144:M165) -> 0 | N166: =SUBTOTAL(9,N144:N165) -> 0 | O166: =SUBTOTAL(9,O144:O165) -> 0 | ... Q166: =SUBTOTAL(9,Q144:Q165) -> 0 | R166: =L166+Q166-J166 -> 0
A173: 46295 | B173: 本月合计 | F173: =SUBTOTAL(9,F167:F172) -> 0 | G173: =SUBTOTAL(9,G167:G172) -> 0 | H173: =SUBTOTAL(9,H167:H172) -> 0 | I173: =SUBTOTAL(9,I167:I172) -> 0 | J173: =SUBTOTAL(9,J167:J172) -> 0 | K173: =SUBTOTAL(9,K167:K172) -> 0 | L173: =SUBTOTAL(9,L167:L172) -> 0 | M173: =SUBTOTAL(9,M167:M172) -> 0 | ... Q173: =SUBTOTAL(9,Q167:Q172) -> 0 | R173: =L173+Q173-J173 -> 0
A176: 46326 | B176: 本月合计 | F176: =SUBTOTAL(9,F174:F175) -> 0 | G176: =SUBTOTAL(9,G174:G175) -> 0 | H176: =SUBTOTAL(9,H174:H175) -> 0 | J176: =SUBTOTAL(9,J174:J175) -> 0 | K176: =SUBTOTAL(9,K174:K175) -> 0 | L176: =SUBTOTAL(9,L174:L175) -> 0 | M176: =SUBTOTAL(9,M174:M175) -> 0 | N176: =SUBTOTAL(9,N174:N175) -> 0 | O176: =SUBTOTAL(9,O174:O175) -> 0 | P176: =SUBTOTAL(9,P174:P175) -> 0 | Q176: =SUBTOTAL(9,Q174:Q175) -> 0 | R176: =L176+Q176-J176 -> 0
A179: 46356 | B179: 本月合计 | F179: =SUBTOTAL(9,F177:F178) -> 0 | G179: =SUBTOTAL(9,G177:G178) -> 0 | H179: =SUBTOTAL(9,H177:H178) -> 0 | I179: =SUBTOTAL(9,I177:I178) -> 0 | J179: =SUBTOTAL(9,J177:J178) -> 0 | K179: =SUBTOTAL(9,K177:K178) -> 0 | L179: =SUBTOTAL(9,L177:L178) -> 0 | M179: =SUBTOTAL(9,M177:M178) -> 0 | ... Q179: =SUBTOTAL(9,Q177:Q178) -> 0 | R179: =L179+Q179-J179 -> 0
A198: 46387 | B198: 本月合计 | F198: =SUBTOTAL(9,F180:F197) -> 0 | H198: =SUBTOTAL(9,H180:H197) -> 0 | I198: =SUBTOTAL(9,I180:I197) -> 0 | J198: =SUBTOTAL(9,J180:J197) -> 0 | K198: =SUBTOTAL(9,K180:K197) -> 0 | L198: =SUBTOTAL(9,L180:L197) -> 0 | M198: =SUBTOTAL(9,M180:M197) -> 0 | N198: =SUBTOTAL(9,N180:N197) -> 0 | O198: =SUBTOTAL(9,O180:O197) -> 0 | ... Q198: =SUBTOTAL(9,Q180:Q197) -> 0 | R198: =L198+Q198-J198 -> 0

Sheet 坯料 BOLETOS
A1: 21年 | B1: 销售 | F1: 未收货款 | G1: 3007010.4 | H1: =SUBTOTAL(9,J1:X1) -> 0 | I1: =H1/G1 -> 0 | J1: 99678.96 | L1: 89565.03 | N1: 113087.99 | P1: 56421.15 | R1: 40771.29 | T1: 16968.46 | V1: 10674.63 | X1: 1944 | Y1: =J1+L1+N1+P1+R1+T1+V1+X1 -> 429111.51 | Z1: =Y1/G1 -> 0.1427037
A2: 22年 | B2: 销售 | F2: 未收货款 | G2: 5287707.5 | H2: =SUBTOTAL(9,J2:X2) -> 0 | I2: =H2/G2 -> 0 | J2: 48391.05 | L2: 38319.26 | N2: 29369.69 | P2: 13553.54 | R2: 858 | Y2: =J2+L2+N2+P2+R2+T2+V2+X2 -> 130491.54 | Z2: =Y2/G2 -> 0.024678283
A3: 23年 | B3: 销售 | F3: 未收货款 | G3: 3070370.4 | H3: =SUBTOTAL(9,J3:X3) -> 0 | I3: =H3/G3 -> 0 | J3: 26865.42 | L3: 35813.9 | N3: 55757 | P3: 2317.16 | R3: 2317.15 | Y3: =J3+L3+N3+P3+R3+T3+V3+X3 -> 123070.63 | Z3: =Y3/G3 -> 0.040083317
A4: 24年 | B4: 销售 | F4: 未收货款 | G4: 2900054.7 | H4: =SUBTOTAL(9,J4:X4) -> 0 | I4: =H4/G4 -> 0 | J4: 35941.8 | L4: 23292.14 | N4: 16688.2 | P4: 3072.82 | R4: 3072.82
F5: 2月份收款 | H5: =SUBTOTAL(9,J5:X5) -> 560744.76 | J5: =J7-J6 -> 485795.2 | L5: =L7-L6 -> 38964.75 | N5: =N7-N6 -> 34614.12 | P5: =P7-P6 -> 435 | R5: =R7-R6 -> 935.69 | T5: =T7-T6 -> 0 | V5: =V7-V6 -> 0 | X5: =X7-X6 -> 0 | Y5: =J5+L5+N5+P5+R5+T5+V5+X5 -> 560744.76
E6: =280896.8-234001.09 -> 46895.71 | F6: 2月末未收 | H6: =SUBTOTAL(9,J6:X6) -> 1866815.1 | J6: 968051.18 | L6: 382361.26 | N6: 347869.52 | P6: 88149.31 | R6: 50796.69 | T6: 16968.46 | V6: 10674.63 | X6: 1944 | Y6: =J6+L6+N6+P6+R6+T6+V6+X6 -> 1866815.1 | AB6: =F8-Y6 -> -1866815.1
F7: 2月初未收 | H7: =SUBTOTAL(9,J7:X7) -> 2427559.8 | J7: =898436.61+555409.77 -> 1453846.4 | L7: =350000.43+71325.58 -> 421326.01 | N7: =349767.03+32716.61 -> 382483.64 | P7: =86115.61+2468.7 -> 88584.31 | R7: 51732.38 | T7: 16968.46 | V7: 10674.63 | X7: 1944 | Y7: =J7+L7+N7+P7+R7+T7+V7+X7 -> 2427559.8 | Z7: =Y7-Y6 -> 560744.76
A8: 总计 | G8: =SUBTOTAL(9,G10:G1007) -> 6645901.1 | J8: =SUBTOTAL(9,J10:J1007) -> 3614351.5 | L8: =SUBTOTAL(9,L10:L1007) -> 1392769 | N8: =SUBTOTAL(9,N10:N1007) -> 1199560.5 | P8: =SUBTOTAL(9,P10:P1007) -> 117999.07 | R8: =SUBTOTAL(9,R10:R1007) -> 69954.67 | T8: =SUBTOTAL(9,T10:T1007) -> 18835.8 | V8: =SUBTOTAL(9,V10:V1007) -> 10674.63 | X8: =SUBTOTAL(9,X10:X1007) -> 1944 | Y8: =SUBTOTAL(9,Y10:Y1007) -> 5922336.2 | Z8: =SUBTOTAL(9,Z10:Z1007) -> 31327.82 | AA8: =SUBTOTAL(9,AA10:AA155) -> 0
A9: 年月 | B9: 日期- DATA | C9: 订单号 - PEDIDO E NF | D9: 公司介绍 /EMPRESA | E9: 推销员/VENDEDOR | F9: 客户资料/ CLIENTE | G9: 金额 | H9: 天数 | I9: 第一期 | J9: 金额 | K9: 第二期 | L9: 金额 | M9: 第三期 | N9: 金额 | O9: 第四期 | P9: 金额 | Q9: 第五期 | R9: 金额 | S9: 第六期 | T9: 金额 | U9: 第七期 | V9: 金额 | W9: 第八期 | X9: 金额 | Y9: 合计 | Z9: 差异 | AB9: 备注
A10: 44105 | B10: 44112 | C10: 42501/489 | D10: COMPBRASIL | E10: KFS CARDOSO | F10: FORTSMAQ COMER DE FERRAMENTAS EIRELI | G10: 69845 | H10: 20/45/60/80/100/120/140/160 | M10: 44179 | N10: 8730.63 | O10: 44199 | P10: 8730.63 | Q10: 44220 | R10: 8730.63 | S10: 44241 | T10: 8730.63 | U10: 44260 | V10: 8730.63
A11: 44105 | B11: 44112 | C11: 1218/1212 | D11: ZHEMAX | E11: KFS CARDOSO | F11: FORTSMAQ COMER DE FERRAMENTAS EIRELI | G11: 15552 | H11: 20/40/60/80/100/120/140/160 | U11: 44260 | V11: 1944 | W11: 44280 | X11: 1944
A12: 44197 | B12: 44210 | C12: 151/139 | D12: COMPBRASIL | E12: D.A NOGUEIRA | F12: PIZZIMAR FERRAGENS E FERRAMENTAS | G12: 4680 | H12: 30/45/60/75/90 | I12: 44241 | K12: 44256 | L12: 936 | M12: 44269 | O12: 44287 | Q12: 44300
A13: 44197 | B13: 44224 | C13: 178/175 | D13: COMPBRASIL | E13: KFS CARDOSO | F13: FORTSMAQ COMERCIO DE FERRAMENTAS EIRELE | G13: 49427 | H13: 20/40/60/80/100/120 | I13: 44245 | J13: 8237.83 | K13: 44265 | L13: 8237.83 | M13: 44285 | N13: 8237.83 | O13: 44312 | P13: 8237.83 | Q13: 44332 | R13: 8237.83 | S13: 44352 | T13: 8237.83
A14: 44197 | B14: 44197 | C14: 182/176 | D14: COMPBRASIL | E14: KFS CARDOSO | F14: FORTSMAQ COMERCIO DE FERRAMENTAS | G14: 49427 | H14: 20/40/60/80/100/120 | I14: 44247 | J14: 8237.83 | Q14: 44327 | R14: 8237.83
A15: 44228 | B15: 44249 | C15: 20001/200 | D15: COMPBRASIL | E15: KFS CARDOSO | F15: VL FERRAMENTAS EIRELI-ME | G15: 5850 | H15: 30/60/90 | I15: 44279 | J15: 1950 | K15: 44310 | L15: 1950 | M15: 44340 | N15: 1950
A16: 44228 | B16: 44232 | C16: 2430/2013 | D16: MOBITECH | E16: EMPRESA | F16: DEYUN | G16: 11995.79 | H16: 30/60 | I16: 44260 | J16: 5997.9 | K16: 44291
A17: 44228 | B17: 44250 | C17: 2603/1987 | D17: DEYUN | E17: FELIPE GOMES | F17: K B DA SILVA | G17: 5800 | H17: 30/60/90/120 | I17: 44278 | K17: 44309 | M17: 44339 | O17: 44370 | P17: 1450
A18: 44256 | B18: 44267 | C18: 2621/2023 | D18: DEYUN | E18: KFS CARDOSO | F18: FORTSMAQ COMERCIO DE FERRAMENTAS EIRELE-ME | G18: 16425 | H18: 20/40/60/80/100 | I18: 44288 | K18: 44308 | M18: 44328 | O18: 44349 | Q18: 44369 | R18: 3285
A19: 44287 | B19: 44300 | C19: 968/941 | D19: ZHEMAX | E19: ADEMIR MOLINA | F19: A DE LIMA SANTANA EIRELE | G19: 2592 | H19: 30/60/90 | I19: 44336 | J19: 864 | K19: 44367 | L19: 864 | M19: 44397 | N19: 864
A20: 44287 | B20: 44306 | C20: 2638/2057 | D20: DEYUN | E20: DOCTORCIA | F20: TUMORO COMERCIO E LOCAÇÃO LTDA-ME | G20: 1208 | H20: 30/60/90 | I20: 44339 | K20: 44370 | L20: 402.67 | M20: 44379
A21: 44287 | B21: 44313 | C21: 2675/2195 | D21: CAIYA | E21: ADEMIR MOLINA | F21: A DE LIMA SANTANA EIRELE | G21: 1744 | H21: 30/60/90 | I21: 44345 | J21: 581.33 | K21: 44373 | L21: 581.33 | M21: 44406 | N21: 581.34
A22: 44287 | B22: 44291 | C22: 24101/263 | D22: COMPBRASIL | E22: ADEMIR MOLINA | F22: VALTEC VALVULAS TECNICAS INDUSTRIAIS LTDA | G22: 9739 | H22: 30/60/90/120 | I22: 44322 | K22: 44353 | M22: 44383 | N22: 2434.75 | O22: 44414
A23: 44287 | B23: 44313 | C23: 2671/2192 | D23: CAIYA | E23: EVIDENCE | F23: ESPAÇO SOLDA COMERCIO E SERVIÇOS EIRELI | G23: 833.75 | H23: 30/60/90 | I23: 44345 | K23: 44376 | M23: 44406 | N23: 277.92
A24: 44317 | B24: 44321 | C24: 2683/2205 | D24: CAIYA | E24: ADEMIR MOLINA | F24: A DE LIMA SANTANA EIRELI | G24: 2180 | H24: 30/60/90 | I24: 44354 | J24: 726.67 | K24: 44384 | L24: 726.67 | M24: 44415 | N24: 726.67
A25: 44317 | B25: 44326 | C25: 993/973 | D25: ZHEMAX | E25: ADEMIR MOLINA | F25: A DE LIMA SANTANA EIRELI | G25: 4152 | H25: 30/60/90 | I25: 44360 | J25: 1384 | K25: 44390 | L25: 1384 | M25: 44421 | N25: 1384
A26: 44317 | B26: 44333 | C26: 1009/1004 | D26: ZHEMAX | E26: ADEMIR MOLINA | F26: ISAEL SANTIAGO DA SILVA | G26: 4152 | H26: 30/60/90 | I26: 44373 | J26: 1384 | K26: 44403 | L26: 1384 | M26: 44434 | N26: 1384
A27: 44317 | B27: 44335 | C27: 2693/2221 | D27: CAIYA | E27: ADEMIR MOLINA | F27: ISAEL SANTIAGO DA SILVA | G27: 2973 | H27: 30/60/90 | I27: 44374 | J27: 991.2 | K27: 44404 | L27: 991.2 | M27: 44435 | N27: 991.2
A28: 44317 | B28: 44336 | C28: 28201/321 | D28: COMPBRASIL | E28: DOCTORCIA | F28: SHOP DAS SOLDAS COMERCIO DE GASES INDUSTRIAIS E EQUIP | G28: 4140 | H28: 30/60/90 | I28: 44373 | K28: 44403 | M28: 44434 | N28: 1380
A29: 44317 | B29: 44342 | C29: 2667/2100 | D29: DEYUN | E29: DOCTORCIA | F29: TEB SOLDAS E EQUIPAMENTOS INDUSTRIAIS LTDA-ME | G29: 1384 | H29: 30/60 | I29: 44371 | J29: 692 | K29: 44401
A30: 44348 | B30: 44351 | C30: 2678/2116 | D30: DEYUN | E30: KFS CARDOSO | F30: VIVIANE DA SILVA THEODORO | G30: 22600 | H30: 30/60/90 | I30: 44385 | J30: 7533.33 | K30: 44416 | L30: 7533.33 | M30: 44447 | N30: 7533.33
A31: 44348 | B31: 44358 | C31: 2689/2121 | D31: deyun | E31: ADEMIR MOLINA | F31: ISAEL SANTIAGO DA SILVA | G31: 7180 | H31: 30/60/90 | I31: 44391 | J31: 2393.33 | K31: 44422 | L31: 2393.33 | M31: 44453 | N31: 2393.34
A32: 44348 | B32: 44358 | C32: 2735/2259 | D32: CAIYA | E32: ADEMIR MOLINA | F32: ISAEL SANTIAGO DA SILVA | G32: 8327 | H32: 30/60/90 | I32: 44391 | J32: 2775.67 | K32: 44422 | L32: 2775.67 | M32: 44453 | N32: 2775.66
A33: 44348 | B33: 44377 | C33: 32801/374 | D33: COMPBRASIL | E33: ADEMIR MOLINA | F33: ISAEL SANTIAGO DA SILVA | G33: 9016.8 | H33: 30/60/90 | I33: 44413 | J33: 3005.6 | K33: 44444 | L33: 3005.6 | M33: 44474 | N33: 3005.6
A34: 44348 | B34: 44356 | C34: 2426/2255 | D34: CAIYA | E34: FRASAN | F34: M HELENA CORREA BATISTA EIRELI ME | G34: 1440 | H34: 30/45/60/75/90/105 | I34: 44386 | K34: 44401 | M34: 44417 | O34: 44432 | Q34: 44448 | R34: 240
A35: 44348 | B35: 44361 | C35: 30301/350 | D35: COMPBRASIL | E35: DOCTORCIA | F35: GIOVANI LINEKER BAZZO MORAO | G35: 6497.1 | H35: 30/60/90 | I35: 44391 | K35: 44422 | M35: 44453 | N35: 2165.7
A36: 44378 | B36: 44404 | C36: 1105/1098 | D36: ZHEMAX | E36: ADEMIR MOLINA | F36: JAIME AURELIANO DOS SANTOS | G36: 3321.6 | H36: 30/60/90 | I36: 44441 | J36: 1107.2 | K36: 44471 | L36: 1107.2 | M36: 44502 | N36: 1107.2
A37: 44378 | B37: 44404 | C37: 35501/409 | D37: COMPBRASIL | E37: ADEMIR MOLINA | F37: JAIME AURELIANO DOS SANTOS | G37: 4508.4 | H37: 30/60/90 | I37: 44441 | J37: 1502.8 | K37: 44471 | L37: 1502.8 | M37: 44502 | N37: 1502.8
A38: 44378 | B38: 44392 | C38: 1078/1070 | D38: ZHEMAX | E38: ADEMIR MOLINA | F38: KADU MATERIAIS PARA SODA E CORTE EIRELI | G38: 5680 | H38: 30/60/90/120 | I38: 44423 | K38: 44454 | M38: 44484 | O38: 44515 | P38: 1420
A39: 44409 | B39: 44431 | C39: 2748/2188 | D39: DEYUN | E39: EVIDENCE | F39: RAFAEL VICENTE BARBOSA ELETRONICOS - ME | G39: 7200 | H39: 30/60/90 | I39: 44464 | J39: 2400 | K39: 44494 | L39: 2400 | M39: 44525 | N39: 2400
A40: 44409 | B40: 44419 | C40: 1143/1131 | D40: ZHEMAX | E40: FELIPE GOMES | F40: ANA CAROLINA DE MELO INACIO | G40: 27680 | H40: 60/90/120/150/180 | I40: 44480 | K40: 44511 | M40: 44541 | N40: 5536 | O40: 44572 | P40: 5536 | Q40: 44603 | R40: 5536
A41: 44440 | B41: 44442 | C41: 1178/1169 | D41: ZHEMAX | E41: EVIDENCE | F41: CKD COMERIO IMPORTAÇÃO E EXPORTAÇÃO EIRELI | G41: 14017.06 | H41: 30/60/90 | I41: 44472 | K41: 44503 | L41: 4672.35 | M41: 44533
A42: 44440 | B42: 44454 | C42: 39901/459 | D42: COMPBRASIL | E42: FELIPE GOMES | F42: ALTHAN COMERCIO DE MOVEIS E FERRAGENS LTDA | G42: 2306 | H42: 14/28 | I42: 44472 | J42: 1153 | K42: 44486 | L42: 1153
A43: 44440 | B43: 44440 | C43: 38201/442 | D43: COMPBRASIL | E43: DOCTORCIA | F43: PALACIO DAS FERRAMENTAS E PARAFUSOS LTDA | G43: 22337.2 | H43: 45/60/75/90 | I43: 44484 | K43: 44501 | M43: 44515 | O43: 44531 | P43: 5584.3
A44: 44470 | B44: 44470 | C44: 41401/474 | D44: COMPBRASIL | E44: KFS CARDOSO | F44: NACIONAL COMERCIO E DISTRIBUICAO DE MAQUINAS E FERRA | G44: 12514 | H44: 30/60/90/120 | I44: 44504 | J44: 3128.5 | K44: 44534 | L44: 3128.5 | M44: 44565 | N44: 3128.5 | O44: 44596 | P44: 3128.5
A45: 44470 | B45: 44470 | C45: 1207/1198 | D45: ZHEMAX | E45: KFS CARDOSO | F45: NACIONAL COMERCIO E DISTRIBUICAO DE MAQUINAS E FERRA | G45: 17907.6 | H45: 30/60/60/120 | I45: 44504 | J45: 4476.9 | K45: 44534 | L45: 4476.9 | M45: 44565 | N45: 4476.9 | O45: 44596 | P45: 4476.9
A46: 44470 | B46: 44476 | C46: 008/013 | D46: NORTE TOOLS | E46: KFS CARDOSO | F46: NACIONAL COMERCIO E DISTRIBUICAO DE MAQUINAS E FERRA | G46: 15778.9 | H46: 30/60/90/120 | I46: 44520 | J46: 3944.72 | K46: 44550 | L46: 3944.72 | M46: 44581 | N46: 3944.72 | O46: 44612 | P46: 3944.74
A47: 44470 | B47: 44474 | C47: 1209/1202 | D47: ZHEMAX | E47: DOCTORCIA | F47: HR SOLDAS E MAQUINAS EIRELI | G47: 1440 | H47: 30/60/90 | I47: 44507 | J47: 480 | K47: 44537 | L47: 480 | M47: 44568 | N47: 480
A48: 44470 | B48: 44474 | C48: 41801/479 | D48: COMPBRASIL | E48: DOCTORCIA | F48: HR SOLDAS E MAQUINAS EIRELI | G48: 2340 | H48: 30/60/90 | I48: 44507 | K48: 44537 | L48: 780 | M48: 44568 | N48: 780
A49: 44470 | B49: 44476 | C49: 41801/479 | D49: COMPBRASIL | E49: DOCTORCIA | F49: PALACIO DAS FERRAMENTAS E PARAFUSOS LTDA | G49: 27713.85 | H49: 45/60/75/90 | I49: 44523 | J49: 6928.46 | K49: 44538 | L49: 6928.46 | M49: 44553 | N49: 6928.46 | O49: 44569
A50: 44470 | B50: 44470 | C50: 2862/2382 | D50: CAIYA | E50: MARCOS ROBERTO | F50: ALTAMIRO CANDIDO | G50: 2904 | H50: 30/60/90 | I50: 44504 | K50: 44534 | M50: 44565 | N50: 968
A51: 44470 | B51: 44470 | C51: 1204/1199 | D51: ZHEMAX | E51: FELIPE GOMES | F51: ANA CAROLINA DE MELO INACIO | G51: 6507.75 | H51: 30/60/90 | I51: 44506 | K51: 44536 | M51: 44567 | N51: 2169.25
A52: 44470 | B52: 44477 | C52: 2867/2395 | D52: CAIYA | E52: D.A NOGUEIRA | F52: J C NEPOMUCENO FERRAMENTAS - ME | G52: 2520 | H52: 30/45/60/75/90 | I52: 44513 | K52: 44529 | M52: 44567 | O52: 44559 | Q52: 44574 | R52: 504
A53: 44470 | B53: 44490 | C53: 44201/504 | D53: COMPBRASIL | E53: FENIX REPRESE | F53: S I R SILVA CAMARGO FERRAGISTA LTDA | G53: 4500 | H53: 28/56/84/112 | I53: 44519 | K53: 44547 | M53: 44576 | N53: 1125 | O53: 44605 | P53: 1125
A54: 44501 | B54: 44504 | C54: 031/031 | D54: NORTE TOOLS | E54: ADEMIR MOLINA | F54: CRISTINA GUEDES DA SILVA | G54: 1302.84 | H54: 30/60/90 | I54: 44539 | J54: 434.28 | K54: 44570 | L54: 434.28 | M54: 44601 | N54: 434.28
A55: 44501 | B55: 44504 | C55: 45301/523 | D55: COMPBRASIL | E55: ADEMIR MOLINA | F55: CRISTINA GUEDES DA SILVA | G55: 4680 | H55: 30/60/90 | I55: 44539 | J55: 1560 | K55: 44570 | L55: 1560 | M55: 44601 | N55: 1560
A56: 44501 | B56: 44504 | C56: 1253/1248 | D56: ZHEMAX | E56: ADEMIR MOLINA | F56: CRISTINA GUEDES DA SILVA | G56: 5483.1 | H56: 30/60/90 | I56: 44539 | J56: 1827.7 | K56: 44570 | L56: 1827.7 | M56: 44601 | N56: 1827.7
A57: 44501 | B57: 44504 | C57: 2798/2239 | D57: DEYUN | E57: ADEMIR MOLINA | F57: CRISTINA GUEDES DA SILVA | G57: 10294.24 | H57: 30/60/90 | I57: 44539 | J57: 3431.41 | K57: 44570 | L57: 3431.41 | M57: 44601 | N57: 3431.42
A58: 44501 | B58: 44504 | C58: 45401/520 | D58: COMPBRASIL | E58: KFS CARDOSO | F58: FORTSMAQ COMER DE FERRAMENTAS EIRELI | G58: 30000 | H58: 20/45/60/80/100 | I58: 44555 | J58: 6000 | K58: 44575 | L58: 6000 | M58: 44595 | N58: 6000 | O58: 44615 | P58: 6000 | Q58: 44635 | R58: 6000
A59: 44501 | B59: 44509 | C59: 017/017 | D59: MARTELUX | E59: MARCOS ROBERTO | F59: ALTAMIRO CANDIDO | G59: 1440 | H59: 30/60/90/120 | I59: 44540 | K59: 44571 | L59: 360 | M59: 44602 | N59: 360 | O59: 44630 | P59: 360
A60: 44501 | B60: 44509 | C60: 1262/1249 | D60: ZHEMAX | E60: MARCOS ROBERTO | F60: ALTAMIRO CANDIDO | G60: 1918 | H60: 30/60/90/120 | I60: 44540 | K60: 44571 | L60: 479.5 | M60: 44602 | N60: 479.5 | O60: 44630 | P60: 479.5
A61: 44501 | B61: 44516 | C61: 2894/2419 | D61: CAIYA | E61: MARCOS ROBERTO | F61: ALTAMIRO CANDIDO | G61: 2904 | H61: 30/60 | I61: 44547 | K61: 44578 | L61: 1452
A62: 44501 | B62: 44519 | C62: 2900/2425 | D62: CAIYA | E62: ADEMIR MOLINA | F62: CRISTINA GUEDES DA SILVA | G62: 10468.8 | H62: 30/60/90 | I62: 44557 | J62: 3489.6 | K62: 44588 | L62: 3489.6 | M62: 44619 | N62: 3489.6
A63: 44501 | B63: 44519 | C63: 1276/1266 | D63: ZHEMAX | E63: ADEMIR MOLINA | F63: CRISTINA GUEDES DA SILVA | G63: 10799.88 | H63: 30/60/90 | I63: 44555 | J63: 3599.96 | K63: 44586 | L63: 3599.96 | M63: 44617 | N63: 3599.96
A64: 44501 | B64: 44523 | C64: 027/028 | D64: MARTELUX | E64: MARCOS ROBERTO | F64: ALTAMIRO CANDIDO | G64: 888 | H64: 30/60/90 | I64: 44557 | K64: 44588 | L64: 296 | M64: 44619 | N64: 296
A65: 44501 | B65: 44523 | C65: 043/039 | D65: NORTE TOOLS | E65: MARCOS ROBERTO | F65: ALTAMIRO CANDIDO | G65: 870 | H65: 30/60/90 | I65: 44557 | K65: 44588 | L65: 290 | M65: 44619 | N65: 290
A66: 44501 | B66: 44505 | C66: 033/028 | D66: NORTE TOOLS | E66: FELIPE GOMES | F66: ANA CAROLINA DE MELO INACIO | G66: 14494.81 | H66: 30/60/90/120 | I66: 44535 | J66: 3623.7 | K66: 44566 | M66: 44597 | N66: 3623.7 | O66: 44625 | P66: 3623.71
A67: 44501 | B67: 44509 | C67: 2806/2240 | D67: DEYUN | E67: MARCOS ROBERTO | F67: ALTAMIRO CANDIDO | G67: 5940 | H67: 30/60/90/120 | I67: 44540 | K67: 44571 | M67: 44602 | N67: 1485 | O67: 44630 | P67: 1485
A68: 44501 | B68: 44512 | C68: 023/021 | D68: MARTELUX | E68: KFS CARDOSO | F68: KFS CARDOSO SERVIÇOS CONTABEIS E REPRESENTACOES | G68: 392 | H68: 60 D | I68: 44573 | J68: 392
A69: 44501 | B69: 44522 | C69: 47101/537 | D69: COMPBRASIL | E69: FELIPE GOMES | F69: ANA CAROLINA DE MELO INACIO | G69: 4212 | H69: 30/60/90 | I69: 44553 | K69: 44584 | M69: 44615 | N69: 1404
A70: 44501 | B70: 44523 | C70: 1284/1267 | D70: ZHEMAX | E70: MARCOS ROBERTO | F70: ALTAMIRO CANDIDO | G70: 3356.1 | H70: 30/60/90/120 | I70: 44557 | J70: 839.02 | K70: 44588 | M70: 44619 | N70: 839.02 | O70: 44647 | P70: 839.04
A71: 44531 | B71: 44538 | C71: 046/042 | D71: NORTE TOOLS | E71: FELIPE GOMES | F71: MARCOS CIRILO DA SILVA | G71: 2175 | H71: 30/60/90 | I71: 44576 | J71: 725 | K71: 44607 | L71: 725 | M71: 44635 | N71: 725
A72: 44531 | B72: 44537 | C72: 1302/1287 | D72: ZHEMAX | E72: FELIPE GOMES | F72: MARCOS CIRILO DA SILVA | G72: 5640.05 | H72: 30/60/90 | I72: 44568 | J72: 1880.02 | K72: 44599 | L72: 1880.02 | M72: 44627 | N72: 1880.01
A73: 2021年合计 | B73: 2021年 | G73: =SUBTOTAL(9,G10:G72) -> 617595.62 | J73: =SUBTOTAL(9,J10:J72) -> 99678.96 | L73: =SUBTOTAL(9,L10:L72) -> 89565.03 | N73: =SUBTOTAL(9,N10:N72) -> 113087.99 | P73: =SUBTOTAL(9,P10:P72) -> 56421.15 | R73: =SUBTOTAL(9,R10:R72) -> 40771.29 | T73: =SUBTOTAL(9,T10:T72) -> 16968.46 | V73: =SUBTOTAL(9,V10:V72) -> 10674.63 | X73: =SUBTOTAL(9,X10:X72) -> 1944 | Y73: =SUBTOTAL(9,Y10:Y72) -> 0 | Z73: =SUBTOTAL(9,Z10:Z72) -> 0
A74: 44562 | B74: 44572 | C74: 055/047 | D74: NORTE TOOLS | E74: MARCOS ROBERTO | F74: ALTAMIRO CANDIDO | G74: 2734 | H74: 30/60/90/120 | I74: 44603 | J74: 683.5 | K74: 44631 | L74: 683.5 | M74: 44662 | N74: 683.5 | O74: 44692 | P74: 683.5 | Y74: =J74+L74+N74+P74+R74+T74+V74+X74 -> 2734 | Z74: =G74-Y74 -> 0
A75: 44562 | B75: 44566 | C75: 1323/1308 | D75: ZHEMAX | E75: MARCOS ROBERTO | F75: ALTAMIRO CANDIDO | G75: 830 | H75: 30/60/90 | I75: 44603 | J75: 276.67 | K75: 44631 | L75: 276.67 | M75: 44662 | N75: 276.66 | Y75: =J75+L75+N75+P75+R75+T75+V75+X75 -> 830 | Z75: =G75-Y75 -> 0
A76: 44562 | B76: 44578 | C76: 1333/1315 | D76: ZHEMAX | E76: ADEMIR MOLINA | F76: M V D DA SILVA EIRELI | G76: 3321.6 | H76: 30/60/90 | I76: 44613 | J76: 1107.2 | K76: 44641 | L76: 1107.2 | M76: 44672 | N76: 1107.2 | Y76: =J76+L76+N76+P76+R76+T76+V76+X76 -> 3321.6 | Z76: =G76-Y76 -> 0
A77: 44562 | B77: 44580 | C77: 052/051 | D77: MARTELUX | E77: MARCOS ROBERTO | F77: ALTAMIRO CANDIDO | G77: 1800 | H77: 30/60 | I77: 44611 | J77: 900 | K77: 44639 | L77: 900 | Y77: =J77+L77+N77+P77+R77+T77+V77+X77 -> 1800 | Z77: =G77-Y77 -> 0
A78: 44562 | B78: 44580 | C78: 2926/2453 | D78: CAIYA | E78: MARCOS ROBERTO | F78: ALTAMIRO CANDIDO | G78: 2815 | H78: 30/60/90/120 | I78: 44611 | J78: 703.75 | K78: 44639 | L78: 703.75 | M78: 44670 | N78: 703.75 | O78: 44700 | P78: 703.75 | Y78: =J78+L78+N78+P78+R78+T78+V78+X78 -> 2815 | Z78: =G78-Y78 -> 0
A79: 44562 | B79: 44580 | C79: 1335/1318 | D79: ZHEMAX | E79: MARCOS ROBERTO | F79: ALTAMIRO CANDIDO | G79: 4263.1 | H79: 30/60/90/120 | I79: 44611 | J79: 1065.78 | K79: 44639 | L79: 1065.78 | M79: 44670 | N79: 1065.78 | O79: 44700 | P79: 1065.76 | Y79: =J79+L79+N79+P79+R79+T79+V79+X79 -> 4263.1 | Z79: =G79-Y79 -> 0
A80: 44562 | B80: 44578 | C80: 049/056 | D80: MARTELUX | E80: ADEMIR MOLINA | F80: M V D DA SILVA EIRELI | G80: 1408 | H80: 30/60/90 | I80: 44620 | J80: 469.33 | K80: 44648 | L80: 469.33 | M80: 44679 | N80: 469.34 | Y80: =J80+L80+N80+P80+R80+T80+V80+X80 -> 1408 | Z80: =G80-Y80 -> 0
A81: 44562 | B81: 44592 | C81: 1348/1332 | D81: ZHEMAX | E81: ADEMIR MOLINA | F81: M V D DA SILVA EIRELI | G81: 4982.4 | H81: 30/60/90 | I81: 44622 | J81: 1660.8 | K81: 44653 | L81: 1660.8 | M81: 44683 | N81: 1660.8 | Y81: =J81+L81+N81+P81+R81+T81+V81+X81 -> 4982.4 | Z81: =G81-Y81 -> 0
A82: 44593 | B82: 44574 | C82: 58/63 | D82: NORTE TOOLS | E82: ADEMIR MOLINA | F82: EDVALDO JULIO DOS SANTOS | G82: 2900 | H82: 30/60/90 | I82: 44640 | J82: 966.67 | K82: 44671 | L82: 966.67 | M82: 44701 | N82: 966.67 | Y82: =J82+L82+N82+P82+R82+T82+V82+X82 -> 2900.01 | Z82: =G82-Y82 -> -0.01
A83: 44593 | B83: 44609 | C83: 74/65 | D83: NORTE TOOLS | E83: ADEMIR MOLINA | F83: EDVALDO JULIO DOS SANTOS | G83: 8571.2 | H83: 30/60/90 | I83: 44640 | J83: 2857.07 | K83: 44671 | L83: 2857.07 | M83: 44701 | N83: 2857.07 | Y83: =J83+L83+N83+P83+R83+T83+V83+X83 -> 8571.21 | Z83: =G83-Y83 -> -0.01
A84: 44593 | B84: 44613 | C84: 76/67 | D84: NORTE TOOLS | E84: ADEMIR MOLINA | F84: MARIA DENISE SANTOS | G84: 3939.2 | H84: 30/60/90 | I84: 44644 | J84: 1313.07 | K84: 44675 | L84: 1313.07 | M84: 44705 | N84: 1313.07 | Y84: =J84+L84+N84+P84+R84+T84+V84+X84 -> 3939.21 | Z84: =G84-Y84 -> -0.01
A85: 44593 | B85: 44574 | C85: 45/63 | D85: MARTELUX | E85: ADEMIR MOLINA | F85: M V D DA SILVA | G85: 1408 | H85: 30/60/90 | I85: 44627 | J85: 469.33 | K85: 44658 | L85: 469.33 | M85: 44688 | N85: 469.34 | Y85: =J85+L85+N85+P85+R85+T85+V85+X85 -> 1408 | Z85: =G85-Y85 -> 0
A86: 44593 | B86: 44607 | C86: 70/70 | D86: MARTELUX | E86: ADEMIR MOLINA | F86: M V D DA SILVA | G86: 1408 | H86: 30/60/90 | I86: 44635 | J86: 469.33 | K86: 44666 | L86: 469.33 | M86: 44696 | N86: 469.34 | Y86: =J86+L86+N86+P86+R86+T86+V86+X86 -> 1408 | Z86: =G86-Y86 -> 0
A87: 44593 | B87: 44607 | C87: 2872/2315 | D87: DEYUN | E87: ADEMIR MOLINA | F87: EDVALDO JULIO DOS SANTOS | G87: 5536 | H87: 30/60/90 | I87: 44640 | J87: 1845.33 | K87: 44671 | L87: 1845.33 | M87: 44701 | N87: 1845.34 | Y87: =J87+L87+N87+P87+R87+T87+V87+X87 -> 5536 | Z87: =G87-Y87 -> 0
A88: 44593 | B88: 44609 | C88: 53701/610 | D88: COMPBRASIL | E88: ADEMIR MOLINA | F88: EDVALDO JULIO DOS SANTOS | G88: 1200 | H88: 30/60/90 | I88: 44640 | J88: 400 | K88: 44671 | L88: 400 | M88: 44701 | N88: 400 | Y88: =J88+L88+N88+P88+R88+T88+V88+X88 -> 1200 | Z88: =G88-Y88 -> 0
A89: 44593 | B89: 44609 | C89: 1368/1355 | D89: ZHEMAX | E89: ADEMIR MOLINA | F89: EDVALDO JULIO DOS SANTOS | G89: 1645.68 | H89: 30/60/90 | I89: 44640 | J89: 548.56 | K89: 44671 | L89: 548.56 | M89: 44701 | N89: 548.56 | Y89: =J89+L89+N89+P89+R89+T89+V89+X89 -> 1645.68 | Z89: =G89-Y89 -> 0
A90: 44593 | B90: 44613 | C90: 1372/1360 | D90: ZHEMAX | E90: ADEMIR MOLINA | F90: MARIA DENISE SANTOS | G90: 3371.84 | H90: 30/60/90 | I90: 44644 | J90: 1123.95 | K90: 44675 | L90: 1123.95 | M90: 44705 | N90: 1123.95 | Y90: =J90+L90+N90+P90+R90+T90+V90+X90 -> 3371.85 | Z90: =G90-Y90 -> -0.01
A91: 44621 | B91: 44623 | C91: 80/68 | D91: NORTE TOOLS | E91: ADEMIR MOLINA | F91: MARIA DENISE SANTOS | G91: 3939.2 | H91: 30/60/90 | I91: 44654 | J91: 1313.07 | K91: 44684 | L91: 1313.07 | M91: 44715 | N91: 1313.07 | Y91: =J91+L91+N91+P91+R91+T91+V91+X91 -> 3939.21 | Z91: =G91-Y91 -> -0.01
... A94: 44621 | B94: 44627 | C94: 2888/2331 | D94: DEYUN | E94: ADEMIR MOLINA | F94: M V D DA SILVA EIRELI | G94: 4428.8 | H94: 30/60/90 | I94: 44658 | J94: 1476.27 | K94: 44688 | L94: 1476.27 | M94: 44719 | N94: 1476.27 | Y94: =J94+L94+N94+P94+R94+T94+V94+X94 -> 4428.81 | Z94: =G94-Y94 -> -0.01
A95: 44621 | B95: 44631 | C95: 55301/625 | D95: COMPBRASIL | E95: EVIDENCE | F95: ESPAÇO SOLDA COMERCIO E SERVIÇOS EIRELI | G95: 4290 | H95: 30/45/60/5/90 | I95: 44666 | K95: 44681 | L95: 858 | M95: 44696 | O95: 44711 | Q95: 44727 | R95: 858 | Y95: =J95+L95+N95+P95+R95+T95+V95+X95 -> 1716 | Z95: =G95-Y95 -> 2574
A96: 44621 | B96: 44636 | C96: 1392/1384 | D96: ZHEMAX | E96: FELIPE GOMES | F96: CONQUISTAR COMERCIAL DE PECAS LIMITDA | G96: 4956.9 | H96: 30/60/90/120 | I96: 44675 | J96: 1239.22 | K96: 44705 | L96: 1239.22 | M96: 44736 | N96: 1239.22 | O96: 44766 | P96: 1239.24 | Y96: =J96+L96+N96+P96+R96+T96+V96+X96 -> 4956.9 | Z96: =G96-Y96 -> 0
A97: 44621 | B97: 44631 | C97: 55401/633 | D97: COMPBRASIL | E97: FELIPE GOMES | F97: CONQUISTAR COMERCIAL DE PECAS LIMITDA | G97: 4508.4 | H97: 30/60/90/120 | I97: 44675 | J97: 1127.1 | K97: 44705 | L97: 1127.1 | M97: 44736 | N97: 1127.1 | O97: 44766 | P97: 1127.1 | Y97: =J97+L97+N97+P97+R97+T97+V97+X97 -> 4508.4 | Z97: =G97-Y97 -> 0
A98: 44621 | B98: 44631 | C98: 2899/2343 | D98: DEYUN | E98: FELIPE GOMES | F98: CONQUISTAR COMERCIAL DE PECAS LIMITDA | G98: 6408.8 | H98: 30/60/90/120 | I98: 44675 | J98: 1602.2 | K98: 44705 | L98: 1602.2 | M98: 44736 | N98: 1602.2 | O98: 44766 | P98: 1602.2 | Y98: =J98+L98+N98+P98+R98+T98+V98+X98 -> 6408.8 | Z98: =G98-Y98 -> 0
A99: 44621 | B99: 44650 | C99: 95/95 | D99: MARTELUX | E99: FELIPE GOMES | F99: M DE L DE SOUSA DOS SANTOS MATERIAIS DE CONTRUCAO | G99: 5600 | H99: 30/60/90 | I99: 44681 | K99: 44711 | L99: 1866.67 | M99: 44742 | Y99: =J99+L99+N99+P99+R99+T99+V99+X99 -> 1866.67 | Z99: =G99-Y99 -> 3733.33
A100: 44652 | B100: 44657 | C100: 105/100 | D100: MARTELUX | E100: FELIPE GOMES | F100: FRANCISCA MARIA DA CONCEIÇAO | G100: 5758.75 | H100: 30/60/90/120 | I100: 44687 | K100: 44718 | L100: 1439.69 | M100: 44748 | O100: 44779 | Y100: =J100+L100+N100+P100+R100+T100+V100+X100 -> 1439.69 | Z100: =G100-Y100 -> 4319.06
A101: 44652 | B101: 44657 | C101: 109/105 | D101: MARTELUX | E101: FELIPE GOMES | F101: FRANCISCA MARIA DA CONCEIÇAO | G101: 1853.55 | H101: 30/60 | I101: 44688 | J101: 926.77 | K101: 44719 | L101: 926.78 | Y101: =J101+L101+N101+P101+R101+T101+V101+X101 -> 1853.55 | Z101: =G101-Y101 -> 0
A102: 44652 | B102: 44659 | C102: 58701/650 | D102: COMPBRASIL | E102: MARCOS ROBERTO | F102: COMERCIAL DE PEÇAS OLIVEIRA E SILVA EIRELI | G102: 4950 | H102: 30/60/90/120 | I102: 44689 | J102: 1237.5 | K102: 44720 | L102: 1237.5 | M102: 44750 | N102: 1237.5 | O102: 44781 | P102: 1237.5 | Y102: =J102+L102+N102+P102+R102+T102+V102+X102 -> 4950 | Z102: =G102-Y102 -> 0
...
